Workbook

Sheet 工业富联资产负债表
A1: 报表日期 | B1: 20240331 | C1: 20231231 | D1: 20230930 | E1: 20230630 | F1: 20230331 | G1: 20221231 | H1: 20220930 | I1: 20220630 | J1: 20220331 | K1: 20211231 | L1: 20201231 | M1: 20191231 | N1: 20181231 | O1: 20171231 | P1: 20161231 | Q1: TRIBB2023YE-2016YE | S1: DIFF
A2: 单位 | B2: 元 | C2: 元 | D2: 元 | E2: 元 | F2: 元 | G2: 元 | H2: 元 | I2: 元 | J2: 元 | K2: 元 | L2: 元 | M2: 元 | N2: 元 | O2: 元 | P2: 元
A3: 流动资产
A4: 货币资金 | B4: 79893620000 | C4: 83462320000 | D4: 79826634000 | E4: 83703809000 | F4: 80248318000 | G4: 69429837000 | H4: 71692576000 | I4: 78115190000 | J4: 82168597000 | K4: 82877051000 | L4: 78056602000 | M4: 66901133000 | N4: 62293132000 | O4: 15518982000 | P4: 4934544000 | Q4: =C4-P4 -> 78527776000
A5: 交易性金融资产 | B5: 313304000 | C5: 333260000 | D5: 0 | E5: 0 | F5: 0 | G5: 0 | H5: 0 | I5: 0 | J5: 0 | K5: 0 | L5: 0 | M5: 0 | N5: 0 | O5: 0 | P5: 0 | Q5: =C5-P5 -> 333260000
A6: 衍生金融资产 | B6: 0 | C6: 279394000 | D6: 6960000 | E6: 10175000 | F6: 255506000 | G6: 15621000 | H6: 291102000 | I6: 42482000 | J6: 157545000 | K6: 246014000 | L6: 467888000 | M6: 157110000 | N6: 0 | O6: 0 | P6: 0 | Q6: =C6-P6 -> 279394000
A7: 应收票据及应收账款8+9 | B7: 81203806000 | C7: 88474241000 | D7: 79960512000 | E7: 74337688000 | F7: 65344050000 | G7: 97689782000 | H7: 107622529000 | I7: 89511871000 | J7: 76644056000 | K7: 87033843000 | L7: 86827595000 | M7: 84643735000 | N7: 86117905000 | O7: 78513196000 | P7: 54573777000
A8: 应收票据 | B8: 12170000 | C8: 7375000 | D8: 2597000 | E8: 4105000 | F8: 5026000 | G8: 16862000 | H8: 23024000 | I8: 15409000 | J8: 5416000 | K8: 4146000 | L8: 100000 | M8: 0 | N8: 923000 | O8: 0 | P8: 0 | Q8: =C8-P8 -> 7375000
A9: 应收账款 | B9: 81191636000 | C9: 88466866000 | D9: 79957915000 | E9: 74333583000 | F9: 65339024000 | G9: 97672920000 | H9: 107599505000 | I9: 89496462000 | J9: 76638640000 | K9: 87029697000 | L9: 86827495000 | M9: 84643735000 | N9: 86116982000 | O9: 78513196000 | P9: 54573777000 | Q9: =C9-P9 -> 33893089000
A10: 应收款项融资 | B10: 0 | C10: 0 | D10: 0 | E10: 0 | F10: 0 | G10: 0 | H10: 0 | I10: 0 | J10: 0 | K10: 0 | L10: 0 | M10: 0 | N10: 0 | O10: 0 | P10: 0 | Q10: =C10-P10 -> 0
A11: 预付款项 | B11: 339159000 | C11: 254708000 | D11: 519815000 | E11: 452718000 | F11: 698360000 | G11: 352362000 | H11: 356090000 | I11: 258772000 | J11: 482126000 | K11: 241612000 | L11: 171467000 | M11: 228837000 | N11: 215215000 | O11: 162513000 | P11: 113861000 | Q11: =C11-P11 -> 140847000
A12: 其他应收款(合计)13+14+15 | B12: 834175000 | C12: 853454000 | D12: 1224739000 | E12: 1213150000 | F12: 1153116000 | G12: 1878878000 | H12: 1009895000 | I12: 2045949000 | J12: 2533516000 | K12: 2516749000 | L12: 395724000 | M12: 455959000 | N12: 1354727000 | O12: 3094712000 | P12: 32600874000
A13: 应收利息 | B13: 0 | C13: 0 | D13: 0 | E13: 0 | F13: 0 | G13: 0 | H13: 0 | I13: 0 | J13: 0 | K13: 0 | L13: 0 | M13: 0 | N13: 166075000 | O13: 0 | P13: 0 | Q13: =C13-P13 -> 0
A14: 应收股利 | B14: 0 | C14: 0 | D14: 0 | E14: 0 | F14: 0 | G14: 0 | H14: 0 | I14: 0 | J14: 0 | K14: 0 | L14: 0 | M14: 0 | N14: 0 | O14: 0 | P14: 0 | Q14: =C14-P14 -> 0
A15: 其他应收款 | B15: 0 | C15: 853454000 | D15: 0 | E15: 1213150000 | F15: 0 | G15: 1878878000 | H15: 0 | I15: 0 | J15: 0 | K15: 2516749000 | L15: 395724000 | M15: 455959000 | N15: 1223171000 | O15: 3094712000 | P15: 32600874000 | Q15: =C15-P15 -> -31747420000
A16: 买入返售金融资产 | B16: 0 | C16: 0 | D16: 0 | E16: 0 | F16: 0 | G16: 0 | H16: 0 | I16: 0 | J16: 0 | K16: 0 | L16: 0 | M16: 0 | N16: 0 | O16: 0 | P16: 0 | Q16: =C16-P16 -> 0
A17: 存货 | B17: 76456995000 | C17: 76683349000 | D17: 76646324000 | E17: 73334293000 | F17: 74633908000 | G17: 77321754000 | H17: 81058282000 | I17: 81427381000 | J17: 76608642000 | K17: 71927837000 | L17: 45353900000 | M17: 41645951000 | N17: 37467635000 | O17: 35551035000 | P17: 28561440000 | Q17: =C17-P17 -> 48121909000
A18: 划分为持有待售的资产（合同资产） | B18: 0 | C18: 0 | D18: 0 | E18: 0 | F18: 0 | G18: 0 | H18: 0 | I18: 0 | J18: 0 | K18: 0 | L18: 0 | M18: 0 | N18: 0 | O18: 0 | P18: 0 | Q18: =C18-P18 -> 0
A19: 一年内到期的非流动资产 | B19: 0 | C19: 0 | D19: 0 | E19: 0 | F19: 10000000 | G19: 10000000 | H19: 41598000 | I19: 41598000 | J19: 31517000 | K19: 31518000 | L19: 0 | M19: 0 | N19: 0 | O19: 0 | P19: 0 | Q19: =C19-P19 -> 0
A20: 待摊费用 | B20: 0 | C20: 0 | D20: 0 | E20: 0 | F20: 0 | G20: 0 | H20: 0 | I20: 0 | J20: 0 | K20: 0 | L20: 0 | M20: 0 | N20: 0 | O20: 0 | P20: 0 | Q20: =C20-P20 -> 0
A21: 待处理流动资产损益 | B21: 0 | C21: 0 | D21: 0 | E21: 0 | F21: 0 | G21: 0 | H21: 0 | I21: 0 | J21: 0 | K21: 0 | L21: 0 | M21: 0 | N21: 0 | O21: 0 | P21: 0 | Q21: =C21-P21 -> 0
A22: 其他流动资产 | B22: 2186413000 | C22: 2137731000 | D22: 2055411000 | E22: 2046238000 | F22: 1989539000 | G22: 2241624000 | H22: 2235380000 | I22: 1905421000 | J22: 2323427000 | K22: 2283751000 | L22: 1980764000 | M22: 1657398000 | N22: 2478701000 | O22: 3830059000 | P22: 1132571000 | Q22: =C22-P22 -> 1005160000
A23: 流动资产合计 | B23: 241227472000 | C23: 252478457000 | D23: 240240395000 | E23: 235098071000 | F23: 224332797000 | G23: 248939858000 | H23: 264307452000 | I23: 253348664000 | J23: 240949426000 | K23: 247158375000 | L23: 213253940000 | M23: 195690123000 | N23: 189927315000 | O23: 136670497000 | P23: 121917067000 | Q23: =C23-P23 -> 130561390000 | R23: =SUM(Q4:Q22) -> 130561390000 | S23: =Q23-R23 -> 0
A24: 非流动资产 | Q24: =C24-P24 -> 0
A25: 发放贷款及垫款 | B25: 0 | C25: 0 | D25: 0 | E25: 0 | F25: 0 | G25: 0 | H25: 0 | I25: 0 | J25: 0 | K25: 0 | L25: 0 | M25: 0 | N25: 0 | O25: 0 | P25: 0 | Q25: =C25-P25 -> 0
A26: 可供出售金融资产（其他权益工具投资） | B26: 0 | C26: =742863*1000 -> 742863000 | D26: 0 | E26: 0 | F26: 0 | G26: =388257*1000 -> 388257000 | H26: 0 | I26: 0 | J26: 0 | K26: =128747*1000 -> 128747000 | L26: 0 | M26: 0 | N26: 40760000 | O26: 3000000 | P26: 46392000 | Q26: =C26-P26 -> 696471000
A27: 持有至到期投资（其他非流动金融资产） | B27: 0 | C27: 0 | D27: 0 | E27: 0 | F27: 0 | G27: 0 | H27: 0 | I27: 0 | J27: 0 | K27: 0 | L27: 0 | M27: 0 | N27: 0 | O27: 0 | P27: 0 | Q27: =C27-P27 -> 0
A28: 长期应收款（债权投资） | B28: 62982000 | C28: 62982000 | D28: 0 | E28: 0 | F28: 0 | G28: 0 | H28: 0 | I28: 0 | J28: 0 | K28: 0 | L28: 0 | M28: 0 | N28: 0 | O28: 0 | P28: 0 | Q28: =C28-P28 -> 62982000
A29: 长期股权投资 | B29: 6156265000 | C29: 7179747000 | D29: 6928598000 | E29: 9084440000 | F29: 9488334000 | G29: 12215696000 | H29: 12205474000 | I29: 12182997000 | J29: 3164642000 | K29: 3167922000 | L29: 1167690000 | M29: 533446000 | N29: 393664000 | O29: 0 | P29: 37500000 | Q29: =C29-P29 -> 7142247000
A30: 投资性房地产 | B30: 0 | C30: 0 | D30: 0 | E30: 0 | F30: 0 | G30: 0 | H30: 0 | I30: 0 | J30: 0 | K30: 0 | L30: 0 | M30: 0 | N30: 0 | O30: 0 | P30: 19820000 | Q30: =C30-P30 -> -19820000
A31: 在建工程(合计)32+33 | B31: 2453239000 | C31: 2508056000 | D31: 1558865000 | E31: 950122000 | F31: 791864000 | G31: 701408000 | H31: 1943146000 | I31: 1059779000 | J31: 1423164000 | K31: 1414692000 | L31: 643821000 | M31: 445902000 | N31: 501073000 | O31: 727529000 | P31: 0
A32: 在建工程 | B32: 0 | C32: 2508056000 | D32: 0 | E32: 950122000 | F32: 0 | G32: 701408000 | H32: 0 | I32: 1059779000 | J32: 0 | K32: 1414692000 | L32: 643821000 | M32: 445902000 | N32: 501073000 | O32: 727529000 | P32: 545608000 | Q32: =C32-P32 -> 1962448000
A33: 工程物资 | B33: 0 | C33: 0 | D33: 0 | E33: 0 | F33: 0 | G33: 0 | H33: 0 | I33: 0 | J33: 0 | K33: 0 | L33: 0 | M33: 0 | N33: 0 | O33: 0 | P33: 0 | Q33: =C33-P33 -> 0
A34: 固定资产及清理(合计)35+36 | B34: 18224552000 | C34: 17711566000 | D34: 15895580000 | E34: 15439300000 | F34: 15944644000 | G34: 15937003000 | H34: 11858129000 | I34: 10719081000 | J34: 10028389000 | K34: 9493537000 | L34: 7123034000 | M34: 6644364000 | N34: 7596072000 | O34: 9032519000 | P34: 0
A35: 固定资产净额 | B35: =B34 -> 18224552000 | C35: 17711566000 | D35: 0 | E35: 15439300000 | F35: 0 | G35: 15937003000 | H35: 0 | I35: 10719081000 | J35: 0 | K35: 9493537000 | L35: 7123034000 | M35: 6644364000 | N35: 7596072000 | O35: 9032519000 | P35: 11359288000 | Q35: =C35-P35 -> 6352278000
A36: 固定资产清理 | B36: 0 | C36: 0 | D36: 0 | E36: 0 | F36: 0 | G36: 0 | H36: 0 | I36: 0 | J36: 0 | K36: 0 | L36: 0 | M36: 0 | N36: 0 | O36: 0 | P36: 0 | Q36: =C36-P36 -> 0
A37: 生产性生物资产 | B37: 0 | C37: 0 | D37: 0 | E37: 0 | F37: 0 | G37: 0 | H37: 0 | I37: 0 | J37: 0 | K37: 0 | L37: 0 | M37: 0 | N37: 0 | O37: 0 | P37: 0 | Q37: =C37-P37 -> 0
A38: 公益性生物资产 | B38: 0 | C38: 0 | D38: 0 | E38: 0 | F38: 0 | G38: 0 | H38: 0 | I38: 0 | J38: 0 | K38: 0 | L38: 0 | M38: 0 | N38: 0 | O38: 0 | P38: 0 | Q38: =C38-P38 -> 0
A39: 油气资产 | B39: 0 | C39: 0 | D39: 0 | E39: 0 | F39: 0 | G39: 0 | H39: 0 | I39: 0 | J39: 0 | K39: 0 | L39: 0 | M39: 0 | N39: 0 | O39: 0 | P39: 0 | Q39: =C39-P39 -> 0
A40: 使用权资产 | B40: 1895890000 | C40: 1571141000 | D40: 1699792000 | E40: 1808249000 | F40: 1975569000 | G40: 2077855000 | H40: 1999763000 | I40: 2013156000 | J40: 2020061000 | K40: 2119621000 | L40: 0 | M40: 0 | N40: 0 | O40: 0 | P40: 0 | Q40: =C40-P40 -> 1571141000
A41: 无形资产 | B41: 1443770000 | C41: 1004412000 | D41: 537871000 | E41: 520887000 | F41: 449118000 | G41: 440305000 | H41: 454768000 | I41: 432764000 | J41: 431860000 | K41: 407013000 | L41: 405317000 | M41: 185727000 | N41: 196982000 | O41: 225285000 | P41: 244349000 | Q41: =C41-P41 -> 760063000
A42: 开发支出 | B42: 0 | C42: 0 | D42: 0 | E42: 0 | F42: 0 | G42: 0 | H42: 0 | I42: 0 | J42: 0 | K42: 0 | L42: 0 | M42: 0 | N42: 0 | O42: 0 | P42: 0 | Q42: =C42-P42 -> 0
A43: 商誉 | B43: 310153000 | C43: 310153000 | D43: 310153000 | E43: 310153000 | F43: 310153000 | G43: 310153000 | H43: 310153000 | I43: 310153000 | J43: 311199000 | K43: 0 | L43: 0 | M43: 0 | N43: 0 | O43: 0 | P43: 0 | Q43: =C43-P43 -> 310153000
A44: 长期待摊费用 | B44: 2646913000 | C44: 2666774000 | D44: 2160105000 | E44: 2123192000 | F44: 1780682000 | G44: 1744506000 | H44: 1568050000 | I44: 1382381000 | J44: 1246550000 | K44: 1255753000 | L44: 935728000 | M44: 664612000 | N44: 549145000 | O44: 341073000 | P44: 231185000 | Q44: =C44-P44 -> 2435589000
A45: 递延所得税资产 | B45: 865472000 | C45: 777928000 | D45: 854754000 | E45: 983796000 | F45: 1023537000 | G45: 954625000 | H45: 1007681000 | I45: 1229704000 | J45: 1016545000 | K45: 1030287000 | L45: 1189043000 | M45: 1089906000 | N45: 1283248000 | O45: 1457368000 | P45: 1284652000 | Q45: =C45-P45 -> -506724000
A46: 其他非流动资产 | B46: 698701000 | C46: 691222000 | D46: 1109118000 | E46: 1116892000 | F46: 978745000 | G46: 477996000 | H46: 472908000 | I46: 495762000 | J46: 6897077000 | K46: 422828000 | L46: 400232000 | M46: 341937000 | N46: 115065000 | O46: 138970000 | P46: 57798000 | Q46: =C46-P46 -> 633424000
A47: 非流动资产合计 | B47: 35485870000 | C47: 35226844000 | D47: 32104603000 | E47: 33054191000 | F47: 33279208000 | G47: 35247804000 | H47: 32173179000 | I47: 30176510000 | J47: 26678171000 | K47: 19450400000 | L47: 12260004000 | M47: 9922822000 | N47: 10676009000 | O47: 11925744000 | P47: 13826592000 | Q47: =C47-P47 -> 21400252000 | R47: =SUM(Q25:Q46) -> 21400252000 | S47: =Q47-R47 -> 0
A48: 资产总计 | B48: 276713342000 | C48: 287705301000 | D48: 272344998000 | E48: 268152262000 | F48: 257612005000 | G48: 284187662000 | H48: 296480631000 | I48: 283525174000 | J48: 267627597000 | K48: 266608775000 | L48: 225513944000 | M48: 205612945000 | N48: 200603324000 | O48: 148596241000 | P48: 135743659000 | Q48: =C48-P48 -> 151961642000
A49: 流动负债 | Q49: =C49-P49 -> 0
A50: 短期借款 | B50: 34444881000 | C50: 41090899000 | D50: 39953132000 | E50: 37746929000 | F50: 40995873000 | G50: 50497692000 | H50: 65955322000 | I50: 63286117000 | J50: 57776278000 | K50: 52136654000 | L50: 44222934000 | M50: 28271285000 | N50: 22490216000 | O50: 6956799000 | P50: 1642918000 | Q50: =C50-P50 -> 39447981000
A51: 交易性金融负债 | B51: 0 | C51: =13133*1000 -> 13133000 | D51: 0 | E51: 0 | F51: 0 | G51: =102072*1000 -> 102072000 | H51: 0 | I51: 0 | J51: 0 | K51: =13889*1000 -> 13889000 | L51: 0 | M51: 0 | N51: 117000 | O51: 0 | P51: 0 | Q51: =C51-P51 -> 13133000
A52: 应付票据及应付账款53+54 | B52: 66759022000 | C52: 75028335000 | D52: 66854649000 | E52: 59904733000 | F52: 54001409000 | G52: 69278939000 | H52: 75570136000 | I52: 64133998000 | J52: 64326629000 | K52: 71986730000 | L52: 62244793000 | M52: 67321345000 | N52: 69730796000 | O52: 76809307000 | P52: 43012900000
A53: 应付票据 | B53: 0 | C53: 0 | D53: 0 | E53: 0 | F53: 0 | G53: 0 | H53: 150000000 | I53: 260000000 | J53: 0 | K53: 250000000 | L53: 100000000 | M53: 0 | N53: 0 | O53: 0 | P53: 0 | Q53: =C53-P53 -> 0
A54: 应付账款 | B54: 66759022000 | C54: 75028335000 | D54: 66854649000 | E54: 59904733000 | F54: 54001409000 | G54: 69278939000 | H54: 75420136000 | I54: 63873998000 | J54: 64326629000 | K54: 71736730000 | L54: 62144793000 | M54: 67321345000 | N54: 69730796000 | O54: 76809307000 | P54: 43012900000 | Q54: =C54-P54 -> 32015435000
A55: 预收款项 | B55: 0 | C55: 0 | D55: 0 | E55: 0 | F55: 0 | G55: 0 | H55: 0 | I55: 0 | J55: 0 | K55: 0 | L55: 0 | M55: 103398000 | N55: 57971000 | O55: 106272000 | P55: 184083000 | Q55: =C55-P55 -> -184083000
A56: 应付手续费及佣金（合同负债） | B56: 0 | C56: =190316*1000 -> 190316000 | D56: 0 | E56: 0 | F56: 0 | G56: =176680*1000 -> 176680000 | H56: 0 | I56: 0 | J56: 0 | K56: =112436*1000 -> 112436000 | L56: 0 | M56: 0 | N56: 0 | O56: 0 | P56: 0 | Q56: =C56-P56 -> 190316000
A57: 应付职工薪酬 | B57: 2668466000 | C57: 4324071000 | D57: 3754793000 | E57: 3078247000 | F57: 2993089000 | G57: 4954450000 | H57: 5918704000 | I57: 4235176000 | J57: 3869297000 | K57: 4889968000 | L57: 5106573000 | M57: 4973173000 | N57: 4382173000 | O57: 3011604000 | P57: 3515886000 | Q57: =C57-P57 -> 808185000
A58: 应交税费 | B58: 1813592000 | C58: 1662690000 | D58: 1675503000 | E58: 1036385000 | F58: 1232218000 | G58: 1237028000 | H58: 1363534000 | I58: 1024847000 | J58: 1342416000 | K58: 1865047000 | L58: 1967584000 | M58: 2322273000 | N58: 3079926000 | O58: 1298927000 | P58: 767639000 | Q58: =C58-P58 -> 895051000
A59: 其他应付款(合计)60+61+62 | B59: 13672575000 | C59: 14184970000 | D59: 11398996000 | E59: 23738869000 | F59: 13719284000 | G59: 16901025000 | H59: 14373852000 | I59: 23277213000 | J59: 9894717000 | K59: 8808538000 | L59: 6372910000 | M59: 12595820000 | N59: 27897455000 | O59: 32103714000 | P59: 8664545000
A60: 应付利息 | B60: 0 | C60: 0 | D60: 0 | E60: 0 | F60: 0 | G60: 0 | H60: 0 | I60: 0 | J60: 0 | K60: 0 | L60: 0 | M60: 16755000 | N60: 177411000 | O60: 0 | P60: 0 | Q60: =C60-P60 -> 0
A61: 应付股利 | B61: 126778000 | C61: 131036000 | D61: 0 | E61: 0 | F61: 0 | G61: 0 | H61: 0 | I61: 9890945000 | J61: 0 | K61: 0 | L61: 0 | M61: 0 | N61: 0 | O61: 0 | P61: 0 | Q61: =C61-P61 -> 131036000
A62: 其他应付款 | B62: 0 | C62: =C59-C61 -> 14053934000 | D62: 0 | E62: 23738869000 | F62: 0 | G62: 16901025000 | H62: 0 | I62: 13386268000 | J62: 0 | K62: 8808538000 | L62: 6372910000 | M62: 12579065000 | N62: 27720044000 | O62: 32103714000 | P62: 8664545000 | Q62: =C62-P62 -> 5389389000
A63: 预提费用 | B63: 0 | C63: 0 | D63: 0 | E63: 0 | F63: 0 | G63: 0 | H63: 0 | I63: 0 | J63: 0 | K63: 0 | L63: 0 | M63: 0 | N63: 0 | O63: 0 | P63: 0 | Q63: =C63-P63 -> 0
A64: 一年内的递延收益 | B64: 0 | C64: 0 | D64: 0 | E64: 0 | F64: 0 | G64: 0 | H64: 0 | I64: 0 | J64: 0 | K64: 0 | L64: 0 | M64: 0 | N64: 0 | O64: 0 | P64: 0 | Q64: =C64-P64 -> 0
A65: 应付短期债券 | B65: 0 | C65: 0 | D65: 0 | E65: 0 | F65: 0 | G65: 0 | H65: 0 | I65: 0 | J65: 0 | K65: 0 | L65: 0 | M65: 0 | N65: 0 | O65: 0 | P65: 0 | Q65: =C65-P65 -> 0
A66: 一年内到期的非流动负债 | B66: 4289545000 | C66: 668738000 | D66: 5199742000 | E66: 5315194000 | F66: 5155127000 | G66: 5266945000 | H66: 798352000 | I66: 1064649000 | J66: 917524000 | K66: 1052072000 | L66: 327000 | M66: 0 | N66: 0 | O66: 0 | P66: 0 | Q66: =C66-P66 -> 668738000
A67: 其他流动负债 | B67: 772300000 | C67: 881372000 | D67: 831009000 | E67: 926576000 | F67: 737844000 | G67: 760750000 | H67: 576155000 | I67: 619162000 | J67: 613103000 | K67: 463197000 | L67: 512496000 | M67: 385314000 | N67: 347193000 | O67: 95086000 | P67: 208205000 | Q67: =C67-P67 -> 673167000
A68: 流动负债合计 | B68: 124849910000 | C68: 138044524000 | D68: 129849297000 | E68: 132008796000 | F68: 119054347000 | G68: 149175581000 | H68: 165436734000 | I68: 157972904000 | J68: 138872630000 | K68: 141328531000 | L68: 120525212000 | M68: 115972608000 | N68: 127985847000 | O68: 120381709000 | P68: 57996176000 | Q68: =C68-P68 -> 80048348000 | R68: =SUM(Q50:Q67) -> 80048348000 | S68: =Q68-R68 -> 0
A69: 非流动负债 | Q69: =C69-P69 -> 0
A70: 长期借款 | B70: 3628177000 | C70: 7096943000 | D70: 7309835000 | E70: 7272758000 | F70: 4036392000 | G70: 3484507000 | H70: 7807071000 | I70: 7362632000 | J70: 3812059000 | K70: 3814347000 | L70: 225000 | M70: 0 | N70: 0 | O70: 0 | P70: 0 | Q70: =C70-P70 -> 7096943000
A71: 应付债券 | B71: 0 | C71: 0 | D71: 0 | E71: 0 | F71: 0 | G71: 0 | H71: 0 | I71: 0 | J71: 0 | K71: 0 | L71: 0 | M71: 0 | N71: 0 | O71: 0 | P71: 0 | Q71: =C71-P71 -> 0
A72: 租赁负债 | B72: 1212603000 | C72: 1010287000 | D72: 861126000 | E72: 834351000 | F72: 1010429000 | G72: 1069223000 | H72: 1247164000 | I72: 1011810000 | J72: 1132790000 | K72: 1187146000 | L72: 0 | M72: 0 | N72: 0 | O72: 0 | P72: 0 | Q72: =C72-P72 -> 1010287000
A73: 长期应付职工薪酬 | B73: 0 | C73: 0 | D73: 0 | E73: 0 | F73: 0 | G73: 0 | H73: 0 | I73: 0 | J73: 0 | K73: 0 | L73: 0 | M73: 0 | N73: 0 | O73: 0 | P73: 0 | Q73: =C73-P73 -> 0
A74: 长期应付款(合计)75+76 | B74: 0 | C74: 0 | D74: 0 | E74: 0 | F74: 0 | G74: 0 | H74: 0 | I74: 0 | J74: 0 | K74: 0 | L74: 0 | M74: 0 | N74: 0 | O74: 0 | P74: 0
A75: 长期应付款 | B75: 0 | C75: 0 | D75: 0 | E75: 0 | F75: 0 | G75: 0 | H75: 0 | I75: 0 | J75: 0 | K75: 0 | L75: 0 | M75: 0 | N75: 0 | O75: 0 | P75: 0 | Q75: =C75-P75 -> 0
A76: 专项应付款 | B76: 0 | C76: 0 | D76: 0 | E76: 0 | F76: 0 | G76: 0 | H76: 0 | I76: 0 | J76: 0 | K76: 0 | L76: 0 | M76: 0 | N76: 0 | O76: 0 | P76: 0 | Q76: =C76-P76 -> 0
A77: 预计非流动负债 | B77: 670272000 | C77: 473487000 | D77: 673073000 | E77: 687883000 | F77: 492948000 | G77: 498020000 | H77: 496540000 | I77: 453980000 | J77: 490456000 | K77: 437165000 | L77: 535305000 | M77: 189498000 | N77: 174549000 | O77: 24599000 | P77: 217457000 | Q77: =C77-P77 -> 256030000
A78: 递延所得税负债 | B78: 157120000 | C78: 204607000 | D78: 98172000 | E78: 77944000 | F78: 162750000 | G78: 270147000 | H78: 70781000 | I78: 29708000 | J78: 114319000 | K78: 50193000 | L78: 139197000 | M78: 83344000 | N78: 91305000 | O78: 0 | P78: 1539000 | Q78: =C78-P78 -> 203068000
A79: 长期递延收益 | B79: 341001000 | C79: 280118000 | D79: 303529000 | E79: 345257000 | F79: 331599000 | G79: 356678000 | H79: 291599000 | I79: 304712000 | J79: 306728000 | K79: 303703000 | L79: 273307000 | M79: 18804000 | N79: 6983000 | O79: 7345000 | P79: 5849000 | Q79: =C79-P79 -> 274269000
A80: 其他非流动负债 | B80: 0 | C80: 0 | D80: 0 | E80: 0 | F80: 0 | G80: 0 | H80: 0 | I80: 0 | J80: 0 | K80: 0 | L80: 0 | M80: 0 | N80: 0 | O80: 0 | P80: 0 | Q80: =C80-P80 -> 0
A81: 非流动负债合计 | B81: 6009173000 | C81: 9065442000 | D81: 9245735000 | E81: 9218193000 | F81: 6034118000 | G81: 5678575000 | H81: 9913155000 | I81: 9162842000 | J81: 5856352000 | K81: 5792554000 | L81: 948034000 | M81: 291646000 | N81: 272837000 | O81: 31944000 | P81: 224845000 | Q81: =C81-P81 -> 8840597000 | R81: =SUM(Q70:Q80) -> 8840597000 | S81: =Q81-R81 -> 0
A82: 负债合计 | B82: 130859083000 | C82: 147109966000 | D82: 139095032000 | E82: 141226989000 | F82: 125088465000 | G82: 154854156000 | H82: 175349889000 | I82: 167135746000 | J82: 144728982000 | K82: 147121085000 | L82: 121473246000 | M82: 116264254000 | N82: 128258684000 | O82: 120413653000 | P82: 58221021000 | Q82: =C82-P82 -> 88888945000
A83: 所有者权益 | Q83: =C83-P83 -> 0
A84: 实收资本(或股本) | B84: 19864027000 | C84: 19866106000 | D84: 19865842000 | E84: 19866455000 | F84: 19862894000 | G84: 19859593000 | H84: 19861035000 | I84: 19865104000 | J84: 19865104000 | K84: 19865070000 | L84: 19870646000 | M84: 19854832000 | N84: 19695300000 | O84: 17725770000 | P84: 0 | Q84: =C84-P84 -> 19866106000
A85: 资本公积 | B85: 29280830000 | C85: 29142633000 | D85: 28982966000 | E85: 28832946000 | F85: 28544667000 | G85: 28491199000 | H85: 28463097000 | I85: 28425306000 | J85: 28367798000 | K85: 28297428000 | L85: 27758040000 | M85: 26692249000 | N85: 25121959000 | O85: 0 | P85: 27823232000 | Q85: =C85-P85 -> 1319401000
A86: 减：库存股 | B86: 2000821000 | C86: 2013975000 | D86: 2029784000 | E86: 2043374000 | F86: 2207903000 | G86: 2207903000 | H86: 1655471000 | I86: 1238364000 | J86: 910965000 | K86: 518907000 | L86: 808531000 | M86: 942148000 | N86: 0 | O86: 0 | P86: 0 | Q86: =C86-P86 -> 2013975000
A87: 其他综合收益 | B87: 2244484000 | C87: 1325689000 | D87: 1683799000 | E87: 1877746000 | F87: 1097961000 | G87: 1088790000 | H87: 637803000 | I87: 439063000 | J87: 430794000 | K87: -17550000 | L87: 424914000 | M87: 628744000 | N87: 477370000 | O87: 337591000 | P87: 2822754000 | Q87: =C87-P87 -> -1497065000
A88: 专项储备 | B88: 0 | C88: 0 | D88: 0 | E88: 0 | F88: 0 | G88: 0 | H88: 0 | I88: 0 | J88: 0 | K88: 0 | L88: 0 | M88: 0 | N88: 0 | O88: 0 | P88: 0 | Q88: =C88-P88 -> 0
A89: 盈余公积 | B89: 5151191000 | C89: 5151191000 | D89: 3809459000 | E89: 3809459000 | F89: 3809459000 | G89: 3809459000 | H89: 2771638000 | I89: 2771638000 | J89: 2771638000 | K89: 2771638000 | L89: 1437435000 | M89: 740214000 | N89: 289183000 | O89: 0 | P89: 0 | Q89: =C89-P89 -> 5151191000
A90: 一般风险准备 | B90: 0 | C90: 0 | D90: 0 | E90: 0 | F90: 0 | G90: 0 | H90: 0 | I90: 0 | J90: 0 | K90: 0 | L90: 0 | M90: 0 | N90: 0 | O90: 0 | P90: 0 | Q90: =C90-P90 -> 0
A91: 未分配利润 | B91: 90900693000 | C91: 86715809000 | D91: 80501094000 | E91: 74177410000 | F91: 81062424000 | G91: 77934054000 | H91: 70694338000 | I91: 65770065000 | J91: 72038710000 | K91: 68782923000 | L91: 55070045000 | M91: 42306789000 | N91: 26710822000 | O91: 10097698000 | P91: 46657098000 | Q91: =C91-P91 -> 40058711000
A92: 归属于母公司股东权益合计 | B92: 145440404000 | C92: 140187453000 | D92: 132813376000 | E92: 126520642000 | F92: 132169502000 | G92: 128975192000 | H92: 120772440000 | I92: 116032812000 | J92: 122563079000 | K92: 119180602000 | L92: 103752549000 | M92: 89280680000 | N92: 72294634000 | O92: 28161059000 | P92: 77303084000 | Q92: =C92-P92 -> 62884369000 | R92: =SUM(Q84:Q85,Q87:Q91)-Q86 -> 62884369000 | S92: =Q92-R92 -> 0
A93: 少数股东权益 | B93: 413855000 | C93: 407882000 | D93: 436590000 | E93: 404631000 | F93: 354038000 | G93: 358314000 | H93: 358302000 | I93: 356616000 | J93: 335536000 | K93: 307088000 | L93: 288149000 | M93: 68011000 | N93: 50006000 | O93: 21529000 | P93: 219554000 | Q93: =C93-P93 -> 188328000
A94: 所有者权益(或股东权益)合计 | B94: 145854259000 | C94: 140595335000 | D94: 133249966000 | E94: 126925273000 | F94: 132523540000 | G94: 129333506000 | H94: 121130742000 | I94: 116389428000 | J94: 122898615000 | K94: 119487690000 | L94: 104040698000 | M94: 89348691000 | N94: 72344640000 | O94: 28182588000 | P94: 77522638000 | Q94: =C94-P94 -> 63072697000
A95: 负债和所有者权益(或股东权益)总计 | B95: 276713342000 | C95: 287705301000 | D95: 272344998000 | E95: 268152262000 | F95: 257612005000 | G95: 284187662000 | H95: 296480631000 | I95: 283525174000 | J95: 267627597000 | K95: 266608775000 | L95: 225513944000 | M95: 205612945000 | N95: 200603324000 | O95: 148596241000 | P95: 135743659000 | Q95: =C95-P95 -> 151961642000
A97: 实际资产负债率 | B97: =(B82-B79)/B95 -> 0.47167253 | C97: =(C82-C79)/C95 -> 0.51034808 | D97: =(D82-D79)/D95 -> 0.50961649 | E97: =(E82-E79)/E95 -> 0.52537961 | F97: =(F82-F79)/F95 -> 0.48428203 | G97: =(G82-G79)/G95 -> 0.54364597 | H97: =(H82-H79)/H95 -> 0.59045439 | I97: =(I82-I79)/I95 -> 0.58841701 | ... P97: =(P82-P79)/P95 -> 0.42886108
A98: FA&CIP占比资产总额 | B98: =(B31+B34)/B48 -> 0.074726397 | C98: =(C31+C34)/C48 -> 0.070278934 | D98: =(D31+D34)/D48 -> 0.064089464 | E98: =(E31+E34)/E48 -> 0.061119835 | F98: =(F31+F34)/F48 -> 0.064967888 | G98: =(G31+G34)/G48 -> 0.058547267 | H98: =(H31+H34)/H48 -> 0.046550343 | I98: =(I31+I34)/I48 -> 0.041544318 | J98: =(J32+J33+J35+J36)/J48 -> 0 | K98: =(K32+K33+K35+K36)/K48 -> 0.040914741 | L98: =(L32+L33+L35+L36)/L48 -> 0.034440686 | M98: =(M32+M33+M35+M36)/M48 -> 0.034483558 | N98: =(N32+N33+N35+N36)/N48 -> 0.040363962 | O98: =(O32+O33+O35+O36)/O48 -> 0.065681661 | P98: =(P32+P33+P35+P36)/P48 -> 0.087701305
A99: 商誉占比归属股东权益 | B99: =B43/B92 -> 0.0021325092 | C99: =C43/C92 -> 0.0022124163 | D99: =D43/D92 -> 0.0023352542 | E99: =E43/E92 -> 0.0024514024 | F99: =F43/F92 -> 0.0023466306 | G99: =G43/G92 -> 0.0024047493 | H99: =H43/H92 -> 0.0025680776 | I99: =I43/I92 -> 0.0026729767 | ... P99: =P43/P92 -> 0
A100: FA&CIP净额 | B100: =B98*B95 -> 20677791000 | C100: =C98*C95 -> 20219622000 | D100: =D98*D95 -> 17454445000 | E100: =E98*E95 -> 16389422000 | F100: =F98*F95 -> 16736508000 | G100: =G98*G95 -> 16638411000 | H100: =H98*H95 -> 13801275000 | I100: =I98*I95 -> 11778860000 | ... P100: =P98*P95 -> 11904896000
A101: FA&CIP净额-合计1 | B101: =SUM(B32,B33,B35,B36) -> 18224552000 | C101: =SUM(C32,C33,C35,C36) -> 20219622000 | D101: =SUM(D32,D33,D35,D36) -> 0 | E101: =SUM(E32,E33,E35,E36) -> 16389422000 | F101: =SUM(F32,F33,F35,F36) -> 0 | G101: =SUM(G32,G33,G35,G36) -> 16638411000 | H101: =SUM(H32,H33,H35,H36) -> 0 | I101: =SUM(I32,I33,I35,I36) -> 11778860000 | ... P101: =SUM(P32,P33,P35,P36) -> 11904896000
...

Sheet 工业富联利润表
A1: 报表日期 | B1: 20240331 | C1: 20231231 | D1: 20230930 | E1: 20230630 | F1: 20230331 | G1: 20221231 | H1: 20220930 | I1: 20220630 | J1: 20220331 | K1: 20211231 | L1: 20201231 | M1: 20191231 | N1: 20181231 | O1: 20171231 | P1: 2017-2023 | Q1: 2019-2023 | R1: 2021-2023
A2: 单位 | B2: 元 | C2: 元 | D2: 元 | E2: 元 | F2: 元 | G2: 元 | H2: 元 | I2: 元 | J2: 元 | K2: 元 | L2: 元 | M2: 元 | N2: 元 | O2: 元 | P2: 最近7年合计 | Q2: 最近5年合计 | R2: 最近3年合计
A3: 一、营业总收入 | B3: 118687964000 | C3: 476340107000 | D3: 328818385000 | E3: 206776498000 | F3: 105888545000 | G3: 511849579000 | H3: 361084106000 | I3: 225260378000 | J3: 105062471000 | K3: 439557195000 | L3: 431785888000 | M3: 408697581000 | N3: 415377697000 | O3: 354543851000 | P3: =SUM(L3:O3,D3,H3) -> 2300307508000 | Q3: =SUM(D3,H3,L3:N3) -> 1945763657000 | R3: =SUM(D3,H3,L3) -> 1121688379000
A4: 营业收入 | B4: 118687964000 | C4: 476340107000 | D4: 328818385000 | E4: 206776498000 | F4: 105888545000 | G4: 511849579000 | H4: 361084106000 | I4: 225260378000 | J4: 105062471000 | K4: 439557195000 | L4: 431785888000 | M4: 408697581000 | N4: 415377697000 | O4: 354543851000 | P4: =SUM(L4:O4,D4,H4) -> 2300307508000 | Q4: =SUM(D4,H4,L4:N4) -> 1945763657000 | R4: =SUM(D4,H4,L4) -> 1121688379000
A5: 二、营业总成本 | B5: 113234576000 | C5: 453820707000 | D5: 313596531000 | E5: 198288696000 | F5: 102143448000 | G5: 490934601000 | H5: 347406089000 | I5: 217764835000 | J5: 101379783000 | K5: 418699687000 | L5: 412871147000 | M5: 389038379000 | N5: 395496190000 | O5: 334966047000
A6: 营业成本 | B6: 109622336000 | C6: 437964301000 | D6: 302650356000 | E6: 191945898000 | F6: 98093623000 | G6: 474677783000 | H6: 336096546000 | I6: 210609058000 | J6: 97948614000 | K6: 403041967000 | L6: 395719226000 | M6: 374450968000 | N6: 379485979000 | O6: 318581972000 | P6: =SUM(L6:O6,D6,H6) -> 2106985047000 | Q6: =SUM(D6,H6,L6:N6) -> 1788403075000 | R6: =SUM(D6,H6,L6) -> 1034466128000
A7: 营业税金及附加 | B7: 85053000 | C7: 380730000 | D7: 308136000 | E7: 204191000 | F7: 136764000 | G7: 486119000 | H7: 389221000 | I7: 242448000 | J7: 132593000 | K7: 595884000 | L7: 723237000 | M7: 641577000 | N7: 456033000 | O7: 540014000
A8: 销售费用 | B8: 301506000 | C8: 1024450000 | D8: 799466000 | E8: 524382000 | F8: 322821000 | G8: 1057828000 | H8: 820356000 | I8: 530729000 | J8: 248784000 | K8: 896045000 | L8: 2124527000 | M8: 1732902000 | N8: 1791128000 | O8: 1792821000
A9: 管理费用 | B9: 1206625000 | C9: 4225829000 | D9: 2987833000 | E9: 1802602000 | F9: 850138000 | G9: 3828399000 | H9: 2896944000 | I9: 1816053000 | J9: 846458000 | K9: 4157148000 | L9: 4502723000 | M9: 3521068000 | N9: 4351957000 | O9: 12425666000
A10: 财务费用 | B10: -244218000 | C10: -585810000 | D10: -965866000 | E10: -1120327000 | F10: 298883000 | G10: -703542000 | H10: -1146199000 | I10: -540564000 | J10: -202689000 | K10: -826389000 | L10: -236295000 | M10: -735316000 | N10: -324098000 | O10: 855147000
A11: 研发费用 | B11: 2263274000 | C11: 10811207000 | D11: 7816606000 | E11: 4931950000 | F11: 2441219000 | G11: 11588014000 | H11: 8349221000 | I11: 5107111000 | J11: 2406023000 | K11: 10835032000 | L11: 10037729000 | M11: 9427180000 | N11: 8998879000 | O11: 0
A12: 资产减值损失 | B12: 0 | C12: 0 | D12: 0 | E12: 0 | F12: 0 | G12: 0 | H12: 0 | I12: 0 | J12: 0 | K12: 0 | L12: 0 | M12: 0 | N12: 736312000 | O12: 770427000 | P12: =SUM(L12:O12,D12,H12) -> 1506739000 | Q12: =SUM(D12,H12,L12:N12) -> 736312000 | R12: =SUM(D12,H12,L12) -> 0
A13: 公允价值变动收益 | B13: -438367000 | C13: 263599000 | D13: 16934000 | E13: -14540000 | F13: 183080000 | G13: -70113000 | H13: -242049000 | I13: 22470000 | J13: -10312000 | K13: -481483000 | L13: 312832000 | M13: 156692000 | N13: -115000 | O13: 0
A14: 投资收益 | B14: 138257000 | C14: -666115000 | D14: -865068000 | E14: -942925000 | F14: -545100000 | G14: 30264000 | H14: 48472000 | I14: 6536000 | J14: -6431000 | K14: 979147000 | L14: 329483000 | M14: 161460000 | N14: -420162000 | O14: 18100000 | P14: =SUM(L14:O14,D14,H14) -> -727715000 | Q14: =SUM(D14,H14,L14:N14) -> -745815000 | R14: =SUM(D14,H14,L14) -> -487113000
A15: 其中:对联营企业和合营企业的投资收益 | B15: 17029000 | C15: 252442000 | D15: 32432000 | E15: 23837000 | F15: -1005000 | G15: 2637000 | H15: -16285000 | I15: -17086000 | J15: -1397000 | K15: 14046000 | L15: 2233000 | M15: 2167000 | N15: -1672000 | O15: -10119000
A16: 汇兑收益 | B16: 0 | C16: 0 | D16: 0 | E16: 0 | F16: 0 | G16: 0 | H16: 0 | I16: 0 | J16: 0 | K16: 0 | L16: 0 | M16: 0 | N16: 0 | O16: 0
A17: 三、营业利润 | B17: 4758479000 | C17: 23066908000 | D17: 14591049000 | E17: 7681086000 | F17: 3434886000 | G17: 21872351000 | H17: 13176858000 | I17: 7521282000 | J17: 3677307000 | K17: 22397600000 | L17: 19715657000 | M17: 21106569000 | N17: 20082629000 | O17: 19957132000
A18: 加:营业外收入 | B18: 4372000 | C18: 123561000 | D18: 256613000 | E18: 49713000 | F18: 13974000 | G18: 121232000 | H18: 67805000 | I18: 55805000 | J18: 6979000 | K18: 83798000 | L18: 91955000 | M18: 85168000 | N18: 38100000 | O18: 88311000
A19: 减：营业外支出 | B19: 4885000 | C19: 66391000 | D19: 36237000 | E19: 22210000 | F19: 5935000 | G19: 30581000 | H19: 4924000 | I19: 2507000 | J19: 18110000 | K19: 163652000 | L19: 61724000 | M19: 59301000 | N19: 49242000 | O19: 4175000
A20: 其中：非流动资产处置损失 | B20: 0 | C20: 0 | D20: 0 | E20: 0 | F20: 0 | G20: 0 | H20: 0 | I20: 0 | J20: 0 | K20: 0 | L20: 0 | M20: 0 | N20: 0 | O20: 0
A21: 四、利润总额 | B21: 4757966000 | C21: 23124078000 | D21: 14811425000 | E21: 7708589000 | F21: 3442925000 | G21: 21963002000 | H21: 13239739000 | I21: 7574580000 | J21: 3666176000 | K21: 22317746000 | L21: 19745888000 | M21: 21132436000 | N21: 20071487000 | O21: 20041268000 | P21: =SUM(L21:O21,D21,H21) -> 109042243000 | Q21: =SUM(D21,H21,L21:N21) -> 89000975000 | R21: =SUM(D21,H21,L21) -> 47797052000
A22: 减：所得税费用 | B22: 564206000 | C22: 2105765000 | D22: 1315633000 | E22: 550072000 | F22: 318831000 | G22: 1879113000 | H22: 1432587000 | I22: 693387000 | J22: 411519000 | K22: 2293010000 | L22: 2319196000 | M22: 2526388000 | N22: 3163930000 | O22: 3821342000 | P22: =SUM(L22:O22,D22,H22) -> 14579076000 | Q22: =SUM(D22,H22,L22:N22) -> 10757734000 | R22: =SUM(D22,H22,L22) -> 5067416000
A23: 五、净利润 | B23: 4193760000 | C23: 21018313000 | D23: 13495792000 | E23: 7158517000 | F23: 3124094000 | G23: 20083889000 | H23: 11807152000 | I23: 6881193000 | J23: 3254657000 | K23: 20024736000 | L23: 17426692000 | M23: 18606048000 | N23: 16907557000 | O23: 16219926000 | P23: =SUM(L23:O23,D23,H23) -> 94463167000 | Q23: =SUM(D23,H23,L23:N23) -> 78243241000 | R23: =SUM(D23,H23,L23) -> 42729636000
A24: 归属于母公司所有者的净利润 | B24: 4184884000 | C24: 21040193000 | D24: 13484712000 | E24: 7161029000 | F24: 3128370000 | G24: 20073072000 | H24: 11795897000 | I24: 6871623000 | J24: 3255787000 | K24: 20009751000 | L24: 17430783000 | M24: 18606184000 | N24: 16902307000 | O24: 15867607000 | P24: =SUM(L24:O24,D24,H24) -> 94087490000 | Q24: =SUM(D24,H24,L24:N24) -> 78219883000 | R24: =SUM(D24,H24,L24) -> 42711392000
A25: 少数股东损益 | B25: 8876000 | C25: -21880000 | D25: 11080000 | E25: -2512000 | F25: -4276000 | G25: 10817000 | H25: 11255000 | I25: 9570000 | J25: -1130000 | K25: 14985000 | L25: -4091000 | M25: -136000 | N25: 5250000 | O25: 352319000
A26: 六、每股收益
A27: 基本每股收益(元/股) | B27: 0.21 | C27: 1.06 | D27: 0.68 | E27: 0.36 | F27: 0.16 | G27: 1.02 | H27: 0.59 | I27: 0.35 | J27: 0.16 | K27: 1.01 | L27: 0.88 | M27: 0.94 | N27: 0.9 | O27: 0.95
A28: 稀释每股收益(元/股) | B28: 0.21 | C28: 1.06 | D28: 0.68 | E28: 0.36 | F28: 0.16 | G28: 1.02 | H28: 0.59 | I28: 0.35 | J28: 0.16 | K28: 1.01 | L28: 0.88 | M28: 0.94 | N28: 0.9 | O28: 0.95
A29: 七、其他综合收益 | B29: 918795000 | C29: 236899000 | D29: 595009000 | E29: 788956000 | F29: 9171000 | G29: 1106340000 | H29: 655353000 | I29: 456613000 | J29: 448344000 | K29: -442464000 | L29: -203830000 | M29: 151374000 | N29: 139779000 | O29: -503912000
A30: 八、综合收益总额 | B30: 5112555000 | C30: 21255212000 | D30: 14090801000 | E30: 7947473000 | F30: 3133265000 | G30: 21190229000 | H30: 12462505000 | I30: 7337806000 | J30: 3703001000 | K30: 19582272000 | L30: 17222862000 | M30: 18757422000 | N30: 17047336000 | O30: 15716014000
A31: 归属于母公司所有者的综合收益总额 | B31: 5103679000 | C31: 21277092000 | D31: 14079721000 | E31: 7949985000 | F31: 3137541000 | G31: 21179412000 | H31: 12451250000 | I31: 7328236000 | J31: 3704131000 | K31: 19567287000 | L31: 17226953000 | M31: 18757558000 | N31: 17042086000 | O31: 15363695000
A32: 归属于少数股东的综合收益总额 | B32: 8876000 | C32: -21880000 | D32: 11080000 | E32: -2512000 | F32: -4276000 | G32: 10817000 | H32: 11255000 | I32: 9570000 | J32: -1130000 | K32: 14985000 | L32: -4091000 | M32: -136000 | N32: 5250000 | O32: 352319000
A34: 毛利率 | B34: =(B4-B6)/B4 -> 0.076382033 | C34: =(C4-C6)/C4 -> 0.080563877 | D34: =(D4-D6)/D4 -> 0.079582013 | E34: =(E4-E6)/E4 -> 0.071722851 | F34: =(F4-F6)/F4 -> 0.073614403 | G34: =(G4-G6)/G4 -> 0.0726225 | H34: =(H4-H6)/H4 -> 0.069201495 | I34: =(I4-I6)/I4 -> 0.065041709 | ... O34: =(O4-O6)/O4 -> 0.1014314
A35: 净利润率 | B35: =B23/B3 -> 0.035334333 | C35: =C23/C3 -> 0.044124592 | D35: =D23/D3 -> 0.041043301 | E35: =E23/E3 -> 0.034619587 | F35: =F23/F3 -> 0.029503607 | G35: =G23/G3 -> 0.039237873 | H35: =H23/H3 -> 0.032699174 | I35: =I23/I3 -> 0.030547729 | ... O35: =O23/O3 -> 0.045748716
A36: 所得税率 | B36: =B22/B21 -> 0.11858134 | C36: =C22/C21 -> 0.091063739 | D36: =D22/D21 -> 0.088825552 | E36: =E22/E21 -> 0.071358325 | F36: =F22/F21 -> 0.092604689 | G36: =G22/G21 -> 0.085558113 | H36: =H22/H21 -> 0.10820357 | I36: =I22/I21 -> 0.091541313 | ... O36: =O22/O21 -> 0.19067366
A37: 研发费用占比总营业收入% | B37: =B11/B3 -> 0.019069111 | C37: =C11/C3 -> 0.022696403 | D37: =D11/D3 -> 0.023771803 | E37: =E11/E3 -> 0.023851598 | F37: =F11/F3 -> 0.023054609 | G37: =G11/G3 -> 0.022639491 | H37: =H11/H3 -> 0.023122649 | I37: =I11/I3 -> 0.022672034
A38: 单季数据
A39: 一、营业总收入 | B39: =B3 -> 118687964000 | C39: =C3-D3 -> 147521722000 | D39: =D3-E3 -> 122041887000 | E39: =E3-F3 -> 100887953000 | F39: =F3 -> 105888545000 | G39: =G3-H3 -> 150765473000 | H39: =H3-I3 -> 135823728000 | I39: =I3-J3 -> 120197907000 | J39: =J3 -> 105062471000
A40: 营业收入 | B40: =B4 -> 118687964000 | C40: =C4-D4 -> 147521722000 | D40: =D4-E4 -> 122041887000 | E40: =E4-F4 -> 100887953000 | F40: =F4 -> 105888545000 | G40: =G4-H4 -> 150765473000 | H40: =H4-I4 -> 135823728000 | I40: =I4-J4 -> 120197907000 | J40: =J4 -> 105062471000
A41: 二、营业总成本 | B41: =B5 -> 113234576000 | C41: =C5-D5 -> 140224176000 | D41: =D5-E5 -> 115307835000 | E41: =E5-F5 -> 96145248000 | F41: =F5 -> 102143448000 | G41: =G5-H5 -> 143528512000 | H41: =H5-I5 -> 129641254000 | I41: =I5-J5 -> 116385052000 | J41: =J5 -> 101379783000
A42: 营业成本 | B42: =B6 -> 109622336000 | C42: =C6-D6 -> 135313945000 | D42: =D6-E6 -> 110704458000 | E42: =E6-F6 -> 93852275000 | F42: =F6 -> 98093623000 | G42: =G6-H6 -> 138581237000 | H42: =H6-I6 -> 125487488000 | I42: =I6-J6 -> 112660444000 | J42: =J6 -> 97948614000
A43: 营业税金及附加 | B43: =B7 -> 85053000 | C43: =C7-D7 -> 72594000 | D43: =D7-E7 -> 103945000 | E43: =E7-F7 -> 67427000 | F43: =F7 -> 136764000 | G43: =G7-H7 -> 96898000 | H43: =H7-I7 -> 146773000 | I43: =I7-J7 -> 109855000 | J43: =J7 -> 132593000
A44: 销售费用 | B44: =B8 -> 301506000 | C44: =C8-D8 -> 224984000 | D44: =D8-E8 -> 275084000 | E44: =E8-F8 -> 201561000 | F44: =F8 -> 322821000 | G44: =G8-H8 -> 237472000 | H44: =H8-I8 -> 289627000 | I44: =I8-J8 -> 281945000 | J44: =J8 -> 248784000
A45: 管理费用 | B45: =B9 -> 1206625000 | C45: =C9-D9 -> 1237996000 | D45: =D9-E9 -> 1185231000 | E45: =E9-F9 -> 952464000 | F45: =F9 -> 850138000 | G45: =G9-H9 -> 931455000 | H45: =H9-I9 -> 1080891000 | I45: =I9-J9 -> 969595000 | J45: =J9 -> 846458000
A46: 财务费用 | B46: =B10 -> -244218000 | C46: =C10-D10 -> 380056000 | D46: =D10-E10 -> 154461000 | E46: =E10-F10 -> -1419210000 | F46: =F10 -> 298883000 | G46: =G10-H10 -> 442657000 | H46: =H10-I10 -> -605635000 | I46: =I10-J10 -> -337875000 | J46: =J10 -> -202689000
A47: 研发费用 | B47: =B11 -> 2263274000 | C47: =C11-D11 -> 2994601000 | D47: =D11-E11 -> 2884656000 | E47: =E11-F11 -> 2490731000 | F47: =F11 -> 2441219000 | G47: =G11-H11 -> 3238793000 | H47: =H11-I11 -> 3242110000 | I47: =I11-J11 -> 2701088000 | J47: =J11 -> 2406023000
A48: 资产减值损失 | B48: =B12 -> 0 | C48: =C12-D12 -> 0 | D48: =D12-E12 -> 0 | E48: =E12-F12 -> 0 | F48: =F12 -> 0 | G48: =G12-H12 -> 0 | H48: =H12-I12 -> 0 | I48: =I12-J12 -> 0 | J48: =J12 -> 0
A49: 公允价值变动收益 | B49: =B13 -> -438367000 | C49: =C13-D13 -> 246665000 | D49: =D13-E13 -> 31474000 | E49: =E13-F13 -> -197620000 | F49: =F13 -> 183080000 | G49: =G13-H13 -> 171936000 | H49: =H13-I13 -> -264519000 | I49: =I13-J13 -> 32782000 | J49: =J13 -> -10312000
A50: 投资收益 | B50: =B14 -> 138257000 | C50: =C14-D14 -> 198953000 | D50: =D14-E14 -> 77857000 | E50: =E14-F14 -> -397825000 | F50: =F14 -> -545100000 | G50: =G14-H14 -> -18208000 | H50: =H14-I14 -> 41936000 | I50: =I14-J14 -> 12967000 | J50: =J14 -> -6431000
... A68: 归属于少数股东的综合收益总额 | B68: =B32 -> 8876000 | C68: =C32-D32 -> -32960000 | D68: =D32-E32 -> 13592000 | E68: =E32-F32 -> 1764000 | F68: =F32 -> -4276000 | G68: =G32-H32 -> -438000 | H68: =H32-I32 -> 1685000 | I68: =I32-J32 -> 10700000 | J68: =J32 -> -1130000
A70: 毛利率 | B70: =(B40-B42)/B40 -> 0.076382033 | C70: =(C40-C42)/C40 -> 0.082752403 | D70: =(D40-D42)/D40 -> 0.092897851 | E70: =(E40-E42)/E40 -> 0.069737543 | F70: =(F40-F42)/F40 -> 0.073614403 | G70: =(G40-G42)/G40 -> 0.080815824 | H70: =(H40-H42)/H40 -> 0.0761004 | I70: =(I40-I42)/I40 -> 0.062708771 | J70: =(J40-J42)/J40 -> 0.067710734
A71: 净利率 | B71: =B59/B39 -> 0.035334333 | C71: =C59/C39 -> 0.050992633 | D71: =D59/D39 -> 0.051927049 | E71: =E59/E39 -> 0.039989145 | F71: =F59/F39 -> 0.029503607 | G71: =G59/G39 -> 0.054898093 | H71: =H59/H39 -> 0.036267293 | I71: =I59/I39 -> 0.030171374 | J71: =J59/J39 -> 0.030978302
A72: ∆单季营收同比% | B72: =B40/F40-1 -> 0.12087633 | C72: =C40/G40-1 -> -0.021515211 | D72: =D40/H40-1 -> -0.10146858 | E72: =E40/I40-1 -> -0.16065133 | F72: =F40/J40-1 -> 0.0078626934 | G72: =G40/K40-1 -> #DIV/0! | H72: =H40/L40-1 -> #DIV/0! | I72: =I40/M40-1 -> #DIV/0! | J72: =J40/N40-1 -> #DIV/0!
A73: ∆单季归属净利同比% | B73: =B59/F59-1 -> 0.34239239 | C73: =C59/G59-1 -> -0.0911248 | D73: =D59/H59-1 -> 0.28650584 | E73: =E59/I59-1 -> 0.11247289 | F73: =F59/J59-1 -> -0.040115748 | G73: =G59/K59-1 -> #DIV/0! | H73: =H59/L59-1 -> #DIV/0! | I73: =I59/M59-1 -> #DIV/0! | J73: =J59/N59-1 -> #DIV/0!

Sheet 工业富联现金流量表
A1: 报表日期 | B1: 20240331 | C1: 20231231 | D1: 20230930 | E1: 20230630 | F1: 20230331 | G1: 20221231 | H1: 20220930 | I1: 20220630 | J1: 20220331 | K1: 20211231 | L1: 20201231 | M1: 20191231 | N1: 20181231 | O1: 20171231 | P1: 2017-2023 | Q1: 2017-2023 | R1: 2019-2023
A2: 单位 | B2: 元 | C2: 元 | D2: 元 | E2: 元 | F2: 元 | G2: 元 | H2: 元 | I2: 元 | J2: 元 | K2: 元 | L2: 元 | M2: 元 | N2: 元 | O2: 元 | P2: 最近7年合计 | Q2: 上市公司净值 | R2: 最近5年合计
A3: 一、经营活动产生的现金流量
A4: 销售商品、提供劳务收到的现金 | B4: 129681021000 | C4: 500495458000 | D4: 359677169000 | E4: 237390844000 | F4: 140440397000 | G4: 516357456000 | H4: 351733710000 | I4: 229891577000 | J4: 115960844000 | K4: 450521140000 | L4: 439888967000 | M4: 422177744000 | N4: 414230214000 | O4: 322632538000 | P4: =SUM(K4:O4,G4,C4) -> 3066303517000 | R4: =SUM(K4:M4,G4,C4) -> 2329440765000
A5: 收到的税费返还 | B5: 1568898000 | C5: 5192596000 | D5: 3403581000 | E5: 2384156000 | F5: 1957431000 | G5: 3519849000 | H5: 2084025000 | I5: 2069536000 | J5: 589495000 | K5: 4762371000 | L5: 4745529000 | M5: 4667007000 | N5: 5250537000 | O5: 2293188000 | P5: =SUM(K5:O5,G5,C5) -> 30431077000 | R5: =SUM(K5:M5,G5,C5) -> 22887352000
A6: 收到的其他与经营活动有关的现金 | B6: 958779000 | C6: 3996772000 | D6: 3170677000 | E6: 1891406000 | F6: 1432868000 | G6: 9666137000 | H6: 9738107000 | I6: 6796265000 | J6: 2322249000 | K6: 7164413000 | L6: 3430860000 | M6: 2902096000 | N6: 1531397000 | O6: 711822000 | P6: =SUM(K6:O6,G6,C6) -> 29403497000 | R6: =SUM(K6:M6,G6,C6) -> 27160278000
A7: 经营活动现金流入小计 | B7: 132208698000 | C7: 509684826000 | D7: 366251427000 | E7: 241666406000 | F7: 143830696000 | G7: 529543442000 | H7: 363555842000 | I7: 238757378000 | J7: 118872588000 | K7: 462447924000 | L7: 448065356000 | M7: 429746847000 | N7: 421012148000 | O7: 325637548000 | P7: =SUM(K7:O7,G7,C7) -> 3126138091000 | R7: =SUM(K7:M7,G7,C7) -> 2379488395000
A8: 购买商品、接受劳务支付的现金 | B8: 114715047000 | C8: 427709577000 | D8: 306100399000 | E8: 195401551000 | F8: 110420030000 | G8: 478979896000 | H8: 338827180000 | I8: 226879578000 | J8: 106517274000 | K8: 419360435000 | L8: 407117486000 | M8: 391348183000 | N8: 367695676000 | O8: 283645130000 | P8: =SUM(K8:O8,G8,C8) -> 2775856383000 | R8: =SUM(K8:M8,G8,C8) -> 2124515577000
A9: 支付给职工以及为职工支付的现金 | B9: 7836644000 | C9: 25328798000 | D9: 17659544000 | E9: 12620311000 | F9: 7791085000 | G9: 25356007000 | H9: 17277097000 | I9: 11595235000 | J9: 5767967000 | K9: 24931687000 | L9: 21865653000 | M9: 19889607000 | N9: 21247342000 | O9: 22032267000 | P9: =SUM(K9:O9,G9,C9) -> 160651361000 | R9: =SUM(K9:M9,G9,C9) -> 117371752000
A10: 支付的各项税费 | B10: 1340368000 | C10: 2911868000 | D10: 1868801000 | E10: 1715810000 | F10: 1477178000 | G10: 3286100000 | H10: 3210315000 | I10: 2459275000 | J10: 875244000 | K10: 3559322000 | L10: 3914716000 | M10: 4742107000 | N10: 2777954000 | O10: 4944887000 | P10: =SUM(K10:O10,G10,C10) -> 26136954000 | R10: =SUM(K10:M10,G10,C10) -> 18414113000
A11: 支付的其他与经营活动有关的现金 | B11: 3111469000 | C11: 10650854000 | D11: 8500523000 | E11: 5343363000 | F11: 3298229000 | G11: 6555812000 | H11: 6156008000 | I11: 3224052000 | J11: 3955305000 | K11: 5871895000 | L11: 7473763000 | M11: 7327663000 | N11: 7285589000 | O11: 6501457000 | P11: =SUM(K11:O11,G11,C11) -> 51667033000 | R11: =SUM(K11:M11,G11,C11) -> 37879987000
A12: 经营活动现金流出小计 | B12: 127003528000 | C12: 466601097000 | D12: 334129267000 | E12: 215081035000 | F12: 122986522000 | G12: 514177815000 | H12: 365470600000 | I12: 244158140000 | J12: 117115790000 | K12: 453723339000 | L12: 440371618000 | M12: 423307560000 | N12: 399006561000 | O12: 317123741000 | P12: =SUM(K12:O12,G12,C12) -> 3014311731000 | R12: =SUM(K12:M12,G12,C12) -> 2298181429000
A13: 经营活动产生的现金流量净额 | B13: 5205170000 | C13: 43083729000 | D13: 32122160000 | E13: 26585371000 | F13: 20844174000 | G13: 15365627000 | H13: -1914758000 | I13: -5400762000 | J13: 1756798000 | K13: 8724585000 | L13: 7693738000 | M13: 6439287000 | N13: 22005587000 | O13: 8513807000 | P13: =SUM(K13:O13,G13,C13) -> 111826360000 | R13: =SUM(K13:M13,G13,C13) -> 81306966000
A14: 二、投资活动产生的现金流量
A15: 收回投资所收到的现金 | B15: 1087426000 | C15: 5380000000 | D15: 5380000000 | E15: 3190000000 | F15: 2690000000 | G15: 0 | H15: 0 | I15: 0 | J15: 0 | K15: 0 | L15: 0 | M15: 0 | N15: 700000000 | O15: 3750000000 | P15: =SUM(K15:O15,G15,C15) -> 9830000000 | R15: =SUM(K15:M15,G15,C15) -> 5380000000
A16: 取得投资收益所收到的现金 | B16: 279394000 | C16: 11983000 | D16: 0 | E16: 0 | F16: 0 | G16: 30077000 | H16: 22376000 | I16: 23622000 | J16: 0 | K16: 965101000 | L16: 327251000 | M16: 165213000 | N16: 142548000 | O16: 13155000 | P16: =SUM(K16:O16,G16,C16) -> 1655328000 | R16: =SUM(K16:M16,G16,C16) -> 1499625000
A17: 处置固定资产、无形资产和其他长期资产所收回的现金净额 | B17: 71652000 | C17: 520011000 | D17: 285371000 | E17: 219765000 | F17: 23784000 | G17: 46566000 | H17: 15140000 | I17: 22819000 | J17: 38973000 | K17: 53791000 | L17: 110405000 | M17: 328392000 | N17: 995550000 | O17: 165800000 | P17: =SUM(K17:O17,G17,C17) -> 2220515000 | R17: =SUM(K17:M17,G17,C17) -> 1059165000
A18: 处置子公司及其他营业单位收到的现金净额 | B18: 27208000 | C18: 21599000 | D18: 21599000 | E18: 21599000 | F18: 21599000 | G18: 0 | H18: 0 | I18: 0 | J18: 0 | K18: 0 | L18: 0 | M18: 0 | N18: 1308190000 | O18: 0 | P18: =SUM(K18:O18,G18,C18) -> 1329789000 | R18: =SUM(K18:M18,G18,C18) -> 21599000
A19: 收到的其他与投资活动有关的现金 | B19: 118351000 | C19: 800495000 | D19: 996031000 | E19: 704117000 | F19: 314433000 | G19: 2975165000 | H19: 2499475000 | I19: 490565000 | J19: 497458000 | K19: 2306524000 | L19: 116260000 | M19: 11512000 | N19: 208696000 | O19: 126383000 | P19: =SUM(K19:O19,G19,C19) -> 6545035000 | R19: =SUM(K19:M19,G19,C19) -> 6209956000
A20: 投资活动现金流入小计 | B20: 1584031000 | C20: 6734088000 | D20: 6683001000 | E20: 4135481000 | F20: 3049816000 | G20: 3051808000 | H20: 2536991000 | I20: 537006000 | J20: 536431000 | K20: 3325416000 | L20: 553916000 | M20: 505117000 | N20: 3354984000 | O20: 4055338000 | P20: =SUM(K20:O20,G20,C20) -> 21580667000 | R20: =SUM(K20:M20,G20,C20) -> 14170345000
A21: 购建固定资产、无形资产和其他长期资产所支付的现金 | B21: 2812894000 | C21: 9189698000 | D21: 6028433000 | E21: 4055130000 | F21: 2282482000 | G21: 8093290000 | H21: 5018470000 | I21: 2592476000 | J21: 1370588000 | K21: 6035315000 | L21: 3606281000 | M21: 3058426000 | N21: 3680488000 | O21: 935661000 | P21: =SUM(K21:O21,G21,C21) -> 34599159000 | R21: =SUM(K21:M21,G21,C21) -> 29983010000
A22: 投资所支付的现金 | B22: 344546000 | C22: 1688310000 | D22: 1311237000 | E22: 1266592000 | F22: 39482000 | G22: 9236384000 | H22: 9194316000 | I22: 9185891000 | J22: 6522567000 | K22: 1798609000 | L22: 983207000 | M22: 153045000 | N22: 851042000 | O22: 4000000000 | P22: =SUM(K22:O22,G22,C22) -> 18710597000 | R22: =SUM(K22:M22,G22,C22) -> 13859555000
A23: 取得子公司及其他营业单位支付的现金净额 | B23: 0 | C23: 0 | D23: 0 | E23: 0 | F23: 0 | G23: 342454000 | H23: 343144000 | I23: 342454000 | J23: 255242000 | K23: 0 | L23: 70465000 | M23: 0 | N23: 0 | O23: 128518000 | P23: =SUM(K23:O23,G23,C23) -> 541437000 | R23: =SUM(K23:M23,G23,C23) -> 412919000
A24: 支付的其他与投资活动有关的现金 | B24: 1559000 | C24: 419639000 | D24: 505200000 | E24: 418507000 | F24: 539609000 | G24: 687182000 | H24: 479589000 | I24: 463385000 | J24: 1420715000 | K24: 2591292000 | L24: 2353818000 | M24: 111282000 | N24: 191687000 | O24: 1358220000 | P24: =SUM(K24:O24,G24,C24) -> 7713120000 | R24: =SUM(K24:M24,G24,C24) -> 6163213000
A25: 投资活动现金流出小计 | B25: 3158999000 | C25: 11297647000 | D25: 7844870000 | E25: 5740229000 | F25: 2861573000 | G25: 18359310000 | H25: 15035519000 | I25: 12584206000 | J25: 9569112000 | K25: 10425216000 | L25: 7013771000 | M25: 3322753000 | N25: 4723217000 | O25: 6422399000 | P25: =SUM(K25:O25,G25,C25) -> 61564313000 | R25: =SUM(K25:M25,G25,C25) -> 50418697000
A26: 投资活动产生的现金流量净额 | B26: -1574968000 | C26: -4563559000 | D26: -1161869000 | E26: -1604748000 | F26: 188243000 | G26: -15307502000 | H26: -12498528000 | I26: -12047200000 | J26: -9032681000 | K26: -7099800000 | L26: -6459855000 | M26: -2817636000 | N26: -1368233000 | O26: -2367061000 | P26: =SUM(K26:O26,G26,C26) -> -39983646000 | R26: =SUM(K26:M26,G26,C26) -> -36248352000
A27: 三、筹资活动产生的现金流量
A28: 吸收投资收到的现金 | B28: 105000 | C28: 174482000 | D28: 165550000 | E28: 140282000 | F28: 36215000 | G28: 386000 | H28: 386000 | I28: 386000 | J28: 386000 | K28: 27413000 | L28: 336153000 | M28: 978782000 | N28: 26780656000 | O28: 2233917000 | P28: =SUM(K28:O28,G28,C28) -> 30531789000 | Q28: =P28-P29 -> 28894607000 | R28: =SUM(K28:M28,G28,C28) -> 1517216000
A29: 其中：子公司吸收少数股东投资收到的现金 | B29: 0 | C29: 95330000 | D29: 89150000 | E29: 65000000 | F29: 0 | G29: 0 | H29: 0 | I29: 0 | J29: 0 | K29: 0 | L29: 207500000 | M29: 18141000 | N29: 0 | O29: 1316211000 | P29: =SUM(K29:O29,G29,C29) -> 1637182000 | R29: =SUM(K29:M29,G29,C29) -> 320971000
A30: 取得借款收到的现金 | B30: 21568617000 | C30: 162512131000 | D30: 135310246000 | E30: 107376496000 | F30: 24486438000 | G30: 148244502000 | H30: 83979975000 | I30: 56335747000 | J30: 37244437000 | K30: 157283504000 | L30: 124970428000 | M30: 58516568000 | N30: 60246268000 | O30: 26545552000 | P30: =SUM(K30:O30,G30,C30) -> 738318953000 | R30: =SUM(K30:M30,G30,C30) -> 651527133000
A31: 发行债券收到的现金 | B31: 0 | C31: 0 | D31: 0 | E31: 0 | F31: 0 | G31: 0 | H31: 0 | I31: 0 | J31: 0 | K31: 0 | L31: 0 | M31: 0 | N31: 0 | O31: 0 | P31: =SUM(K31:O31,G31,C31) -> 0 | R31: =SUM(K31:M31,G31,C31) -> 0
A32: 收到其他与筹资活动有关的现金 | B32: 0 | C32: 146563000 | D32: 146554000 | E32: 146554000 | F32: 146554000 | G32: 837281000 | H32: 405925000 | I32: 457870000 | J32: 0 | K32: 0 | L32: 0 | M32: 2133082000 | N32: 5243622000 | O32: 1807555000 | P32: =SUM(K32:O32,G32,C32) -> 10168103000 | R32: =SUM(K32:M32,G32,C32) -> 3116926000
A33: 筹资活动现金流入小计 | B33: 21568722000 | C33: 162833176000 | D33: 135622350000 | E33: 107663332000 | F33: 24669207000 | G33: 149082169000 | H33: 84386286000 | I33: 56794003000 | J33: 37244823000 | K33: 157310917000 | L33: 125306581000 | M33: 61628432000 | N33: 92270546000 | O33: 30587024000 | P33: =SUM(K33:O33,G33,C33) -> 779018845000 | R33: =SUM(K33:M33,G33,C33) -> 656161275000
A34: 偿还债务支付的现金 | B34: 28348037000 | C34: 172729523000 | D34: 142937695000 | E34: 117197799000 | F34: 33249696000 | G34: 148264199000 | H34: 68779753000 | I34: 42741857000 | J34: 30826178000 | K34: 144780429000 | L34: 107984036000 | M34: 52800364000 | N34: 44444332000 | O34: 19960885000 | P34: =SUM(K34:O34,G34,C34) -> 690963768000 | R34: =SUM(K34:M34,G34,C34) -> 626558551000
A35: 分配股利、利润或偿付利息所支付的现金 | B35: 583783000 | C35: 13267414000 | D35: 12583701000 | E35: 1086088000 | F35: 599048000 | G35: 11089755000 | H35: 10786385000 | I35: 512912000 | J35: 123320000 | K35: 5360861000 | L35: 4597764000 | M35: 3368348000 | N35: 698297000 | O35: 1957911000 | P35: =SUM(K35:O35,G35,C35) -> 40340350000 | Q35: =P35-P36 -> 40340350000 | R35: =SUM(K35:M35,G35,C35) -> 37684142000
A36: 其中：子公司支付给少数股东的股利、利润 | B36: 0 | C36: 0 | D36: 0 | E36: 0 | F36: 0 | G36: 0 | H36: 0 | I36: 0 | J36: 0 | K36: 0 | L36: 0 | M36: 0 | N36: 0 | O36: 0 | P36: =SUM(K36:O36,G36,C36) -> 0 | R36: =SUM(K36:M36,G36,C36) -> 0
A37: 支付其他与筹资活动有关的现金 | B37: 469783000 | C37: 1569739000 | D37: 1325213000 | E37: 876909000 | F37: 392995000 | G37: 3796671000 | H37: 2258041000 | I37: 1566399000 | J37: 445078000 | K37: 2403431000 | L37: 4568914000 | M37: 2739832000 | N37: 22243229000 | O37: 5082330000 | P37: =SUM(K37:O37,G37,C37) -> 42404146000 | R37: =SUM(K37:M37,G37,C37) -> 15078587000
A38: 筹资活动现金流出小计 | B38: 29401603000 | C38: 187566676000 | D38: 156846609000 | E38: 119160796000 | F38: 34241739000 | G38: 163150625000 | H38: 81824179000 | I38: 44821168000 | J38: 31394576000 | K38: 152544721000 | L38: 117150714000 | M38: 58908544000 | N38: 67385858000 | O38: 27001126000 | P38: =SUM(K38:O38,G38,C38) -> 773708264000 | R38: =SUM(K38:M38,G38,C38) -> 679321280000
A39: 筹资活动产生的现金流量净额 | B39: -7832881000 | C39: -24733500000 | D39: -21224259000 | E39: -11497464000 | F39: -9572532000 | G39: -14068456000 | H39: 2562107000 | I39: 11972835000 | J39: 5850247000 | K39: 4766196000 | L39: 8155867000 | M39: 2719888000 | N39: 24884688000 | O39: 3585898000 | P39: =SUM(K39:O39,G39,C39) -> 5310581000 | R39: =SUM(K39:M39,G39,C39) -> -23160005000
A40: 四、汇率变动对现金及现金等价物的影响 | B40: 613601000 | C40: 398722000 | D40: 795956000 | E40: 891304000 | F40: -436138000 | G40: 2105696000 | H40: 1942524000 | I40: 907772000 | J40: -39778000 | K40: -613101000 | L40: -668120000 | M40: 96822000 | N40: 425967000 | O40: -384279000 | P40: =SUM(K40:O40,G40,C40) -> 1361707000 | R40: =SUM(K40:M40,G40,C40) -> 1320019000
A41: 五、现金及现金等价物净增加额 | B41: -3589078000 | C41: 14185392000 | D41: 10531988000 | E41: 14374463000 | F41: 11023747000 | G41: -11904635000 | H41: -9908655000 | I41: -4567355000 | J41: -1465414000 | K41: 5777880000 | L41: 8721630000 | M41: 6438361000 | N41: 45948009000 | O41: 9348365000 | P41: =SUM(K41:O41,G41,C41) -> 78515002000 | R41: =SUM(K41:M41,G41,C41) -> 23218628000
A42: 加:期初现金及现金等价物余额 | B42: 83351894000 | C42: 69166502000 | D42: 69166502000 | E42: 69166502000 | F42: 69166502000 | G42: 81071137000 | H42: 81071137000 | I42: 81071137000 | J42: 81071137000 | K42: 75293257000 | L42: 66571627000 | M42: 60133266000 | N42: 14185257000 | O42: 4836892000 | P42: =SUM(K42:O42,G42,C42) -> 371257938000 | R42: =SUM(K42:M42,G42,C42) -> 352235789000
A43: 六、期末现金及现金等价物余额 | B43: 79762816000 | C43: 83351894000 | D43: 79698490000 | E43: 83540965000 | F43: 80190249000 | G43: 69166502000 | H43: 71162482000 | I43: 76503782000 | J43: 79605723000 | K43: 81071137000 | L43: 75293257000 | M43: 66571627000 | N43: 60133266000 | O43: 14185257000 | P43: =SUM(K43:O43,G43,C43) -> 449772940000 | R43: =SUM(K43:M43,G43,C43) -> 375454417000
A44: 附注 | P44: =SUM(K44:O44,G44,C44) -> 0 | R44: =SUM(K44:M44,G44,C44) -> 0
A45: 净利润 | B45: 0 | C45: 21018313000 | D45: 0 | E45: 7158517000 | F45: 0 | G45: 20083889000 | H45: 0 | I45: 6881193000 | J45: 0 | K45: 20024736000 | L45: 17426692000 | M45: 18606048000 | N45: 16907557000 | O45: 16219926000 | P45: =SUM(K45:O45,G45,C45) -> 130287161000 | R45: =SUM(K45:M45,G45,C45) -> 97159678000
A46: 少数股东权益 | B46: 0 | C46: 0 | D46: 0 | E46: 0 | F46: 0 | G46: 0 | H46: 0 | I46: 0 | J46: 0 | K46: 0 | L46: 0 | M46: 0 | N46: 0 | O46: 0 | P46: =SUM(K46:O46,G46,C46) -> 0 | R46: =SUM(K46:M46,G46,C46) -> 0
A47: 未确认的投资损失 | B47: 0 | C47: 0 | D47: 0 | E47: 0 | F47: 0 | G47: 0 | H47: 0 | I47: 0 | J47: 0 | K47: 0 | L47: 0 | M47: 0 | N47: 0 | O47: 0 | P47: =SUM(K47:O47,G47,C47) -> 0 | R47: =SUM(K47:M47,G47,C47) -> 0
A48: 资产减值准备 | B48: 0 | C48: 543186000 | D48: 0 | E48: 513697000 | F48: 0 | G48: 1068668000 | H48: 0 | I48: 619805000 | J48: 0 | K48: 407573000 | L48: 1332979000 | M48: 502012000 | N48: 736312000 | O48: 770427000 | P48: =SUM(K48:O48,G48,C48) -> 5361157000 | R48: =SUM(K48:M48,G48,C48) -> 3854418000
A49: 固定资产折旧、油气资产折耗、生产性物资折旧 | B49: 0 | C49: 4449463000 | D49: 0 | E49: 2090263000 | F49: 0 | G49: 3220238000 | H49: 0 | I49: 1438005000 | J49: 0 | K49: 2515669000 | L49: 2432955000 | M49: 2746040000 | N49: 3867919000 | O49: 3686021000 | P49: =SUM(K49:O49,G49,C49) -> 22918305000 | R49: =SUM(K49:M49,G49,C49) -> 15364365000
A50: 无形资产摊销 | B50: 0 | C50: 0 | D50: 0 | E50: 0 | F50: 0 | G50: 0 | H50: 0 | I50: 0 | J50: 0 | K50: 0 | L50: 0 | M50: 0 | N50: 0 | O50: 0 | P50: =SUM(K50:O50,G50,C50) -> 0 | R50: =SUM(K50:M50,G50,C50) -> 0
A51: 长期待摊费用摊销 | B51: 0 | C51: 0 | D51: 0 | E51: 0 | F51: 0 | G51: 0 | H51: 0 | I51: 0 | J51: 0 | K51: 0 | L51: 0 | M51: 0 | N51: 0 | O51: 0 | P51: =SUM(K51:O51,G51,C51) -> 0 | R51: =SUM(K51:M51,G51,C51) -> 0
A52: 待摊费用的减少 | B52: 0 | C52: 0 | D52: 0 | E52: 0 | F52: 0 | G52: 0 | H52: 0 | I52: 0 | J52: 0 | K52: 0 | L52: 0 | M52: 0 | N52: 0 | O52: 0 | P52: =SUM(K52:O52,G52,C52) -> 0 | R52: =SUM(K52:M52,G52,C52) -> 0
A53: 预提费用的增加 | B53: 0 | C53: 0 | D53: 0 | E53: 0 | F53: 0 | G53: 0 | H53: 0 | I53: 0 | J53: 0 | K53: 0 | L53: 0 | M53: 0 | N53: 0 | O53: 0 | P53: =SUM(K53:O53,G53,C53) -> 0 | R53: =SUM(K53:M53,G53,C53) -> 0
A54: 处置固定资产、无形资产和其他长期资产的损失 | B54: 0 | C54: -130071000 | D54: 0 | E54: -38079000 | F54: 0 | G54: -8825000 | H54: 0 | I54: -6549000 | J54: 0 | K54: -13590000 | L54: -34091000 | M54: 45067000 | N54: -128307000 | O54: 42886000 | P54: =SUM(K54:O54,G54,C54) -> -226931000 | R54: =SUM(K54:M54,G54,C54) -> -141510000
A55: 固定资产报废损失 | B55: 0 | C55: 28663000 | D55: 0 | E55: 763000 | F55: 0 | G55: 21995000 | H55: 0 | I55: 673000 | J55: 0 | K55: 10741000 | L55: 5835000 | M55: 0 | N55: 0 | O55: 0 | P55: =SUM(K55:O55,G55,C55) -> 67234000 | R55: =SUM(K55:M55,G55,C55) -> 67234000
A56: 公允价值变动损失 | B56: 0 | C56: -263599000 | D56: 0 | E56: 14540000 | F56: 0 | G56: 70113000 | H56: 0 | I56: -22470000 | J56: 0 | K56: 481483000 | L56: -312832000 | M56: -156692000 | N56: 115000 | O56: 0 | P56: =SUM(K56:O56,G56,C56) -> -181412000 | R56: =SUM(K56:M56,G56,C56) -> -181527000
... A77: 现金及现金等价物的净增加额 | B77: 0 | C77: 14185392000 | D77: 0 | E77: 14374463000 | F77: 0 | G77: -11904635000 | H77: 0 | I77: -4567355000 | J77: 0 | K77: 5777880000 | L77: 8721630000 | M77: 6438361000 | N77: 45948009000 | O77: 9348365000 | P77: =SUM(K77:O77,G77,C77) -> 78515002000 | R77: =SUM(K77:M77,G77,C77) -> 23218628000
A79: 自由现金流1=LINE13-LINE21 | B79: =B13-B21 -> 2392276000 | C79: =C13-C21 -> 33894031000 | D79: =D13-D21 -> 26093727000 | E79: =E13-E21 -> 22530241000 | F79: =F13-F21 -> 18561692000 | G79: =G13-G21 -> 7272337000 | H79: =H13-H21 -> -6933228000 | I79: =I13-I21 -> -7993238000 | ... P79: =P13-P21 -> 77227201000 | R79: =R13-R21 -> 51323956000
A80: 自由现金流2 | B80: =B45+B49+B48+B50+B51-B21 -> -2812894000 | C80: =C45+C49+C48+C50+C51-C21 -> 16821264000 | E80: =E45+E49+E48+E50+E51-E21 -> 5707347000 | G80: =G45+G49+G48+G50+G51-G21 -> 16279505000 | K80: =K45+K49+K48+K50+K51-K21 -> 16912663000 | L80: =L45+L49+L48+L50+L51-L21 -> 17586345000 | M80: =M45+M49+M48+M50+M51-M21 -> 18795674000 | N80: =N45+N49+N48+N50+N51-N21 -> 17831300000 | O80: =O45+O49+O48+O50+O51-O21 -> 19740713000 | P80: =P45+P49+P48+P50+P51-P21 -> 123967464000

Sheet 工业富联资产负债变动表
A1: 报表日期 | B1: 20231231 | C1: 20221231 | D1: 20211231 | E1: 20201231 | F1: 20191231 | G1: 20181231 | H1: 20171231 | I1: 2017-2023 | J1: 2019-2023
A2: 单位 | I2: 最近7年合计 | J2: 最近5年合计
A3: ∆流动资产
A4: ∆货币资金 | B4: =工业富联资产负债表!C4-工业富联资产负债表!G4 -> 14032483000 | C4: =工业富联资产负债表!G4-工业富联资产负债表!K4 -> -13447214000 | D4: =工业富联资产负债表!K4-工业富联资产负债表!L4 -> 4820449000 | E4: =工业富联资产负债表!L4-工业富联资产负债表!M4 -> 11155469000 | F4: =工业富联资产负债表!M4-工业富联资产负债表!N4 -> 4608001000 | G4: =工业富联资产负债表!N4-工业富联资产负债表!O4 -> 46774150000 | H4: =工业富联资产负债表!O4-工业富联资产负债表!P4 -> 10584438000 | I4: =SUM(B4:H4) -> 78527776000 | J4: =SUM(B4:F4) -> 21169188000
A5: ∆交易性金融资产 | B5: =工业富联资产负债表!C5-工业富联资产负债表!G5 -> 333260000 | C5: =工业富联资产负债表!G5-工业富联资产负债表!K5 -> 0 | D5: =工业富联资产负债表!K5-工业富联资产负债表!L5 -> 0 | E5: =工业富联资产负债表!L5-工业富联资产负债表!M5 -> 0 | F5: =工业富联资产负债表!M5-工业富联资产负债表!N5 -> 0 | G5: =工业富联资产负债表!N5-工业富联资产负债表!O5 -> 0 | H5: =工业富联资产负债表!O5-工业富联资产负债表!P5 -> 0 | I5: =SUM(B5:H5) -> 333260000 | J5: =SUM(B5:F5) -> 333260000
A6: ∆衍生金融资产 | B6: =工业富联资产负债表!C6-工业富联资产负债表!G6 -> 263773000 | C6: =工业富联资产负债表!G6-工业富联资产负债表!K6 -> -230393000 | D6: =工业富联资产负债表!K6-工业富联资产负债表!L6 -> -221874000 | E6: =工业富联资产负债表!L6-工业富联资产负债表!M6 -> 310778000 | F6: =工业富联资产负债表!M6-工业富联资产负债表!N6 -> 157110000 | G6: =工业富联资产负债表!N6-工业富联资产负债表!O6 -> 0 | H6: =工业富联资产负债表!O6-工业富联资产负债表!P6 -> 0 | I6: =SUM(B6:H6) -> 279394000 | J6: =SUM(B6:F6) -> 279394000
A7: ∆应收票据及应收账款8+9 | B7: =工业富联资产负债表!C7-工业富联资产负债表!G7 -> -9215541000 | C7: =工业富联资产负债表!G7-工业富联资产负债表!K7 -> 10655939000 | D7: =工业富联资产负债表!K7-工业富联资产负债表!L7 -> 206248000 | E7: =工业富联资产负债表!L7-工业富联资产负债表!M7 -> 2183860000 | F7: =工业富联资产负债表!M7-工业富联资产负债表!N7 -> -1474170000 | G7: =工业富联资产负债表!N7-工业富联资产负债表!O7 -> 7604709000 | H7: =工业富联资产负债表!O7-工业富联资产负债表!P7 -> 23939419000 | I7: =SUM(B7:H7) -> 33900464000 | J7: =SUM(B7:F7) -> 2356336000
A8: ∆应收票据 | B8: =工业富联资产负债表!C8-工业富联资产负债表!G8 -> -9487000 | C8: =工业富联资产负债表!G8-工业富联资产负债表!K8 -> 12716000 | D8: =工业富联资产负债表!K8-工业富联资产负债表!L8 -> 4046000 | E8: =工业富联资产负债表!L8-工业富联资产负债表!M8 -> 100000 | F8: =工业富联资产负债表!M8-工业富联资产负债表!N8 -> -923000 | G8: =工业富联资产负债表!N8-工业富联资产负债表!O8 -> 923000 | H8: =工业富联资产负债表!O8-工业富联资产负债表!P8 -> 0 | I8: =SUM(B8:H8) -> 7375000 | J8: =SUM(B8:F8) -> 6452000
A9: ∆应收账款 | B9: =工业富联资产负债表!C9-工业富联资产负债表!G9 -> -9206054000 | C9: =工业富联资产负债表!G9-工业富联资产负债表!K9 -> 10643223000 | D9: =工业富联资产负债表!K9-工业富联资产负债表!L9 -> 202202000 | E9: =工业富联资产负债表!L9-工业富联资产负债表!M9 -> 2183760000 | F9: =工业富联资产负债表!M9-工业富联资产负债表!N9 -> -1473247000 | G9: =工业富联资产负债表!N9-工业富联资产负债表!O9 -> 7603786000 | H9: =工业富联资产负债表!O9-工业富联资产负债表!P9 -> 23939419000 | I9: =SUM(B9:H9) -> 33893089000 | J9: =SUM(B9:F9) -> 2349884000
A10: ∆应收款项融资 | B10: =工业富联资产负债表!C10-工业富联资产负债表!G10 -> 0 | C10: =工业富联资产负债表!G10-工业富联资产负债表!K10 -> 0 | D10: =工业富联资产负债表!K10-工业富联资产负债表!L10 -> 0 | E10: =工业富联资产负债表!L10-工业富联资产负债表!M10 -> 0 | F10: =工业富联资产负债表!M10-工业富联资产负债表!N10 -> 0 | G10: =工业富联资产负债表!N10-工业富联资产负债表!O10 -> 0 | H10: =工业富联资产负债表!O10-工业富联资产负债表!P10 -> 0 | I10: =SUM(B10:H10) -> 0 | J10: =SUM(B10:F10) -> 0
A11: ∆预付款项 | B11: =工业富联资产负债表!C11-工业富联资产负债表!G11 -> -97654000 | C11: =工业富联资产负债表!G11-工业富联资产负债表!K11 -> 110750000 | D11: =工业富联资产负债表!K11-工业富联资产负债表!L11 -> 70145000 | E11: =工业富联资产负债表!L11-工业富联资产负债表!M11 -> -57370000 | F11: =工业富联资产负债表!M11-工业富联资产负债表!N11 -> 13622000 | G11: =工业富联资产负债表!N11-工业富联资产负债表!O11 -> 52702000 | H11: =工业富联资产负债表!O11-工业富联资产负债表!P11 -> 48652000 | I11: =SUM(B11:H11) -> 140847000 | J11: =SUM(B11:F11) -> 39493000
A12: ∆其他应收款(合计)13+14+15 | B12: =工业富联资产负债表!C12-工业富联资产负债表!G12 -> -1025424000 | C12: =工业富联资产负债表!G12-工业富联资产负债表!K12 -> -637871000 | D12: =工业富联资产负债表!K12-工业富联资产负债表!L12 -> 2121025000 | E12: =工业富联资产负债表!L12-工业富联资产负债表!M12 -> -60235000 | F12: =工业富联资产负债表!M12-工业富联资产负债表!N12 -> -898768000 | G12: =工业富联资产负债表!N12-工业富联资产负债表!O12 -> -1739985000 | H12: =工业富联资产负债表!O12-工业富联资产负债表!P12 -> -29506162000 | I12: =SUM(B12:H12) -> -31747420000 | J12: =SUM(B12:F12) -> -501273000
A13: ∆应收利息 | B13: =工业富联资产负债表!C13-工业富联资产负债表!G13 -> 0 | C13: =工业富联资产负债表!G13-工业富联资产负债表!K13 -> 0 | D13: =工业富联资产负债表!K13-工业富联资产负债表!L13 -> 0 | E13: =工业富联资产负债表!L13-工业富联资产负债表!M13 -> 0 | F13: =工业富联资产负债表!M13-工业富联资产负债表!N13 -> -166075000 | G13: =工业富联资产负债表!N13-工业富联资产负债表!O13 -> 166075000 | H13: =工业富联资产负债表!O13-工业富联资产负债表!P13 -> 0 | I13: =SUM(B13:H13) -> 0 | J13: =SUM(B13:F13) -> -166075000
A14: ∆应收股利 | B14: =工业富联资产负债表!C14-工业富联资产负债表!G14 -> 0 | C14: =工业富联资产负债表!G14-工业富联资产负债表!K14 -> 0 | D14: =工业富联资产负债表!K14-工业富联资产负债表!L14 -> 0 | E14: =工业富联资产负债表!L14-工业富联资产负债表!M14 -> 0 | F14: =工业富联资产负债表!M14-工业富联资产负债表!N14 -> 0 | G14: =工业富联资产负债表!N14-工业富联资产负债表!O14 -> 0 | H14: =工业富联资产负债表!O14-工业富联资产负债表!P14 -> 0 | I14: =SUM(B14:H14) -> 0 | J14: =SUM(B14:F14) -> 0
A15: ∆其他应收款 | B15: =工业富联资产负债表!C15-工业富联资产负债表!G15 -> -1025424000 | C15: =工业富联资产负债表!G15-工业富联资产负债表!K15 -> -637871000 | D15: =工业富联资产负债表!K15-工业富联资产负债表!L15 -> 2121025000 | E15: =工业富联资产负债表!L15-工业富联资产负债表!M15 -> -60235000 | F15: =工业富联资产负债表!M15-工业富联资产负债表!N15 -> -767212000 | G15: =工业富联资产负债表!N15-工业富联资产负债表!O15 -> -1871541000 | H15: =工业富联资产负债表!O15-工业富联资产负债表!P15 -> -29506162000 | I15: =SUM(B15:H15) -> -31747420000 | J15: =SUM(B15:F15) -> -369717000
... A95: ∆负债和所有者权益(或股东权益)总计 | B95: =工业富联资产负债表!C95-工业富联资产负债表!G95 -> 3517639000 | C95: =工业富联资产负债表!G95-工业富联资产负债表!K95 -> 17578887000 | D95: =工业富联资产负债表!K95-工业富联资产负债表!L95 -> 41094831000 | E95: =工业富联资产负债表!L95-工业富联资产负债表!M95 -> 19900999000 | F95: =工业富联资产负债表!M95-工业富联资产负债表!N95 -> 5009621000 | G95: =工业富联资产负债表!N95-工业富联资产负债表!O95 -> 52007083000 | H95: =工业富联资产负债表!O95-工业富联资产负债表!P95 -> 12852582000 | I95: =SUM(B95:H95) -> 151961642000 | J95: =SUM(B95:F95) -> 87101977000
I96: =SUM(B96:H96) -> 0 | J96: =SUM(B96:F96) -> 0
A97: Δ货币资金及等价物 | B97: =B4+B5+B6+B8+B10+B16+B22-B51-B53 -> 14605075000 | C97: =C4+C5+C6+C8+C10+C16+C22-C51-C53 -> -13545201000 | D97: =D4+D5+D6+D8+D10+D16+D22-D51-D53 -> 4741719000 | E97: =E4+E5+E6+E8+E10+E16+E22-E51-E53 -> 11689713000 | F97: =F4+F5+F6+F8+F10+F16+F22-F51-F53 -> 3943002000 | G97: =G4+G5+G6+G8+G10+G16+G22-G51-G53 -> 45423598000 | H97: =H4+H5+H6+H8+H10+H16+H22-H51-H53 -> 13281926000 | I97: =SUM(B97:H97) -> 80139832000 | J97: =SUM(B97:F97) -> 21434308000
A98: Δ应收账款-Δ应付账款-A | B98: =B9-B54 -> -14955450000 | C98: =C9-C54 -> 13101014000 | D98: =D9-D54 -> -9389735000 | E98: =E9-E54 -> 7360312000 | F98: =F9-F54 -> 936204000 | G98: =G9-G54 -> 14682297000 | H98: =H9-H54 -> -9856988000 | I98: =SUM(B98:H98) -> 1877654000 | J98: =SUM(B98:F98) -> -2947655000
A99: Δ其他应收款-Δ其他应付款-B | B99: =B15-B62 -> 1821667000 | C99: =C15-C62 -> -8730358000 | D99: =D15-D62 -> -314603000 | E99: =E15-E62 -> 6145920000 | F99: =F15-F62 -> 14373767000 | G99: =G15-G62 -> 2512129000 | H99: =H15-H62 -> -52945331000 | I99: =SUM(B99:H99) -> -37136809000 | J99: =SUM(B99:F99) -> 13296393000
A100: Δ存货-C | B100: =B17 -> -638405000 | C100: =C17 -> 5393917000 | D100: =D17 -> 26573937000 | E100: =E17 -> 3707949000 | F100: =F17 -> 4178316000 | G100: =G17 -> 1916600000 | H100: =H17 -> 6989595000 | I100: =SUM(B100:H100) -> 48121909000 | J100: =SUM(B100:F100) -> 39215714000
A101: Δ其他营运资本项目净值-D | B101: =B23-B68-B97-B98-B99-B100+B102+B103 -> 4527630000 | C101: =C23-C68-C97-C98-C99-C100+C102+C103 -> -4034651000 | D101: =D23-D68-D97-D98-D99-D100+D102+D103 -> -666627000 | E101: =E23-E68-E97-E98-E99-E100+E102+E103 -> 12940000 | F101: =F23-F68-F97-F98-F99-F100+F102+F103 -> 157632000 | G101: =G23-G68-G97-G98-G99-G100+G102+G103 -> -3449530000 | H101: =H23-H68-H97-H98-H99-H100+H102+H103 -> 86113000 | I101: =SUM(B101:H101) -> -3366493000 | J101: =SUM(B101:F101) -> -3076000
A102: Δ短期借款 | B102: =B50 -> -9406793000 | C102: =C50 -> -1638962000 | D102: =D50 -> 7913720000 | E102: =E50 -> 15951649000 | F102: =F50 -> 5781069000 | G102: =G50 -> 15533417000 | H102: =H50 -> 5313881000 | I102: =SUM(B102:H102) -> 39447981000 | J102: =SUM(B102:F102) -> 18600683000
A103: Δ预收账款-Δ预付账款-F | B103: =B55-B11 -> 97654000 | C103: =C55-C11 -> -110750000 | D103: =D55-D11 -> -70145000 | E103: =E55-E11 -> -46028000 | F103: =F55-F11 -> 31805000 | G103: =G55-G11 -> -101003000 | H103: =H55-H11 -> -126463000 | I103: =SUM(B103:H103) -> -324930000 | J103: =SUM(B103:F103) -> -97464000
I104: =SUM(B104:H104) -> 0 | J104: =SUM(B104:F104) -> 0
A105: 归属净利润 | B105: =工业富联利润表!C24 -> 21040193000 | C105: =工业富联利润表!G24 -> 20073072000 | D105: =工业富联利润表!K24 -> 20009751000 | E105: =工业富联利润表!L24 -> 17430783000 | F105: =工业富联利润表!M24 -> 18606184000 | G105: =工业富联利润表!N24 -> 16902307000 | H105: =工业富联利润表!O24 -> 15867607000 | I105: =SUM(B105:H105) -> 129929897000 | J105: =SUM(B105:F105) -> 97159983000
A106: 现金分红 | B106: =-1092520.06*10000 -> -10925200600 | C106: -9890945200 | D106: -4966789900 | E106: -3974420500 | F106: -2559938400 | I106: =SUM(B106:H106) -> -32317294600 | J106: =SUM(B106:F106) -> -32317294600
A107: 增发 | G107: 26722900000 | I107: =SUM(B107:H107) -> 26722900000 | J107: =SUM(B107:F107) -> 0
A108: 对归属权益的贡献 | B108: =SUM(B105:B107) -> 10114992400 | C108: =SUM(C105:C107) -> 10182126800 | D108: =SUM(D105:D107) -> 15042961100 | E108: =SUM(E105:E107) -> 13456362500 | F108: =SUM(F105:F107) -> 16046245600 | G108: =SUM(G105:G107) -> 43625207000 | H108: =SUM(H105:H107) -> 15867607000 | I108: =SUM(B108:H108) -> 124335502400 | J108: =SUM(B108:F108) -> 64842688400
A109: 与资产负债表归属权益变动差异 | B109: =B92-B108 -> 1097268600 | C109: =C92-C108 -> -387536800 | D109: =D92-D108 -> 385091900 | E109: =E92-E108 -> 1015506500 | F109: =F92-F108 -> 939800400 | G109: =G92-G108 -> 508368000 | H109: =H92-H108 -> -65009632000 | I109: =SUM(B109:H109) -> -61451133400 | J109: =SUM(B109:F109) -> 3050130600
I110: =SUM(B110:H110) -> 0 | J110: =SUM(B110:F110) -> 0
A111: 企业经营现金流=净利润-（应收-应付)-存货 | B111: =B105-B98-B100 -> 36634048000 | C111: =C105-C98-C100 -> 1578141000 | D111: =D105-D98-D100 -> 2825549000 | E111: =E105-E98-E100 -> 6362522000 | F111: =F105-F98-F100 -> 13491664000 | G111: =G105-G98-G100 -> 303410000 | H111: =H105-H98-H100 -> 18735000000 | I111: =SUM(B111:H111) -> 79930334000 | J111: =SUM(B111:F111) -> 60891924000
A112: 现金流量表中的“自由现金流” | B112: =工业富联现金流量表!C79 -> 33894031000 | C112: =工业富联现金流量表!G79 -> 7272337000 | D112: =工业富联现金流量表!K79 -> 2689270000 | E112: =工业富联现金流量表!L79 -> 4087457000 | F112: =工业富联现金流量表!M79 -> 3380861000 | G112: =工业富联现金流量表!N79 -> 18325099000 | H112: =工业富联现金流量表!O79 -> 7578146000 | I112: =SUM(B112:H112) -> 77227201000 | J112: =SUM(B112:F112) -> 51323956000
A113: 经营现金流量净额 | B113: =工业富联现金流量表!C13 -> 43083729000 | C113: =工业富联现金流量表!G13 -> 15365627000 | D113: =工业富联现金流量表!K13 -> 8724585000 | E113: =工业富联现金流量表!L13 -> 7693738000 | F113: =工业富联现金流量表!M13 -> 6439287000 | G113: =工业富联现金流量表!N13 -> 22005587000 | H113: =工业富联现金流量表!O13 -> 8513807000 | I113: =SUM(B113:H113) -> 111826360000 | J113: =SUM(B113:F113) -> 81306966000
A114: 经营净现金流超过归属净利润的金额 | B114: =B113-B105 -> 22043536000 | C114: =C113-C105 -> -4707445000 | D114: =D113-D105 -> -11285166000 | E114: =E113-E105 -> -9737045000 | F114: =F113-F105 -> -12166897000 | G114: =G113-G105 -> 5103280000 | H114: =H113-H105 -> -7353800000 | I114: =SUM(B114:H114) -> -18103537000 | J114: =SUM(B114:F114) -> -15853017000
A115: 自由现金流占比营业收入% | B115: =B112/B117 -> 0.071155106 | C115: =C112/C117 -> 0.014207957 | D115: =D112/D117 -> 0.0061181344 | E115: =E112/E117 -> 0.0094663978 | F115: =F112/F117 -> 0.0082722804 | G115: =G112/G117 -> 0.044116714 | H115: =H112/H117 -> 0.021374355 | I115: =I112/I117 -> 0.025419138 | J115: =J112/J117 -> 0.022627312
I116: =SUM(B116:H116) -> 0 | J116: =SUM(B116:F116) -> 0
A117: 营业收入（非营业总收入） | B117: =工业富联利润表!C4 -> 476340107000 | C117: =工业富联利润表!G4 -> 511849579000 | D117: =工业富联利润表!K4 -> 439557195000 | E117: =工业富联利润表!L4 -> 431785888000 | F117: =工业富联利润表!M4 -> 408697581000 | G117: =工业富联利润表!N4 -> 415377697000 | H117: =工业富联利润表!O4 -> 354543851000 | I117: =SUM(B117:H117) -> 3038151898000 | J117: =SUM(B117:F117) -> 2268230350000
A118: 利息费用(财务费用） | B118: =工业富联利润表!C10 -> -585810000 | C118: =工业富联利润表!G10 -> -703542000 | D118: =工业富联利润表!K10 -> -826389000 | E118: =工业富联利润表!L10 -> -236295000 | F118: =工业富联利润表!M10 -> -735316000 | G118: =工业富联利润表!N10 -> -324098000 | H118: =工业富联利润表!O10 -> 855147000 | I118: =SUM(B118:H118) -> -2556303000 | J118: =SUM(B118:F118) -> -3087352000
A119: 应收账款期末值 | B119: =工业富联资产负债表!C9 -> 88466866000 | C119: =工业富联资产负债表!G9 -> 97672920000 | D119: =工业富联资产负债表!K9 -> 87029697000 | E119: =工业富联资产负债表!L9 -> 86827495000 | F119: =工业富联资产负债表!M9 -> 84643735000 | G119: =工业富联资产负债表!N9 -> 86116982000 | H119: =工业富联资产负债表!O9 -> 78513196000
A120: 存货期末值 | B120: =工业富联资产负债表!C17 -> 76683349000 | C120: =工业富联资产负债表!G17 -> 77321754000 | D120: =工业富联资产负债表!K17 -> 71927837000 | E120: =工业富联资产负债表!L17 -> 45353900000 | F120: =工业富联资产负债表!M17 -> 41645951000 | G120: =工业富联资产负债表!N17 -> 37467635000 | H120: =工业富联资产负债表!O17 -> 35551035000
A121: 固定资产&CIP净额合计 | B121: =工业富联资产负债表!C100 -> 20219622000 | C121: =工业富联资产负债表!G100 -> 16638411000 | D121: =工业富联资产负债表!K100 -> 10908229000 | E121: =工业富联资产负债表!L100 -> 7766855000 | F121: =工业富联资产负债表!M100 -> 7090266000 | G121: =工业富联资产负债表!N100 -> 8.097145e+09 | H121: =工业富联资产负债表!O100 -> 9760048000
A122: 归属股东权益期末值 | B122: =工业富联资产负债表!C92 -> 140187453000 | C122: =工业富联资产负债表!G92 -> 128975192000 | D122: =工业富联资产负债表!K92 -> 119180602000 | E122: =工业富联资产负债表!L92 -> 103752549000 | F122: =工业富联资产负债表!M92 -> 89280680000 | G122: =工业富联资产负债表!N92 -> 72294634000 | H122: =工业富联资产负债表!O92 -> 28161059000
A123: 资产总额 | B123: =工业富联资产负债表!C48 -> 287705301000 | C123: =工业富联资产负债表!G48 -> 284187662000 | D123: =工业富联资产负债表!K48 -> 266608775000 | E123: =工业富联资产负债表!L48 -> 225513944000 | F123: =工业富联资产负债表!M48 -> 205612945000 | G123: =工业富联资产负债表!N48 -> 200603324000 | H123: =工业富联资产负债表!O48 -> 148596241000
A125: 应收账款周转率=销售收入/期末应收账款 | B125: =B117/B119 -> 5.38439 | C125: =C117/C119 -> 5.2404451 | D125: =D117/D119 -> 5.0506575 | E125: =E117/E119 -> 4.9729166 | F125: =F117/F119 -> 4.8284446 | G125: =G117/G119 -> 4.8234121 | H125: =H117/H119 -> 4.5157231
A126: 存货周转率=销售收入/期末存货 | B126: =B117/B120 -> 6.2117802 | C126: =C117/C120 -> 6.6197357 | D126: =D117/D120 -> 6.111086 | E126: =E117/E120 -> 9.5203695 | F126: =F117/F120 -> 9.813621 | G126: =G117/G120 -> 11.086307 | H126: =H117/H120 -> 9.9728138
A127: 总资产收益率=(归属净利+利息费用）/资产总额 | B127: =(B105+B118)/B123 -> 0.071094912 | C127: =(C105+C118)/C123 -> 0.068157533 | D127: =(D105+D118)/D123 -> 0.071953228 | E127: =(E105+E118)/E123 -> 0.076245786 | F127: =(F105+F118)/F123 -> 0.086915092 | G127: =(G105+G118)/G123 -> 0.082641746 | H127: =(H105+H118)/H123 -> 0.1125382
A128: ROE=归属净利/归属股东权益 | B128: =B105/B122 -> 0.15008614 | C128: =C105/C122 -> 0.15563514 | D128: =D105/D122 -> 0.16789436 | E128: =E105/E122 -> 0.16800342 | F128: =F105/F122 -> 0.20840101 | G128: =G105/G122 -> 0.23379753 | H128: =H105/H122 -> 0.56345917
A129: 实际资产负债率 | B129: =工业富联资产负债表!C97 -> 0.51034808 | C129: =工业富联资产负债表!G97 -> 0.54364597 | D129: =工业富联资产负债表!K97 -> 0.55068473 | E129: =工业富联资产负债表!L97 -> 0.53743878 | F129: =工业富联资产负债表!M97 -> 0.56536056 | G129: =工业富联资产负债表!N97 -> 0.63932989 | H129: =工业富联资产负债表!O97 -> 0.81029175
A130: 毛利率 | B130: =工业富联利润表!C34 -> 0.080563877 | C130: =工业富联利润表!G34 -> 0.0726225 | D130: =工业富联利润表!K34 -> 0.083072757 | E130: =工业富联利润表!L34 -> 0.083529043 | F130: =工业富联利润表!M34 -> 0.083794509 | G130: =工业富联利润表!N34 -> 0.086407427 | H130: =工业富联利润表!O34 -> 0.1014314
A131: 净利润率 | B131: =工业富联利润表!C35 -> 0.044124592 | C131: =工业富联利润表!G35 -> 0.039237873 | D131: =工业富联利润表!K35 -> 0.045556611 | E131: =工业富联利润表!L35 -> 0.040359568 | F131: =工业富联利润表!M35 -> 0.045525222 | G131: =工业富联利润表!N35 -> 0.040704056 | H131: =工业富联利润表!O35 -> 0.045748716
A132: 所得税率 | B132: =工业富联利润表!C36 -> 0.091063739 | C132: =工业富联利润表!G36 -> 0.085558113 | D132: =工业富联利润表!K36 -> 0.1027438 | E132: =工业富联利润表!L36 -> 0.1174521 | F132: =工业富联利润表!M36 -> 0.11955025 | G132: =工业富联利润表!N36 -> 0.15763306 | H132: =工业富联利润表!O36 -> 0.19067366
A134: 购建固定资产、无形资产和其他长期资产所支付的现金 | B134: =工业富联现金流量表!C21 -> 9189698000 | C134: =工业富联现金流量表!G21 -> 8093290000 | D134: =工业富联现金流量表!K21 -> 6035315000 | E134: =工业富联现金流量表!L21 -> 3606281000 | F134: =工业富联现金流量表!M21 -> 3058426000 | G134: =工业富联现金流量表!N21 -> 3680488000 | H134: =工业富联现金流量表!O21 -> 935661000
A135: 固定资产折旧、油气资产折耗、生产性物资折旧 | B135: =工业富联现金流量表!C49 -> 4449463000 | C135: =工业富联现金流量表!G49 -> 3220238000 | D135: =工业富联现金流量表!K49 -> 2515669000 | E135: =工业富联现金流量表!L49 -> 2432955000 | F135: =工业富联现金流量表!M49 -> 2746040000 | G135: =工业富联现金流量表!N49 -> 3867919000 | H135: =工业富联现金流量表!O49 -> 3686021000
A136: 无形资产摊销 | B136: =工业富联现金流量表!C50 -> 0 | C136: =工业富联现金流量表!G50 -> 0 | D136: =工业富联现金流量表!K50 -> 0 | E136: =工业富联现金流量表!L50 -> 0 | F136: =工业富联现金流量表!M50 -> 0 | G136: =工业富联现金流量表!N50 -> 0 | H136: =工业富联现金流量表!O50 -> 0
A137: 长期待摊费用摊销 | B137: =工业富联现金流量表!C51 -> 0 | C137: =工业富联现金流量表!G51 -> 0 | D137: =工业富联现金流量表!K51 -> 0 | E137: =工业富联现金流量表!L51 -> 0 | F137: =工业富联现金流量表!M51 -> 0 | G137: =工业富联现金流量表!N51 -> 0 | H137: =工业富联现金流量表!O51 -> 0
A138: 购建-∑摊销折旧（净增加） | B138: =B134-SUM(B135:B137) -> 4740235000 | C138: =C134-SUM(C135:C137) -> 4873052000 | D138: =D134-SUM(D135:D137) -> 3519646000 | E138: =E134-SUM(E135:E137) -> 1173326000 | F138: =F134-SUM(F135:F137) -> 312386000 | G138: =G134-SUM(G135:G137) -> -187431000 | H138: =H134-SUM(H135:H137) -> -2750360000

Sheet 罗杰斯分析表
A1: =工业富联资产负债变动表!I1 -> 2017-2023 | B1: 单位：亿元 | C1: =工业富联资产负债变动表!B1 -> 20231231 | D1: =工业富联资产负债变动表!C1 -> 20221231 | E1: =工业富联资产负债变动表!D1 -> 20211231 | F1: =工业富联资产负债变动表!E1 -> 20201231 | G1: =工业富联资产负债变动表!F1 -> 20191231 | H1: =工业富联资产负债变动表!G1 -> 20181231 | I1: =工业富联资产负债变动表!H1 -> 20171231
A2: 营业总收入 | B2: 来自利润表 | C2: =工业富联利润表!C3/100000000 -> 4763.4011 | D2: =工业富联利润表!G3/100000000 -> 5118.4958 | E2: =工业富联利润表!K3/100000000 -> 4395.5719 | F2: =工业富联利润表!L3/100000000 -> 4317.8589 | G2: =工业富联利润表!M3/100000000 -> 4086.9758 | H2: =工业富联利润表!N3/100000000 -> 4153.777 | I2: =工业富联利润表!O3/100000000 -> 3545.4385
A3: 营业收入（非营业总收入） | B3: 来自利润表 | C3: =工业富联利润表!C4/100000000 -> 4763.4011 | D3: =工业富联利润表!G4/100000000 -> 5118.4958 | E3: =工业富联利润表!K4/100000000 -> 4395.5719 | F3: =工业富联利润表!L4/100000000 -> 4317.8589 | G3: =工业富联利润表!M4/100000000 -> 4086.9758 | H3: =工业富联利润表!N4/100000000 -> 4153.777 | I3: =工业富联利润表!O4/100000000 -> 3545.4385
A4: 营业收入（非营业总收入） | B4: 来自变动表 | C4: =工业富联资产负债变动表!B117/100000000 -> 4763.4011 | D4: =工业富联资产负债变动表!C117/100000000 -> 5118.4958 | E4: =工业富联资产负债变动表!D117/100000000 -> 4395.5719 | F4: =工业富联资产负债变动表!E117/100000000 -> 4317.8589 | G4: =工业富联资产负债变动表!F117/100000000 -> 4086.9758 | H4: =工业富联资产负债变动表!G117/100000000 -> 4153.777 | I4: =工业富联资产负债变动表!H117/100000000 -> 3545.4385
A6: 折旧 | B6: 固定资产折旧、油气资产折耗、生产性物资折旧 | C6: =工业富联资产负债变动表!B135/100000000 -> 44.49463 | D6: =工业富联资产负债变动表!C135/100000000 -> 32.20238 | E6: =工业富联资产负债变动表!D135/100000000 -> 25.15669 | F6: =工业富联资产负债变动表!E135/100000000 -> 24.32955 | G6: =工业富联资产负债变动表!F135/100000000 -> 27.4604 | H6: =工业富联资产负债变动表!G135/100000000 -> 38.67919 | I6: =工业富联资产负债变动表!H135/100000000 -> 36.86021
A7: 折旧占比营业收入% | C7: =C6/C3 -> 0.0093409371 | D7: =D6/D3 -> 0.0062913757 | E7: =E6/E3 -> 0.0057231892 | F7: =F6/F3 -> 0.005634633 | G7: =G6/G3 -> 0.0067190023 | H7: =H6/H3 -> 0.0093118119 | I7: =I6/I3 -> 0.010396517
A9: 毛利润 | B9: ‘=营业收入-营业成本 | C9: =(工业富联利润表!C4-工业富联利润表!C6)/100000000 -> 383.75806 | D9: =(工业富联利润表!G4-工业富联利润表!G6)/100000000 -> 371.71796 | E9: =(工业富联利润表!K4-工业富联利润表!K6)/100000000 -> 365.15228 | F9: =(工业富联利润表!L4-工业富联利润表!L6)/100000000 -> 360.66662 | G9: =(工业富联利润表!M4-工业富联利润表!M6)/100000000 -> 342.46613 | H9: =(工业富联利润表!N4-工业富联利润表!N6)/100000000 -> 358.91718 | I9: =(工业富联利润表!O4-工业富联利润表!O6)/100000000 -> 359.61879
A10: 毛利率 | B10: ‘=毛利润/营业收入 | C10: =C9/C4 -> 0.080563877 | D10: =D9/D4 -> 0.0726225 | E10: =E9/E4 -> 0.083072757 | F10: =F9/F4 -> 0.083529043 | G10: =G9/G4 -> 0.083794509 | H10: =H9/H4 -> 0.086407427 | I10: =I9/I4 -> 0.1014314
A11: 验证（毛利率来自变动表） | C11: =工业富联资产负债变动表!B130 -> 0.080563877 | D11: =工业富联资产负债变动表!C130 -> 0.0726225 | E11: =工业富联资产负债变动表!D130 -> 0.083072757 | F11: =工业富联资产负债变动表!E130 -> 0.083529043 | G11: =工业富联资产负债变动表!F130 -> 0.083794509 | H11: =工业富联资产负债变动表!G130 -> 0.086407427 | I11: =工业富联资产负债变动表!H130 -> 0.1014314
A13: 营业外收入 | C13: =工业富联利润表!C18/100000000 -> 1.23561 | D13: =工业富联利润表!G18/100000000 -> 1.21232 | E13: =工业富联利润表!K18/100000000 -> 0.83798 | F13: =工业富联利润表!L18/100000000 -> 0.91955 | G13: =工业富联利润表!M18/100000000 -> 0.85168 | H13: =工业富联利润表!N18/100000000 -> 0.381 | I13: =工业富联利润表!O18/100000000 -> 0.88311
A14: 营业外支出 | C14: =工业富联利润表!C19/100000000 -> 0.66391 | D14: =工业富联利润表!G19/100000000 -> 0.30581 | E14: =工业富联利润表!K19/100000000 -> 1.63652 | F14: =工业富联利润表!L19/100000000 -> 0.61724 | G14: =工业富联利润表!M19/100000000 -> 0.59301 | H14: =工业富联利润表!N19/100000000 -> 0.49242 | I14: =工业富联利润表!O19/100000000 -> 0.04175
A16: 利润总额（税前） | C16: =工业富联利润表!C21/100000000 -> 231.24078 | D16: =工业富联利润表!G21/100000000 -> 219.63002 | E16: =工业富联利润表!K21/100000000 -> 223.17746 | F16: =工业富联利润表!L21/100000000 -> 197.45888 | G16: =工业富联利润表!M21/100000000 -> 211.32436 | H16: =工业富联利润表!N21/100000000 -> 200.71487 | I16: =工业富联利润表!O21/100000000 -> 200.41268
A17: 税前利润率 | B17: ‘=利润总额/营业收入 | C17: =C16/C4 -> 0.04854531 | D17: =D16/D4 -> 0.042909095 | E17: =E16/E4 -> 0.050773247 | F17: =F16/F4 -> 0.04573074 | G17: =G16/G4 -> 0.05170678 | H17: =H16/H4 -> 0.048321051 | I17: =I16/I4 -> 0.056526909
A18: 所得税费用 | C18: =工业富联利润表!C22/100000000 -> 21.05765 | D18: =工业富联利润表!G22/100000000 -> 18.79113 | E18: =工业富联利润表!K22/100000000 -> 22.9301 | F18: =工业富联利润表!L22/100000000 -> 23.19196 | G18: =工业富联利润表!M22/100000000 -> 25.26388 | H18: =工业富联利润表!N22/100000000 -> 31.6393 | I18: =工业富联利润表!O22/100000000 -> 38.21342
A19: 所得税税率 | B19: ‘=所得税费用/利润总额 | C19: =C18/C16 -> 0.091063739 | D19: =D18/D16 -> 0.085558113 | E19: =E18/E16 -> 0.1027438 | F19: =F18/F16 -> 0.1174521 | G19: =G18/G16 -> 0.11955025 | H19: =H18/H16 -> 0.15763306 | I19: =I18/I16 -> 0.19067366
A20: 净利润 | C20: =C16-C18 -> 210.18313 | D20: =D16-D18 -> 200.83889 | E20: =E16-E18 -> 200.24736 | F20: =F16-F18 -> 174.26692 | G20: =G16-G18 -> 186.06048 | H20: =H16-H18 -> 169.07557 | I20: =I16-I18 -> 162.19926
A21: 验证（净利润来自利润表） | C21: =工业富联利润表!C23/100000000 -> 210.18313 | D21: =工业富联利润表!G23/100000000 -> 200.83889 | E21: =工业富联利润表!K23/100000000 -> 200.24736 | F21: =工业富联利润表!L23/100000000 -> 174.26692 | G21: =工业富联利润表!M23/100000000 -> 186.06048 | H21: =工业富联利润表!N23/100000000 -> 169.07557 | I21: =工业富联利润表!O23/100000000 -> 162.19926
A22: 扣非净利润率 | B22: ‘=扣非净利润/营业收入 | C22: =C27/C3 -> 0.042427668 | D22: =D27/D3 -> 0.035967598 | E22: =E27/E3 -> 0.042269812 | F22: =F27/F3 -> 0.037958628 | G22: =G27/G3 -> 0.041546612 | H22: =H27/H3 -> 0.040252522 | I22: =I27/I3 -> 0.044987383
A24: 少数股东损益 | C24: =工业富联利润表!C25/100000000 -> -0.2188 | D24: =工业富联利润表!G25/100000000 -> 0.10817 | E24: =工业富联利润表!K25/100000000 -> 0.14985 | F24: =工业富联利润表!L25/100000000 -> -0.04091 | G24: =工业富联利润表!M25/100000000 -> -0.00136 | H24: =工业富联利润表!N25/100000000 -> 0.0525 | I24: =工业富联利润表!O25/100000000 -> 3.52319
A25: 归属于母公司股东的净利润 | B25: 来自利润表 | C25: =工业富联利润表!C24/100000000 -> 210.40193 | D25: =工业富联利润表!G24/100000000 -> 200.73072 | E25: =工业富联利润表!K24/100000000 -> 200.09751 | F25: =工业富联利润表!L24/100000000 -> 174.30783 | G25: =工业富联利润表!M24/100000000 -> 186.06184 | H25: =工业富联利润表!N24/100000000 -> 169.02307 | I25: =工业富联利润表!O24/100000000 -> 158.67607
A26: 归属净利润 | B26: 来自东财F10 | C26: =工业富联东财年度指标!B4 -> 210.4 | D26: =工业富联东财年度指标!C4 -> 200.7 | E26: =工业富联东财年度指标!D4 -> 200.1 | F26: =工业富联东财年度指标!E4 -> 174.3 | G26: =工业富联东财年度指标!F4 -> 186.1 | H26: =工业富联东财年度指标!G4 -> 169 | I26: =工业富联东财年度指标!H4 -> 158.7
A27: 扣非净利润 | B27: 来自东财F10 | C27: =工业富联东财年度指标!B5 -> 202.1 | D27: =工业富联东财年度指标!C5 -> 184.1 | E27: =工业富联东财年度指标!D5 -> 185.8 | F27: =工业富联东财年度指标!E5 -> 163.9 | G27: =工业富联东财年度指标!F5 -> 169.8 | H27: =工业富联东财年度指标!G5 -> 167.2 | I27: =工业富联东财年度指标!H5 -> 159.5
A29: 年末股本数（亿股） | C29: =1986610.61/10000 -> 198.66106 | D29: =1985959.29/10000 -> 198.59593 | E29: =1986510.4/10000 -> 198.65104 | F29: =1986510.4/10000 -> 198.65104 | G29: =1986510.4/10000 -> 198.65104 | H29: =1986510.4/10000 -> 198.65104
A30: 每股收益 | B30: ‘=归属净利润/总股本数 | C30: =C25/C29 -> 1.0591 | D30: =D25/D29 -> 1.0107494 | E30: =E25/E29 -> 1.0072815 | F30: =F25/F29 -> 0.87745742 | G30: =G25/G29 -> 0.93662656 | H30: =H25/H29 -> 0.85085419 | I30: =I25/I29 -> #DIV/0!
A31: 每股扣非收益 | B31: ‘=扣非净利润/总股本数 | C31: =C27/C29 -> 1.0173106 | D31: =D27/D29 -> 0.92700792 | E31: =E27/E29 -> 0.93530847 | F31: =F27/F29 -> 0.8250649 | G31: =G27/G29 -> 0.85476522 | H31: =H27/H29 -> 0.84167694
A32: 每股分红 | C32: 0.58 | D32: 0.55 | E32: 0.5 | F32: 0.25 | G32: 0.2 | H32: 0.129
A33: 分红率 | B33: ‘=每股分红/每股收益 | C33: =C32/C30 -> 0.54763478 | D33: =D32/D30 -> 0.5441507 | E33: =E32/E30 -> 0.49638559 | F33: =F32/F30 -> 0.28491411 | G33: =G32/G30 -> 0.21353228 | H33: =H32/H30 -> 0.15161235
A35: 每股净资产 | B35: ‘=股东权益/年末股本数 | C35: =C36/C29 -> 7.0566145 | D35: =D36/D29 -> 6.4943523 | E35: =E36/E29 -> 5.9994955 | F35: =F36/F29 -> 5.2228546 | G35: =G36/G29 -> 4.4943475 | H35: =H36/H29 -> 3.6392779 | I35: =I36/I29 -> #DIV/0!
A36: 股东权益（年末净资产） | C36: =工业富联资产负债变动表!B122/100000000 -> 1401.8745 | D36: =工业富联资产负债变动表!C122/100000000 -> 1289.7519 | E36: =工业富联资产负债变动表!D122/100000000 -> 1191.806 | F36: =工业富联资产负债变动表!E122/100000000 -> 1037.5255 | G36: =工业富联资产负债变动表!F122/100000000 -> 892.8068 | H36: =工业富联资产负债变动表!G122/100000000 -> 722.94634 | I36: =工业富联资产负债变动表!H122/100000000 -> 281.61059
A37: ROE | B37: ‘=归属净利润/股东权益 | C37: =C25/C36 -> 0.15008614 | D37: =D25/D36 -> 0.15563514 | E37: =E25/E36 -> 0.16789436 | F37: =F25/F36 -> 0.16800342 | G37: =G25/G36 -> 0.20840101 | H37: =H25/H36 -> 0.23379753 | I37: =I25/I36 -> 0.56345917
A38: 扣非ROE | B38: ‘=扣非净利润/股东权益 | C38: =C27/C36 -> 0.14416411 | D38: =D27/D36 -> 0.14274063 | E38: =E27/E36 -> 0.15589785 | F38: =F27/F36 -> 0.15797202 | G38: =G27/G36 -> 0.19018672 | H38: =H27/H36 -> 0.23127581 | I38: =I27/I36 -> 0.56638495
A40: 权益负债率 | B40: ‘=负债总额/股东权益 | C40: =工业富联资产负债变动表!B123/工业富联资产负债变动表!B122-1 -> 1.05229 | D40: =工业富联资产负债变动表!C123/工业富联资产负债变动表!C122-1 -> 1.2034289 | E40: =工业富联资产负债变动表!D123/工业富联资产负债变动表!D122-1 -> 1.2370148 | F40: =工业富联资产负债变动表!E123/工业富联资产负债变动表!E122-1 -> 1.173575 | G40: =工业富联资产负债变动表!F123/工业富联资产负债变动表!F122-1 -> 1.3029948 | H40: =工业富联资产负债变动表!G123/工业富联资产负债变动表!G122-1 -> 1.7748024 | I40: =工业富联资产负债变动表!H123/工业富联资产负债变动表!H122-1 -> 4.2766567
B41: ‘=资产负债率/（1-资产负债率） | C41: =工业富联资产负债变动表!B129/(1-工业富联资产负债变动表!B129) -> 1.0422671 | D41: =工业富联资产负债变动表!C129/(1-工业富联资产负债变动表!C129) -> 1.1912812 | E41: =工业富联资产负债变动表!D129/(1-工业富联资产负债变动表!D129) -> 1.2256088 | F41: =工业富联资产负债变动表!E129/(1-工业富联资产负债变动表!E129) -> 1.161876 | G41: =工业富联资产负债变动表!F129/(1-工业富联资产负债变动表!F129) -> 1.3007576 | H41: =工业富联资产负债变动表!G129/(1-工业富联资产负债变动表!G129) -> 1.7726168 | I41: =工业富联资产负债变动表!H129/(1-工业富联资产负债变动表!H129) -> 4.271252
A42: 实际资产负债率 | C42: =工业富联资产负债变动表!B129 -> 0.51034808 | D42: =工业富联资产负债变动表!C129 -> 0.54364597 | E42: =工业富联资产负债变动表!D129 -> 0.55068473 | F42: =工业富联资产负债变动表!E129 -> 0.53743878 | G42: =工业富联资产负债变动表!F129 -> 0.56536056 | H42: =工业富联资产负债变动表!G129 -> 0.63932989 | I42: =工业富联资产负债变动表!H129 -> 0.81029175
A44: 应收账款&应收票据/营业收入 | C44: =工业富联资产负债表!C7/工业富联利润表!C4 -> 0.18573754 | D44: =工业富联资产负债表!G7/工业富联利润表!G4 -> 0.19085643 | E44: =工业富联资产负债表!K7/工业富联利润表!K4 -> 0.19800345 | F44: =工业富联资产负债表!L7/工业富联利润表!L4 -> 0.20108947 | G44: =工业富联资产负债表!M7/工业富联利润表!M4 -> 0.20710603 | H44: =工业富联资产负债表!N7/工业富联利润表!N4 -> 0.20732434 | I44: =工业富联资产负债表!O7/工业富联利润表!O4 -> 0.22144848
A45: 存货/营业收入 | C45: =工业富联资产负债表!C17/工业富联利润表!C4 -> 0.16098445 | D45: =工业富联资产负债表!G17/工业富联利润表!G4 -> 0.15106343 | E45: =工业富联资产负债表!K17/工业富联利润表!K4 -> 0.16363704 | F45: =工业富联资产负债表!L17/工业富联利润表!L4 -> 0.10503794 | G45: =工业富联资产负债表!M17/工业富联利润表!M4 -> 0.10189919 | H45: =工业富联资产负债表!N17/工业富联利润表!N4 -> 0.090201364 | I45: =工业富联资产负债表!O17/工业富联利润表!O4 -> 0.1002726
A47: 广告
A48: 研发 | C48: =工业富联利润表!C11/100000000 -> 108.11207 | D48: =工业富联利润表!G11/100000000 -> 115.88014 | E48: =工业富联利润表!K11/100000000 -> 108.35032 | F48: =工业富联利润表!L11/100000000 -> 100.37729 | G48: =工业富联利润表!M11/100000000 -> 94.2718 | H48: =工业富联利润表!N11/100000000 -> 89.98879 | I48: =工业富联利润表!O11/100000000 -> 0
A49: 资本性支出（来自现金流量表） | B49: ‘=（FA期末+CIP期末）-（FA期初+CIP期初）+计提折旧 | C49: =工业富联资产负债变动表!B134/100000000 -> 91.89698 | D49: =工业富联资产负债变动表!C134/100000000 -> 80.9329 | E49: =工业富联资产负债变动表!D134/100000000 -> 60.35315 | F49: =工业富联资产负债变动表!E134/100000000 -> 36.06281 | G49: =工业富联资产负债变动表!F134/100000000 -> 30.58426 | H49: =工业富联资产负债变动表!G134/100000000 -> 36.80488
A50: 资本性支出与折旧比率 | C50: =C49/D6 -> 2.8537326 | D50: =D49/E6 -> 3.2171522 | E50: =E49/F6 -> 2.4806521 | F50: =F49/G6 -> 1.313266 | G50: =G49/H6 -> 0.79071614 | H50: =H49/I6 -> 0.99849892
A51: 资本性支出与厂房和设备原值比率 | C51: =C49/工业富联资产负债变动表!B121*100000000 -> 0.45449406 | D51: =D49/工业富联资产负债变动表!C121*100000000 -> 0.48642205 | E51: =E49/工业富联资产负债变动表!D121*100000000 -> 0.55328092 | F51: =F49/工业富联资产负债变动表!E121*100000000 -> 0.46431677 | G51: =G49/工业富联资产负债变动表!F121*100000000 -> 0.43135561 | H51: =H49/工业富联资产负债变动表!G121*100000000 -> 0.45454145
A52: 资本性支出与净市盈率比值
A54: 股价波动幅度
A56: 累计
A57: 累计销售
A59: 商店数目
A60: 销售与商店比率
A62: 财务费用 | C62: =工业富联利润表!C10/100000000 -> -5.8581 | D62: =工业富联利润表!G10/100000000 -> -7.03542 | E62: =工业富联利润表!K10/100000000 -> -8.26389 | F62: =工业富联利润表!L10/100000000 -> -2.36295 | G62: =工业富联利润表!M10/100000000 -> -7.35316 | H62: =工业富联利润表!N10/100000000 -> -3.24098 | I62: =工业富联利润表!O10/100000000 -> 8.55147
A63: 财务费用占比营业收入% | C63: =C62/C3 -> -0.0012298146 | D63: =D62/D3 -> -0.0013745093 | E63: =E62/E3 -> -0.0018800489 | F63: =F62/F3 -> -0.0005472504 | G63: =G62/G3 -> -0.001799169 | H63: =H62/H3 -> -0.00078024892 | I63: =I62/I3 -> 0.002411964

Sheet 工业富联资产负债变动明细表
A1: 报表日期 | B1: =工业富联资产负债变动表!I1 -> 2017-2023 | D1: =B1 -> 2017-2023
A2: 单位：人民币亿元 | B2: =工业富联资产负债变动表!I2 -> 最近7年合计 | D2: =B2 -> 最近7年合计
A3: ∆流动资产 | C3: ∆流动负债
A4: ∆货币资金 | B4: =工业富联资产负债变动表!I4/100000000 -> 785.27776 | C4: ∆短期借款 | D4: =工业富联资产负债变动表!I50/100000000 -> 394.47981 | F4: ∆流动资产合计 | G4: =B23 -> 1305.6139 | H4: ∆流动负债合计 | I4: =D22 -> 800.48348
A5: ∆交易性金融资产 | B5: =工业富联资产负债变动表!I5/100000000 -> 3.3326 | C5: ∆交易性金融负债 | D5: =工业富联资产负债变动表!I51/100000000 -> 0.13133
A6: ∆衍生金融资产 | B6: =工业富联资产负债变动表!I6/100000000 -> 2.79394 | C6: ∆应付票据及应付账款53+54 | D6: =工业富联资产负债变动表!I52/100000000 -> 320.15435 | H6: ∆非流动负债合计 | I6: =D35 -> 88.40597
A7: ∆应收票据及应收账款8+9 | B7: =工业富联资产负债变动表!I7/100000000 -> 339.00464 | C7: ∆应付票据 | D7: =工业富联资产负债变动表!I53/100000000 -> 0
A8: ∆应收票据 | B8: =工业富联资产负债变动表!I8/100000000 -> 0.07375 | C8: ∆应付账款 | D8: =工业富联资产负债变动表!I54/100000000 -> 320.15435 | F8: ∆非流动资产合计 | G8: =B47 -> 214.00252 | H8: ∆所有者权益(或股东权益)合计 | I8: =D48 -> 630.72697
A9: ∆应收账款 | B9: =工业富联资产负债变动表!I9/100000000 -> 338.93089 | C9: ∆预收款项 | D9: =工业富联资产负债变动表!I55/100000000 -> -1.84083
A10: ∆应收款项融资 | B10: =工业富联资产负债变动表!I10/100000000 -> 0 | C10: ∆应付手续费及佣金 | D10: =工业富联资产负债变动表!I56/100000000 -> 1.90316 | F10: ∆资产总计 | G10: =G4+G8 -> 1519.6164 | H10: ∆负债和所有者权益(或股东权益)总计 | I10: =I4+I6+I8 -> 1519.6164
A11: ∆预付款项 | B11: =工业富联资产负债变动表!I11/100000000 -> 1.40847 | C11: ∆应付职工薪酬 | D11: =工业富联资产负债变动表!I57/100000000 -> 8.08185
A12: ∆其他应收款(合计)13+14+15 | B12: =工业富联资产负债变动表!I12/100000000 -> -317.4742 | C12: ∆应交税费 | D12: =工业富联资产负债变动表!I58/100000000 -> 8.95051
A13: ∆应收利息 | B13: =工业富联资产负债变动表!I13/100000000 -> 0 | C13: ∆其他应付款(合计)60+61+62 | D13: =工业富联资产负债变动表!I59/100000000 -> 55.20425
A14: ∆应收股利 | B14: =工业富联资产负债变动表!I14/100000000 -> 0 | C14: ∆应付利息 | D14: =工业富联资产负债变动表!I60/100000000 -> 0
A15: ∆其他应收款 | B15: =工业富联资产负债变动表!I15/100000000 -> -317.4742 | C15: ∆应付股利 | D15: =工业富联资产负债变动表!I61/100000000 -> 1.31036
A16: ∆买入返售金融资产 | B16: =工业富联资产负债变动表!I16/100000000 -> 0 | C16: ∆其他应付款 | D16: =工业富联资产负债变动表!I62/100000000 -> 53.89389
A17: ∆存货 | B17: =工业富联资产负债变动表!I17/100000000 -> 481.21909 | C17: ∆预提费用 | D17: =工业富联资产负债变动表!I63/100000000 -> 0
A18: ∆划分为持有待售的资产 | B18: =工业富联资产负债变动表!I18/100000000 -> 0 | C18: ∆一年内的递延收益 | D18: =工业富联资产负债变动表!I64/100000000 -> 0
A19: ∆一年内到期的非流动资产 | B19: =工业富联资产负债变动表!I19/100000000 -> 0 | C19: ∆应付短期债券 | D19: =工业富联资产负债变动表!I65/100000000 -> 0
A20: ∆待摊费用 | B20: =工业富联资产负债变动表!I20/100000000 -> 0 | C20: ∆一年内到期的非流动负债 | D20: =工业富联资产负债变动表!I66/100000000 -> 6.68738
A21: ∆待处理流动资产损益 | B21: =工业富联资产负债变动表!I21/100000000 -> 0 | C21: ∆其他流动负债 | D21: =工业富联资产负债变动表!I67/100000000 -> 6.73167
A22: ∆其他流动资产 | B22: =工业富联资产负债变动表!I22/100000000 -> 10.0516 | C22: ∆流动负债合计 | D22: =工业富联资产负债变动表!I68/100000000 -> 800.48348
A23: ∆流动资产合计 | B23: =工业富联资产负债变动表!I23/100000000 -> 1305.6139 | C23: ∆非流动负债
A24: ∆非流动资产 | C24: ∆长期借款 | D24: =工业富联资产负债变动表!I70/100000000 -> 70.96943
A25: ∆发放贷款及垫款 | B25: =工业富联资产负债变动表!I25/100000000 -> 0 | C25: ∆应付债券 | D25: =工业富联资产负债变动表!I71/100000000 -> 0
A26: ∆可供出售金融资产 | B26: =工业富联资产负债变动表!I26/100000000 -> 6.96471 | C26: ∆租赁负债 | D26: =工业富联资产负债变动表!I72/100000000 -> 10.10287
A27: ∆持有至到期投资 | B27: =工业富联资产负债变动表!I27/100000000 -> 0 | C27: ∆长期应付职工薪酬 | D27: =工业富联资产负债变动表!I73/100000000 -> 0
A28: ∆长期应收款 | B28: =工业富联资产负债变动表!I28/100000000 -> 0.62982 | C28: ∆长期应付款(合计)75+76 | D28: =工业富联资产负债变动表!I74/100000000 -> 0
A29: ∆长期股权投资 | B29: =工业富联资产负债变动表!I29/100000000 -> 71.42247 | C29: ∆长期应付款 | D29: =工业富联资产负债变动表!I75/100000000 -> 0
A30: ∆投资性房地产 | B30: =工业富联资产负债变动表!I30/100000000 -> -0.1982 | C30: ∆专项应付款 | D30: =工业富联资产负债变动表!I76/100000000 -> 0
A31: ∆在建工程(合计)32+33 | B31: =工业富联资产负债变动表!I31/100000000 -> 25.08056 | C31: ∆预计非流动负债 | D31: =工业富联资产负债变动表!I77/100000000 -> 2.5603
A32: ∆在建工程 | B32: =工业富联资产负债变动表!I32/100000000 -> 19.62448 | C32: ∆递延所得税负债 | D32: =工业富联资产负债变动表!I78/100000000 -> 2.03068
A33: ∆工程物资 | B33: =工业富联资产负债变动表!I33/100000000 -> 0 | C33: ∆长期递延收益 | D33: =工业富联资产负债变动表!I79/100000000 -> 2.74269
A34: ∆固定资产及清理(合计)35+36 | B34: =工业富联资产负债变动表!I34/100000000 -> 177.11566 | C34: ∆其他非流动负债 | D34: =工业富联资产负债变动表!I80/100000000 -> 0
A35: ∆固定资产净额 | B35: =工业富联资产负债变动表!I35/100000000 -> 63.52278 | C35: ∆非流动负债合计 | D35: =工业富联资产负债变动表!I81/100000000 -> 88.40597
A36: ∆固定资产清理 | B36: =工业富联资产负债变动表!I36/100000000 -> 0 | C36: ∆负债合计 | D36: =工业富联资产负债变动表!I82/100000000 -> 888.88945
A37: ∆生产性生物资产 | B37: =工业富联资产负债变动表!I37/100000000 -> 0 | C37: ∆所有者权益
A38: ∆公益性生物资产 | B38: =工业富联资产负债变动表!I38/100000000 -> 0 | C38: ∆实收资本(或股本) | D38: =工业富联资产负债变动表!I84/100000000 -> 198.66106
A39: ∆油气资产 | B39: =工业富联资产负债变动表!I39/100000000 -> 0 | C39: ∆资本公积 | D39: =工业富联资产负债变动表!I85/100000000 -> 13.19401
A40: ∆使用权资产 | B40: =工业富联资产负债变动表!I40/100000000 -> 15.71141 | C40: ∆减：库存股 | D40: =工业富联资产负债变动表!I86/100000000 -> 20.13975
A41: ∆无形资产 | B41: =工业富联资产负债变动表!I41/100000000 -> 7.60063 | C41: ∆其他综合收益 | D41: =工业富联资产负债变动表!I87/100000000 -> -14.97065
A42: ∆开发支出 | B42: =工业富联资产负债变动表!I42/100000000 -> 0 | C42: ∆专项储备 | D42: =工业富联资产负债变动表!I88/100000000 -> 0
A43: ∆商誉 | B43: =工业富联资产负债变动表!I43/100000000 -> 3.10153 | C43: ∆盈余公积 | D43: =工业富联资产负债变动表!I89/100000000 -> 51.51191
A44: ∆长期待摊费用 | B44: =工业富联资产负债变动表!I44/100000000 -> 24.35589 | C44: ∆一般风险准备 | D44: =工业富联资产负债变动表!I90/100000000 -> 0
A45: ∆递延所得税资产 | B45: =工业富联资产负债变动表!I45/100000000 -> -5.06724 | C45: ∆未分配利润 | D45: =工业富联资产负债变动表!I91/100000000 -> 400.58711
A46: ∆其他非流动资产 | B46: =工业富联资产负债变动表!I46/100000000 -> 6.33424 | C46: ∆归属于母公司股东权益合计 | D46: =工业富联资产负债变动表!I92/100000000 -> 628.84369
A47: ∆非流动资产合计 | B47: =工业富联资产负债变动表!I47/100000000 -> 214.00252 | C47: ∆少数股东权益 | D47: =工业富联资产负债变动表!I93/100000000 -> 1.88328
C48: ∆所有者权益(或股东权益)合计 | D48: =工业富联资产负债变动表!I94/100000000 -> 630.72697
A49: ∆资产总计 | B49: =工业富联资产负债变动表!I48/100000000 -> 1519.6164 | C49: ∆负债和所有者权益(或股东权益)总计 | D49: =工业富联资产负债变动表!I95/100000000 -> 1519.6164

Sheet 资产变化路径表7年
A1: 2017/1/1-2023/12/31（7年） | B1: 变动额 | E1: 变动额
A2: Δ货币资金及等价物 | B2: =工业富联资产负债变动表!I97 -> 80139832000 | D2: Δ短期借款 | E2: =工业富联资产负债变动表!I102 -> 39447981000
A3: Δ应收账款-Δ应付账款 | B3: =工业富联资产负债变动表!I98 -> 1877654000 | D3: Δ(预收-预付)账款 | E3: =工业富联资产负债变动表!I103 -> -324930000
A4: Δ存货 | B4: =工业富联资产负债变动表!I100 -> 48121909000
A5: Δ其他应收款-Δ其他应付款 | B5: =工业富联资产负债变动表!I99 -> -37136809000 | G5: 现金流量表 | H5: 差异
A6: Δ其他营运资本（不含预收账款） | B6: =工业富联资产负债变动表!I101 -> -3366493000 | F6: 现金分红 | G6: =工业富联现金流量表!P35 -> 40340350000 | H6: =G6-G10 -> 72657644600
A7: Δ金融资产 | B7: =工业富联资产负债变动表!I25+工业富联资产负债变动表!I26+工业富联资产负债变动表!I27 -> 696471000 | D7: Δ长期借款 | E7: =工业富联资产负债变动表!I70 -> 7096943000
A8: Δ长期应收款 | B8: =工业富联资产负债变动表!I28 -> 62982000 | D8: Δ长期债券 | E8: =工业富联资产负债变动表!I71 -> 0
A9: Δ长期股权投资 | B9: =工业富联资产负债变动表!I29 -> 7142247000 | D9: Δ其他长期负债 | E9: =工业富联资产负债变动表!I81-工业富联资产负债变动表!I70-工业富联资产负债变动表!I71 -> 1743654000 | F9: 归属净利润 | G9: =工业富联资产负债变动表!I105 -> 129929897000 | I9: 现金分红比例
A10: Δ投资性房地产 | B10: =工业富联资产负债变动表!I30 -> -19820000 | F10: 现金分红 | G10: =工业富联资产负债变动表!I106 -> -32317294600 | H10: =SUM(G9:G10) -> 97612602400 | I10: =-G10/G9 -> 0.2487287
A11: ΔFA&CIP | B11: =工业富联资产负债变动表!I32+工业富联资产负债变动表!I33+工业富联资产负债变动表!I35+工业富联资产负债变动表!I36 -> 8314726000 | F11: IPO&增发 | G11: =工业富联资产负债变动表!I107 -> 26722900000
A12: Δ生产性生物性/公益性生物性/油气/使用权资产 | B12: =工业富联资产负债变动表!I37+工业富联资产负债变动表!I38+工业富联资产负债变动表!I39+工业富联资产负债变动表!I40 -> 1571141000 | F12: CF净吸收投资 | G12: =工业富联现金流量表!P28-G11 -> 3808889000
A13: Δ无形资产 | B13: =工业富联资产负债变动表!I41 -> 760063000 | F13: 其他 | G13: =G14-G10-G11-G9-G12 -> -65260022400
A14: Δ开发支出 | B14: =工业富联资产负债变动表!I42 -> 0 | D14: Δ归属权益 | E14: =工业富联资产负债变动表!I92 -> 62884369000 | G14: =E14 -> 62884369000
A15: Δ商誉 | B15: =工业富联资产负债变动表!I43 -> 310153000
A16: Δ其他资产 | B16: =工业富联资产负债变动表!I44+工业富联资产负债变动表!I45+工业富联资产负债变动表!I46 -> 2562289000 | D16: Δ少数权益 | E16: =工业富联资产负债变动表!I93 -> 188328000
A17: 合计 | B17: =SUM(B2:B16) -> 111036345000 | D17: 合计 | E17: =SUM(E2:E16) -> 111036345000
E18: =B17-E17 -> 0
A19: ΔAR+Δ存货 | B19: =B3+B4 -> 49999563000 | D19: ∑归属净利润 | E19: =G9 -> 129929897000 | F19: =B19/E19 -> 0.38481954
A20: ΔFA&CIP | B20: =B11 -> 8314726000 | D20: ∑归属净利润 | E20: =E19 -> 129929897000 | F20: =B20/E20 -> 0.06399394
A21: 年平均自由现金流（7年） | B21: =(E20-B20)/7 -> 1.7373596e+10 | D21: 年平均自由现金流ROE | F21: =B21/(B26/B30) -> 0.11945509
B23: TTM（至2024Q1) | D23: TTM（至2023Q1) | E23: 同比增长率
A24: 过去12个月营业收入（非营业总收入） | B24: =SUM(工业富联利润表!B40:E40) -> 489139526000 | D24: =SUM(工业富联利润表!F40:I40) -> 512675653000 | E24: =B24/D24-1 -> -0.045908416
A25: 过去12个月营业成本 | B25: =SUM(工业富联利润表!B42:E42) -> 449493014000 | D25: =SUM(工业富联利润表!F42:I42) -> 474822792000 | E25: =B25/D25-1 -> -0.05334575
A26: 过去12个月归属净利润 | B26: =SUM(工业富联利润表!B60:E60) -> 22096707000 | D26: =SUM(工业富联利润表!F60:I60) -> 19945655000 | E26: =B26/D26-1 -> 0.10784564
A27: 过去12个月经营净现金流 | B27: =工业富联现金流量表!B13+工业富联现金流量表!C13-工业富联现金流量表!F13 -> 27444725000 | D27: =工业富联现金流量表!F13+工业富联现金流量表!G13-工业富联现金流量表!J13 -> 34453003000 | E27: =B27/D27-1 -> -0.20341559
A28: 过去12个月财务费用 | B28: =SUM(工业富联利润表!B46:E46) -> -1128911000 | D28: =SUM(工业富联利润表!F46:I46) -> -201970000 | E28: =B28/D28-1 -> 4.5894984
A29: 过去12个月投资收益 | B29: =SUM(工业富联利润表!B50:E50) -> 17242000 | D29: =SUM(工业富联利润表!F50:I50) -> -508405000 | E29: =B29/D29-1 -> -1.0339139
A30: ROE=归属净利/归属股东权益 | B30: =B26/工业富联资产负债表!B92 -> 0.15192963 | D30: =D26/工业富联资产负债表!F92 -> 0.15090966
A31: 过去12个月毛利 | B31: =B24-B25 -> 39646512000 | D31: =D24-D25 -> 37852861000
A32: 过去12个月毛利率 | B32: =B31/B24 -> 0.081053585 | D32: =D31/D24 -> 0.073833935
A33: 过去12个月净利率 | B33: =B26/B24 -> 0.04517465 | D33: =D26/D24 -> 0.038905017
A34: 总资产周转率 | B34: =B24/工业富联资产负债表!B95 -> 1.767676 | D34: =D24/工业富联资产负债表!F95 -> 1.9901078
A35: 权益乘数=资产总额/归属股东权益 | B35: =工业富联资产负债表!B95/工业富联资产负债表!B92 -> 1.9025892 | D35: =工业富联资产负债表!F95/工业富联资产负债表!F92 -> 1.9491032
A36: ROE-摊薄 | B36: =B33*B34*B35 -> 0.15192963 | D36: =D33*D34*D35 -> 0.15090966
A37: 实际资产负债率 | B37: =工业富联资产负债表!B97 -> 0.47167253 | D37: =工业富联资产负债表!F97 -> 0.48428203
A38: 投入资本回报率 | B38: =(B26+B28)/(工业富联资产负债表!B48-工业富联资产负债表!B43-工业富联资产负债表!B68) -> 0.13835264 | D38: =(D26+D28)/(工业富联资产负债表!F48-工业富联资产负债表!F43-工业富联资产负债表!F68) -> 0.14281404
A39: 近7年经营现金流/归属净利 | B39: =工业富联资产负债变动表!I111/工业富联资产负债变动表!I105 -> 0.61518046
A40: ROA=ROE/权益乘数 | B40: =B36/B35 -> 0.079854144
A41: 投入资本回报率=息前利润/（资产总额-流动负债-商誉）
A42: 投资收益占比净利润 | B42: =B29/B26 -> 0.00078029726
A43: （投资收益+利息收入）/净利润 | B43: =(B29-B28)/B26 -> 0.051869856
A44: 年平均自由现金流ROE=(∑归属净利润-∆FA&CIP)/7/当前期末归属股东权益*100%

Sheet 资产变化路径表5年
A1: 2019/1/1-2023/12/31（5年） | B1: 变动额 | E1: 变动额
A2: Δ货币资金及等价物 | B2: =工业富联资产负债变动表!J97 -> 21434308000 | D2: Δ短期借款 | E2: =工业富联资产负债变动表!J102 -> 18600683000
A3: Δ应收账款-Δ应付账款 | B3: =工业富联资产负债变动表!J98 -> -2947655000 | D3: Δ(预收-预付)账款 | E3: =工业富联资产负债变动表!J103 -> -97464000
A4: Δ存货 | B4: =工业富联资产负债变动表!J100 -> 39215714000
A5: Δ其他应收款-Δ其他应付款 | B5: =工业富联资产负债变动表!J99 -> 13296393000 | G5: 现金流量表 | H5: 差异
A6: Δ其他营运资本（不含预收账款） | B6: =工业富联资产负债变动表!J101 -> -3076000 | F6: 现金分红 | G6: =工业富联现金流量表!R35 -> 37684142000 | H6: =G6-G10 -> 70001436600
A7: Δ金融资产 | B7: =工业富联资产负债变动表!J25+工业富联资产负债变动表!J26+工业富联资产负债变动表!J27 -> 702103000 | D7: Δ长期借款 | E7: =工业富联资产负债变动表!J70 -> 7096943000
A8: Δ长期应收款 | B8: =工业富联资产负债变动表!J28 -> 62982000 | D8: Δ长期债券 | E8: =工业富联资产负债变动表!J71 -> 0
A9: Δ长期股权投资 | B9: =工业富联资产负债变动表!J29 -> 6786083000 | D9: Δ其他长期负债 | E9: =工业富联资产负债变动表!J81-工业富联资产负债变动表!J70-工业富联资产负债变动表!J71 -> 1695662000 | F9: 归属净利润 | G9: =工业富联资产负债变动表!J105 -> 97159983000 | I9: 现金分红比例
A10: Δ投资性房地产 | B10: =工业富联资产负债变动表!J30 -> 0 | F10: 现金分红 | G10: =工业富联资产负债变动表!J106 -> -32317294600 | H10: =SUM(G9:G10) -> 64842688400 | I10: =-G10/G9 -> 0.33261939
A11: ΔFA&CIP | B11: =工业富联资产负债变动表!J32+工业富联资产负债变动表!J33+工业富联资产负债变动表!J35+工业富联资产负债变动表!J36 -> 12122477000 | F11: IPO&增发 | G11: =工业富联资产负债变动表!J107 -> 0
A12: Δ生产性生物性/公益性生物性/油气/使用权资产 | B12: =工业富联资产负债变动表!J37+工业富联资产负债变动表!J38+工业富联资产负债变动表!J39+工业富联资产负债变动表!J40 -> 1571141000 | F12: CF净吸收投资 | G12: =工业富联现金流量表!R28-G11 -> 1517216000
A13: Δ无形资产 | B13: =工业富联资产负债变动表!J41 -> 807430000 | F13: 其他 | G13: =G14-G10-G11-G9-G12 -> 1532914600
A14: Δ开发支出 | B14: =工业富联资产负债变动表!J42 -> 0 | D14: Δ归属权益 | E14: =工业富联资产负债变动表!J92 -> 67892819000 | G14: =E14 -> 67892819000
A15: Δ商誉 | B15: =工业富联资产负债变动表!J43 -> 310153000
A16: Δ其他资产 | B16: =工业富联资产负债变动表!J44+工业富联资产负债变动表!J45+工业富联资产负债变动表!J46 -> 2188466000 | D16: Δ少数权益 | E16: =工业富联资产负债变动表!J93 -> 357876000
A17: 合计 | B17: =SUM(B2:B16) -> 95546519000 | D17: 合计 | E17: =SUM(E2:E16) -> 95546519000
E18: =B17-E17 -> 0
A19: ΔAR+Δ存货 | B19: =B3+B4 -> 36268059000 | D19: ∑归属净利润 | E19: =G9 -> 97159983000 | F19: =B19/E19 -> 0.37328186
A20: ΔFA&CIP | B20: =B11 -> 12122477000 | D20: ∑归属净利润 | E20: =E19 -> 97159983000 | F20: =B20/E20 -> 0.12476821
A21: 年平均自由现金流（5年） | B21: =(E20-B20)/5 -> 17007501200 | D21: 年平均自由现金流ROE | F21: =B21/(B26/B30) -> 0.11693794
B23: TTM（至2024Q1) | D23: TTM（至2023Q1) | E23: 同比增长率
A24: 过去12个月营业收入（非营业总收入） | B24: =SUM(工业富联利润表!B40:E40) -> 489139526000 | D24: =SUM(工业富联利润表!F40:I40) -> 512675653000 | E24: =B24/D24-1 -> -0.045908416
A25: 过去12个月营业成本 | B25: =SUM(工业富联利润表!B42:E42) -> 449493014000 | D25: =SUM(工业富联利润表!F42:I42) -> 474822792000 | E25: =B25/D25-1 -> -0.05334575
A26: 过去12个月归属净利润 | B26: =SUM(工业富联利润表!B60:E60) -> 22096707000 | D26: =SUM(工业富联利润表!F60:I60) -> 19945655000 | E26: =B26/D26-1 -> 0.10784564
A27: 过去12个月经营净现金流 | B27: =工业富联现金流量表!B13+工业富联现金流量表!C13-工业富联现金流量表!F13 -> 27444725000 | D27: =工业富联现金流量表!F13+工业富联现金流量表!G13-工业富联现金流量表!J13 -> 34453003000 | E27: =B27/D27-1 -> -0.20341559
A28: 过去12个月财务费用 | B28: =SUM(工业富联利润表!B46:E46) -> -1128911000 | D28: =SUM(工业富联利润表!F46:I46) -> -201970000 | E28: =B28/D28-1 -> 4.5894984
A29: 过去12个月投资收益 | B29: =SUM(工业富联利润表!B50:E50) -> 17242000 | D29: =SUM(工业富联利润表!F50:I50) -> -508405000 | E29: =B29/D29-1 -> -1.0339139
A30: ROE=归属净利/归属股东权益 | B30: =B26/工业富联资产负债表!B92 -> 0.15192963 | D30: =D26/工业富联资产负债表!F92 -> 0.15090966
A31: 过去12个月毛利 | B31: =B24-B25 -> 39646512000 | D31: =D24-D25 -> 37852861000
A32: 过去12个月毛利率 | B32: =B31/B24 -> 0.081053585 | D32: =D31/D24 -> 0.073833935
A33: 过去12个月净利率 | B33: =B26/B24 -> 0.04517465 | D33: =D26/D24 -> 0.038905017
A34: 总资产周转率 | B34: =B24/工业富联资产负债表!B95 -> 1.767676 | D34: =D24/工业富联资产负债表!F95 -> 1.9901078
A35: 权益乘数=资产总额/归属股东权益 | B35: =工业富联资产负债表!B95/工业富联资产负债表!B92 -> 1.9025892 | D35: =工业富联资产负债表!F95/工业富联资产负债表!F92 -> 1.9491032
A36: ROE-摊薄 | B36: =B33*B34*B35 -> 0.15192963 | D36: =D33*D34*D35 -> 0.15090966
A37: 实际资产负债率 | B37: =工业富联资产负债表!B97 -> 0.47167253 | D37: =工业富联资产负债表!F97 -> 0.48428203
A38: 投入资本回报率 | B38: =(B26+B28)/(工业富联资产负债表!B48-工业富联资产负债表!B43-工业富联资产负债表!B68) -> 0.13835264 | D38: =(D26+D28)/(工业富联资产负债表!F48-工业富联资产负债表!F43-工业富联资产负债表!F68) -> 0.14281404
A39: 近5年经营现金流/归属净利 | B39: =工业富联资产负债变动表!J111/工业富联资产负债变动表!J105 -> 0.62671814
A40: ROA=ROE/权益乘数 | B40: =B36/B35 -> 0.079854144
A41: 投入资本回报率=息前利润/（资产总额-流动负债-商誉）
A42: 投资收益占比净利润 | B42: =B29/B26 -> 0.00078029726
A43: （投资收益+利息收入）/净利润 | B43: =(B29-B28)/B26 -> 0.051869856
A44: 年平均自由现金流ROE=(∑归属净利润-∆FA&CIP)/6/当前期末归属股东权益*100%

Sheet 资产变化路径表-亿元7年
A1: =资产变化路径表7年!A1 -> 2017/1/1-2023/12/31（7年） | B1: 变动额 | E1: 变动额
A2: Δ货币资金及等价物 | B2: =资产变化路径表7年!B2/100000000 -> 801.39832 | D2: Δ短期借款 | E2: =资产变化路径表7年!E2/100000000 -> 394.47981
A3: Δ应收账款-Δ应付账款 | B3: =资产变化路径表7年!B3/100000000 -> 18.77654 | D3: Δ(预收-预付)账款 | E3: =资产变化路径表7年!E3/100000000 -> -3.2493
A4: Δ存货 | B4: =资产变化路径表7年!B4/100000000 -> 481.21909
A5: Δ其他应收款-Δ其他应付款 | B5: =资产变化路径表7年!B5/100000000 -> -371.36809
A6: Δ其他营运资本（不含预收账款） | B6: =资产变化路径表7年!B6/100000000 -> -33.66493
A7: Δ金融资产 | B7: =资产变化路径表7年!B7/100000000 -> 6.96471 | D7: Δ长期借款 | E7: =资产变化路径表7年!E7/100000000 -> 70.96943
A8: Δ长期应收款 | B8: =资产变化路径表7年!B8/100000000 -> 0.62982 | D8: Δ长期债券 | E8: =资产变化路径表7年!E8/100000000 -> 0
A9: Δ长期股权投资 | B9: =资产变化路径表7年!B9/100000000 -> 71.42247 | D9: Δ其他长期负债 | E9: =资产变化路径表7年!E9/100000000 -> 17.43654 | F9: 归属净利润 | G9: =资产变化路径表7年!G9/100000000 -> 1299.299 | I9: 现金分红比例
A10: Δ投资性房地产 | B10: =资产变化路径表7年!B10/100000000 -> -0.1982 | F10: 现金分红 | G10: =资产变化路径表7年!G10/100000000 -> -323.17295 | H10: =SUM(G9:G10) -> 976.12602 | I10: =-G10/G9 -> 0.2487287
A11: ΔFA&CIP | B11: =资产变化路径表7年!B11/100000000 -> 83.14726 | F11: IPO&增发 | G11: =资产变化路径表7年!G11/100000000 -> 267.229
A12: Δ生产性生物性/公益性生物性/油气/使用权资产 | B12: =资产变化路径表7年!B12/100000000 -> 15.71141 | F12: CF净吸收投资 | G12: =资产变化路径表7年!G12/100000000 -> 38.08889
A13: Δ无形资产 | B13: =资产变化路径表7年!B13/100000000 -> 7.60063 | F13: 其他 | G13: =资产变化路径表7年!G13/100000000 -> -652.60022 | H13: DIFF
A14: Δ开发支出 | B14: =资产变化路径表7年!B14/100000000 -> 0 | D14: Δ归属权益 | E14: =资产变化路径表7年!E14/100000000 -> 628.84369 | G14: =E14 -> 628.84369 | H14: =E14-G14 -> 0
A15: Δ商誉 | B15: =资产变化路径表7年!B15/100000000 -> 3.10153
A16: Δ其他资产 | B16: =资产变化路径表7年!B16/100000000 -> 25.62289 | D16: Δ少数权益 | E16: =资产变化路径表7年!E16/100000000 -> 1.88328
A17: 合计 | B17: =SUM(B2:B16) -> 1110.3634 | D17: 合计 | E17: =SUM(E2:E16) -> 1110.3635
E18: =B17-E17 -> 0
A19: ΔAR+Δ存货 | B19: =B3+B4 -> 499.99563 | D19: ∑归属净利润 | E19: =G9 -> 1299.299 | F19: =B19/E19 -> 0.38481954
A20: ΔFA&CIP | B20: =B11 -> 83.14726 | D20: ∑归属净利润 | E20: =E19 -> 1299.299 | F20: =B20/E20 -> 0.06399394
A23: 单位：人民币亿元 | B23: =资产变化路径表7年!B23 -> TTM（至2024Q1) | D23: =资产变化路径表7年!D23 -> TTM（至2023Q1) | E23: 同比增长率
A24: 过去12个月营业收入 | B24: =资产变化路径表7年!B24/100000000 -> 4891.3953 | D24: =资产变化路径表7年!D24/100000000 -> 5126.7565 | E24: =B24/D24-1 -> -0.045908416
A25: 过去12个月营业成本 | B25: =资产变化路径表7年!B25/100000000 -> 4494.9301 | D25: =资产变化路径表7年!D25/100000000 -> 4748.2279 | E25: =B25/D25-1 -> -0.05334575
A26: 过去12个月归属净利润 | B26: =资产变化路径表7年!B26/100000000 -> 220.96707 | D26: =资产变化路径表7年!D26/100000000 -> 199.45655 | E26: =B26/D26-1 -> 0.10784564
A27: 过去12个月经营净现金流 | B27: =资产变化路径表7年!B27/100000000 -> 274.44725 | D27: =资产变化路径表7年!D27/100000000 -> 344.53003 | E27: =B27/D27-1 -> -0.20341559
A28: 过去12个月财务费用 | B28: =资产变化路径表7年!B28/100000000 -> -11.28911 | D28: =资产变化路径表7年!D28/100000000 -> -2.0197 | E28: =B28/D28-1 -> 4.5894984
A29: 过去12个月投资收益 | B29: =资产变化路径表7年!B29/100000000 -> 0.17242 | D29: =资产变化路径表7年!D29/100000000 -> -5.08405 | E29: =B29/D29-1 -> -1.0339139
A30: ROE=归属净利/归属股东权益 | B30: =资产变化路径表7年!B30 -> 0.15192963 | D30: =资产变化路径表7年!D30 -> 0.15090966
A31: 过去12个月毛利 | B31: =B24-B25 -> 396.46512 | D31: =D24-D25 -> 378.52861
A32: 过去12个月毛利率 | B32: =资产变化路径表7年!B32 -> 0.081053585 | D32: =资产变化路径表7年!D32 -> 0.073833935
A33: 过去12个月净利率 | B33: =资产变化路径表7年!B33 -> 0.04517465 | D33: =资产变化路径表7年!D33 -> 0.038905017
A34: 总资产周转率 | B34: =资产变化路径表7年!B34 -> 1.767676 | D34: =资产变化路径表7年!D34 -> 1.9901078
A35: 权益乘数=资产总额/归属股东权益 | B35: =资产变化路径表7年!B35 -> 1.9025892 | D35: =资产变化路径表7年!D35 -> 1.9491032
A36: ROE-摊薄 | B36: =资产变化路径表7年!B36 -> 0.15192963 | D36: =资产变化路径表7年!D36 -> 0.15090966
A37: 实际资产负债率 | B37: =资产变化路径表7年!B37 -> 0.47167253 | D37: =资产变化路径表7年!D37 -> 0.48428203
A38: 投入资本回报率 | B38: =资产变化路径表7年!B38 -> 0.13835264 | D38: =资产变化路径表7年!D38 -> 0.14281404
A39: 近六年经营现金流/归属净利 | B39: =资产变化路径表7年!B39 -> 0.61518046
A40: ROA=ROE/权益乘数 | B40: =资产变化路径表7年!B40 -> 0.079854144
A41: 投入资本回报率=息前利润/（资产总额-流动负债-商誉）

Sheet 资产变化路径表-亿元5年
A1: =资产变化路径表5年!A1 -> 2019/1/1-2023/12/31（5年） | B1: 变动额 | E1: 变动额
A2: Δ货币资金及等价物 | B2: =资产变化路径表5年!B2/100000000 -> 214.34308 | D2: Δ短期借款 | E2: =资产变化路径表5年!E2/100000000 -> 186.00683
A3: Δ应收账款-Δ应付账款 | B3: =资产变化路径表5年!B3/100000000 -> -29.47655 | D3: Δ(预收-预付)账款 | E3: =资产变化路径表5年!E3/100000000 -> -0.97464
A4: Δ存货 | B4: =资产变化路径表5年!B4/100000000 -> 392.15714
A5: Δ其他应收款-Δ其他应付款 | B5: =资产变化路径表5年!B5/100000000 -> 132.96393
A6: Δ其他营运资本（不含预收账款） | B6: =资产变化路径表5年!B6/100000000 -> -0.03076
A7: Δ金融资产 | B7: =资产变化路径表5年!B7/100000000 -> 7.02103 | D7: Δ长期借款 | E7: =资产变化路径表5年!E7/100000000 -> 70.96943
A8: Δ长期应收款 | B8: =资产变化路径表5年!B8/100000000 -> 0.62982 | D8: Δ长期债券 | E8: =资产变化路径表5年!E8/100000000 -> 0
A9: Δ长期股权投资 | B9: =资产变化路径表5年!B9/100000000 -> 67.86083 | D9: Δ其他长期负债 | E9: =资产变化路径表5年!E9/100000000 -> 16.95662 | F9: 归属净利润 | G9: =资产变化路径表5年!G9/100000000 -> 971.59983 | I9: 现金分红比例
A10: Δ投资性房地产 | B10: =资产变化路径表5年!B10/100000000 -> 0 | F10: 现金分红 | G10: =资产变化路径表5年!G10/100000000 -> -323.17295 | H10: =SUM(G9:G10) -> 648.42688 | I10: =-G10/G9 -> 0.33261939
A11: ΔFA&CIP | B11: =资产变化路径表5年!B11/100000000 -> 121.22477 | F11: IPO&增发 | G11: =资产变化路径表5年!G11/100000000 -> 0
A12: Δ生产性生物性/公益性生物性/油气/使用权资产 | B12: =资产变化路径表5年!B12/100000000 -> 15.71141 | F12: CF净吸收投资 | G12: =资产变化路径表5年!G12/100000000 -> 15.17216
A13: Δ无形资产 | B13: =资产变化路径表5年!B13/100000000 -> 8.0743 | F13: 其他 | G13: =资产变化路径表5年!G13/100000000 -> 15.329146 | H13: DIFF
A14: Δ开发支出 | B14: =资产变化路径表5年!B14/100000000 -> 0 | D14: Δ归属权益 | E14: =资产变化路径表5年!E14/100000000 -> 678.92819 | G14: =E14 -> 678.92819 | H14: =E14-G14 -> 0
A15: Δ商誉 | B15: =资产变化路径表5年!B15/100000000 -> 3.10153
A16: Δ其他资产 | B16: =资产变化路径表5年!B16/100000000 -> 21.88466 | D16: Δ少数权益 | E16: =资产变化路径表5年!E16/100000000 -> 3.57876
A17: 合计 | B17: =SUM(B2:B16) -> 955.46519 | D17: 合计 | E17: =SUM(E2:E16) -> 955.46519
E18: =B17-E17 -> 0
A19: ΔAR+Δ存货 | B19: =B3+B4 -> 362.68059 | D19: ∑归属净利润 | E19: =G9 -> 971.59983 | F19: =B19/E19 -> 0.37328186
A20: ΔFA&CIP | B20: =B11 -> 121.22477 | D20: ∑归属净利润 | E20: =E19 -> 971.59983 | F20: =B20/E20 -> 0.12476821
A23: 单位：人民币亿元 | B23: =资产变化路径表5年!B23 -> TTM（至2024Q1) | D23: =资产变化路径表5年!D23 -> TTM（至2023Q1) | E23: 同比增长率
A24: 过去12个月营业收入 | B24: =资产变化路径表5年!B24/100000000 -> 4891.3953 | D24: =资产变化路径表5年!D24/100000000 -> 5126.7565 | E24: =B24/D24-1 -> -0.045908416
A25: 过去12个月营业成本 | B25: =资产变化路径表5年!B25/100000000 -> 4494.9301 | D25: =资产变化路径表5年!D25/100000000 -> 4748.2279 | E25: =B25/D25-1 -> -0.05334575
A26: 过去12个月归属净利润 | B26: =资产变化路径表5年!B26/100000000 -> 220.96707 | D26: =资产变化路径表5年!D26/100000000 -> 199.45655 | E26: =B26/D26-1 -> 0.10784564
A27: 过去12个月经营净现金流 | B27: =资产变化路径表5年!B27/100000000 -> 274.44725 | D27: =资产变化路径表5年!D27/100000000 -> 344.53003 | E27: =B27/D27-1 -> -0.20341559
A28: 过去12个月财务费用 | B28: =资产变化路径表5年!B28/100000000 -> -11.28911 | D28: =资产变化路径表5年!D28/100000000 -> -2.0197 | E28: =B28/D28-1 -> 4.5894984
A29: 过去12个月投资收益 | B29: =资产变化路径表5年!B29/100000000 -> 0.17242 | D29: =资产变化路径表5年!D29/100000000 -> -5.08405 | E29: =B29/D29-1 -> -1.0339139
A30: ROE=归属净利/归属股东权益 | B30: =资产变化路径表5年!B30 -> 0.15192963 | D30: =资产变化路径表5年!D30 -> 0.15090966
A31: 过去12个月毛利 | B31: =B24-B25 -> 396.46512 | D31: =D24-D25 -> 378.52861
A32: 过去12个月毛利率 | B32: =资产变化路径表5年!B32 -> 0.081053585 | D32: =资产变化路径表5年!D32 -> 0.073833935
A33: 过去12个月净利率 | B33: =资产变化路径表5年!B33 -> 0.04517465 | D33: =资产变化路径表5年!D33 -> 0.038905017
A34: 总资产周转率 | B34: =资产变化路径表5年!B34 -> 1.767676 | D34: =资产变化路径表5年!D34 -> 1.9901078
A35: 权益乘数=资产总额/归属股东权益 | B35: =资产变化路径表5年!B35 -> 1.9025892 | D35: =资产变化路径表5年!D35 -> 1.9491032
A36: ROE-摊薄 | B36: =资产变化路径表5年!B36 -> 0.15192963 | D36: =资产变化路径表5年!D36 -> 0.15090966
A37: 实际资产负债率 | B37: =资产变化路径表5年!B37 -> 0.47167253 | D37: =资产变化路径表5年!D37 -> 0.48428203
A38: 投入资本回报率 | B38: =资产变化路径表5年!B38 -> 0.13835264 | D38: =资产变化路径表5年!D38 -> 0.14281404
A39: 近5年经营现金流/归属净利 | B39: =资产变化路径表5年!B39 -> 0.62671814
A40: ROA=ROE/权益乘数 | B40: =资产变化路径表5年!B40 -> 0.079854144
A41: 投入资本回报率=息前利润/（资产总额-流动负债-商誉）

Sheet 资产变化路径表 (2023)-亿元
A1: 2023/1/1-2023/12/31 | B1: 变动额 | E1: 变动额
A2: Δ货币资金及等价物 | B2: =工业富联资产负债变动表!B97/100000000 -> 146.05075 | D2: Δ短期借款 | E2: =工业富联资产负债变动表!B102/100000000 -> -94.06793
A3: Δ应收账款-Δ应付账款 | B3: =工业富联资产负债变动表!B98/100000000 -> -149.5545 | D3: Δ(预收-预付)账款 | E3: =工业富联资产负债变动表!B103/100000000 -> 0.97654
A4: Δ存货 | B4: =工业富联资产负债变动表!B100/100000000 -> -6.38405
A5: Δ其他应收款-Δ其他应付款 | B5: =工业富联资产负债变动表!B99/100000000 -> 18.21667
A6: Δ其他营运资本（不含预收账款） | B6: =工业富联资产负债变动表!B101/100000000 -> 45.2763
A7: Δ金融资产 | B7: =(工业富联资产负债变动表!B25+工业富联资产负债变动表!B26+工业富联资产负债变动表!B27)/100000000 -> 3.54606 | D7: Δ长期借款 | E7: =工业富联资产负债变动表!B70/100000000 -> 36.12436
A8: Δ长期应收款 | B8: =工业富联资产负债变动表!B28/100000000 -> 0.62982 | D8: Δ长期债券 | E8: =工业富联资产负债变动表!B71/100000000 -> 0
A9: Δ长期股权投资 | B9: =工业富联资产负债变动表!B29/100000000 -> -50.35949 | D9: Δ其他长期负债 | E9: =(工业富联资产负债变动表!B81-工业富联资产负债变动表!B70-工业富联资产负债变动表!B71)/100000000 -> -2.25569
A10: Δ投资性房地产 | B10: =工业富联资产负债变动表!B30/100000000 -> 0 | F10: 归属净利润 | G10: =工业富联资产负债变动表!B105/100000000 -> 210.40193 | I10: 现金分红比例
A11: ΔFA&CIP | B11: =(工业富联资产负债变动表!B32+工业富联资产负债变动表!B33+工业富联资产负债变动表!B35)/100000000 -> 35.81211 | F11: 现金分红 | G11: =工业富联资产负债变动表!B106/100000000 -> -109.25201 | H11: =SUM(G10:G11) -> 101.14992 | I11: =-G11/G10 -> 0.51925382
A12: Δ生产性生物性/公益性生物性/油气/使用权资产 | B12: =(工业富联资产负债变动表!B37+工业富联资产负债变动表!B38+工业富联资产负债变动表!B39+工业富联资产负债变动表!B40)/100000000 -> -5.06714 | F12: IPO&增发 | G12: =工业富联资产负债变动表!B107/100000000 -> 0
A13: Δ无形资产 | B13: =工业富联资产负债变动表!B41/100000000 -> 5.64107 | F13: 其他 | G13: =G14-G11-G12-G10 -> 10.972686 | H13: DIFF
A14: Δ开发支出 | B14: =工业富联资产负债变动表!B42/100000000 -> 0 | D14: Δ归属权益 | E14: =工业富联资产负债变动表!B92/100000000 -> 112.12261 | G14: =E14 -> 112.12261 | H14: =E14-G14 -> 0
A15: Δ商誉 | B15: =工业富联资产负债变动表!B43/100000000 -> 0
A16: Δ其他资产 | B16: =(工业富联资产负债变动表!B44+工业富联资产负债变动表!B45+工业富联资产负债变动表!B46)/100000000 -> 9.58797 | D16: Δ少数权益 | E16: =工业富联资产负债变动表!B93/100000000 -> 0.49568
A17: 合计 | B17: =SUM(B2:B16) -> 53.39557 | D17: 合计 | E17: =SUM(E2:E16) -> 53.39557
E18: =B17-E17 -> 0
A19: ΔAR+Δ存货 | B19: =B3+B4 -> -155.93855 | D19: ∑归属净利润 | E19: =G10 -> 210.40193 | F19: =B19/E19 -> -0.74114601
A20: ΔFA&CIP | B20: =B11 -> 35.81211 | D20: ∑归属净利润 | E20: =E19 -> 210.40193 | F20: =B20/E20 -> 0.17020809

Sheet 资产变化路径表 (2022)-亿元
A1: 2022/1/1-2022/12/31 | B1: 变动额 | E1: 变动额
A2: Δ货币资金及等价物 | B2: =工业富联资产负债变动表!C97/100000000 -> -135.45201 | D2: Δ短期借款 | E2: =工业富联资产负债变动表!C102/100000000 -> -16.38962
A3: Δ应收账款-Δ应付账款 | B3: =工业富联资产负债变动表!C98/100000000 -> 131.01014 | D3: Δ(预收-预付)账款 | E3: =工业富联资产负债变动表!C103/100000000 -> -1.1075
A4: Δ存货 | B4: =工业富联资产负债变动表!C100/100000000 -> 53.93917
A5: Δ其他应收款-Δ其他应付款 | B5: =工业富联资产负债变动表!C99/100000000 -> -87.30358
A6: Δ其他营运资本（不含预收账款） | B6: =工业富联资产负债变动表!C101/100000000 -> -40.34651
A7: Δ金融资产 | B7: =(工业富联资产负债变动表!C25+工业富联资产负债变动表!C26+工业富联资产负债变动表!C27)/100000000 -> 2.5951 | D7: Δ长期借款 | E7: =工业富联资产负债变动表!C70/100000000 -> -3.2984
A8: Δ长期应收款 | B8: =工业富联资产负债变动表!C28/100000000 -> 0 | D8: Δ长期债券 | E8: =工业富联资产负债变动表!C71/100000000 -> 0
A9: Δ长期股权投资 | B9: =工业富联资产负债变动表!C29/100000000 -> 90.47774 | D9: Δ其他长期负债 | E9: =(工业富联资产负债变动表!C81-工业富联资产负债变动表!C70-工业富联资产负债变动表!C71)/100000000 -> 2.15861
A10: Δ投资性房地产 | B10: =工业富联资产负债变动表!C30/100000000 -> 0 | F10: 归属净利润 | G10: =工业富联资产负债变动表!C105/100000000 -> 200.73072 | I10: 现金分红比例
A11: ΔFA&CIP | B11: =(工业富联资产负债变动表!C32+工业富联资产负债变动表!C33+工业富联资产负债变动表!C35)/100000000 -> 57.30182 | F11: 现金分红 | G11: =工业富联资产负债变动表!C106/100000000 -> -98.909452 | H11: =SUM(G10:G11) -> 101.82127 | I11: =-G11/G10 -> 0.49274696
A12: Δ生产性生物性/公益性生物性/油气/使用权资产 | B12: =(工业富联资产负债变动表!C37+工业富联资产负债变动表!C38+工业富联资产负债变动表!C39+工业富联资产负债变动表!C40)/100000000 -> -0.41766 | F12: IPO&增发 | G12: =工业富联资产负债变动表!C107/100000000 -> 0
A13: Δ无形资产 | B13: =工业富联资产负债变动表!C41/100000000 -> 0.33292 | F13: 其他 | G13: =G14-G11-G12-G10 -> -3.875368 | H13: DIFF
A14: Δ开发支出 | B14: =工业富联资产负债变动表!C42/100000000 -> 0 | D14: Δ归属权益 | E14: =工业富联资产负债变动表!C92/100000000 -> 97.9459 | G14: =E14 -> 97.9459 | H14: =E14-G14 -> 0
A15: Δ商誉 | B15: =工业富联资产负债变动表!C43/100000000 -> 3.10153
A16: Δ其他资产 | B16: =(工业富联资产负债变动表!C44+工业富联资产负债变动表!C45+工业富联资产负债变动表!C46)/100000000 -> 4.68259 | D16: Δ少数权益 | E16: =工业富联资产负债变动表!C93/100000000 -> 0.51226
A17: 合计 | B17: =SUM(B2:B16) -> 79.92125 | D17: 合计 | E17: =SUM(E2:E16) -> 79.82125
E18: =B17-E17 -> 0.1
A19: ΔAR+Δ存货 | B19: =B3+B4 -> 184.94931 | D19: ∑归属净利润 | E19: =G10 -> 200.73072 | F19: =B19/E19 -> 0.9213802
A20: ΔFA&CIP | B20: =B11 -> 57.30182 | D20: ∑归属净利润 | E20: =E19 -> 200.73072 | F20: =B20/E20 -> 0.28546612

Sheet 资产变化路径表 (2021)-亿元
A1: 2021/1/1-2021/12/31 | B1: 变动额 | E1: 变动额
A2: Δ货币资金及等价物 | B2: =工业富联资产负债变动表!D97/100000000 -> 47.41719 | D2: Δ短期借款 | E2: =工业富联资产负债变动表!D102/100000000 -> 79.1372
A3: Δ应收账款-Δ应付账款 | B3: =工业富联资产负债变动表!D98/100000000 -> -93.89735 | D3: Δ(预收-预付)账款 | E3: =工业富联资产负债变动表!D103/100000000 -> -0.70145
A4: Δ存货 | B4: =工业富联资产负债变动表!D100/100000000 -> 265.73937
A5: Δ其他应收款-Δ其他应付款 | B5: =工业富联资产负债变动表!D99/100000000 -> -3.14603
A6: Δ其他营运资本（不含预收账款） | B6: =工业富联资产负债变动表!D101/100000000 -> -6.66627
A7: Δ金融资产 | B7: =(工业富联资产负债变动表!D25+工业富联资产负债变动表!D26+工业富联资产负债变动表!D27)/100000000 -> 1.28747 | D7: Δ长期借款 | E7: =工业富联资产负债变动表!D70/100000000 -> 38.14122
A8: Δ长期应收款 | B8: =工业富联资产负债变动表!D28/100000000 -> 0 | D8: Δ长期债券 | E8: =工业富联资产负债变动表!D71/100000000 -> 0
A9: Δ长期股权投资 | B9: =工业富联资产负债变动表!D29/100000000 -> 20.00232 | D9: Δ其他长期负债 | E9: =(工业富联资产负债变动表!D81-工业富联资产负债变动表!D70-工业富联资产负债变动表!D71)/100000000 -> 10.30398
A10: Δ投资性房地产 | B10: =工业富联资产负债变动表!D30/100000000 -> 0 | F10: 归属净利润 | G10: =工业富联资产负债变动表!D105/100000000 -> 200.09751 | I10: 现金分红比例
A11: ΔFA&CIP | B11: =(工业富联资产负债变动表!D32+工业富联资产负债变动表!D33+工业富联资产负债变动表!D35)/100000000 -> 31.41374 | F11: 现金分红 | G11: =工业富联资产负债变动表!D106/100000000 -> -49.667899 | H11: =SUM(G10:G11) -> 150.42961 | I11: =-G11/G10 -> 0.24821848
A12: Δ生产性生物性/公益性生物性/油气/使用权资产 | B12: =(工业富联资产负债变动表!D37+工业富联资产负债变动表!D38+工业富联资产负债变动表!D39+工业富联资产负债变动表!D40)/100000000 -> 21.19621 | F12: IPO&增发 | G12: =工业富联资产负债变动表!D107/100000000 -> 0
A13: Δ无形资产 | B13: =工业富联资产负债变动表!D41/100000000 -> 0.01696 | F13: 其他 | G13: =G14-G11-G12-G10 -> 3.850919 | H13: DIFF
A14: Δ开发支出 | B14: =工业富联资产负债变动表!D42/100000000 -> 0 | D14: Δ归属权益 | E14: =工业富联资产负债变动表!D92/100000000 -> 154.28053 | G14: =E14 -> 154.28053 | H14: =E14-G14 -> 0
A15: Δ商誉 | B15: =工业富联资产负债变动表!D43/100000000 -> 0
A16: Δ其他资产 | B16: =(工业富联资产负债变动表!D44+工业富联资产负债变动表!D45+工业富联资产负债变动表!D46)/100000000 -> 1.83865 | D16: Δ少数权益 | E16: =工业富联资产负债变动表!D93/100000000 -> 0.18939
A17: 合计 | B17: =SUM(B2:B16) -> 285.20226 | D17: 合计 | E17: =SUM(E2:E16) -> 281.35087
E18: =B17-E17 -> 3.85139
A19: ΔAR+Δ存货 | B19: =B3+B4 -> 171.84202 | D19: ∑归属净利润 | E19: =G10 -> 200.09751 | F19: =B19/E19 -> 0.8587914
A20: ΔFA&CIP | B20: =B11 -> 31.41374 | D20: ∑归属净利润 | E20: =E19 -> 200.09751 | F20: =B20/E20 -> 0.15699216

Sheet 总结 
D1: 工业富联 | G1: 工业富联
D2: 45544 | F2: 验证 | G2: 45422 | H2: 增减变动%
C3: 股价 | D3: 18.6 | E3: 元 | G3: 23.84 | H3: =D3/G3-1 -> -0.21979866
C4: 总股本 | D4: =1986402.73/10000 -> 198.64027 | E4: 亿 | G4: 198.64027
C5: 总市值 | D5: =D3*D4 -> 3694.7091 | E5: 亿 | G5: 4735.5841 | H5: =D5/G5-1 -> -0.21979866
C6: TTM营业收入 | D6: =SUM(东财季度指标!B2:E2) -> 4891 | E6: 亿 | F6: =资产变化路径表7年!B24/100000000 -> 4891.3953 | G6: 4891 | H6: =D6/G6-1 -> 0
C7: TTM归属净利 | D7: =SUM(东财季度指标!B4:E4) -> 220.97 | E7: 亿 | F7: =资产变化路径表7年!B26/100000000 -> 220.96707 | G7: 220.97 | H7: =D7/G7-1 -> 0
C8: TTM扣非净利 | D8: =SUM(东财季度指标!B5:E5) -> 212.74 | E8: 亿 | G8: 212.74 | H8: =D8/G8-1 -> 0
C9: TTM自由现金流2 | D9: =工业富联现金流量表!C80/100000000 -> 168.21264 | E9: 亿 | G9: 168.21264 | H9: =D9/G9-1 -> 0
C10: 最新期末资产总额 | D10: =工业富联资产负债表!B95/100000000 -> 2767.1334 | E10: 亿 | G10: 2767.1334 | H10: =D10/G10-1 -> 0
C11: 最新期末FA&CIP | D11: =工业富联资产负债表!B100/100000000 -> 206.77791 | E11: 亿 | G11: 206.77791 | H11: =D11/G11-1 -> 0
C12: 最新期末股东权益 | D12: =工业富联资产负债表!B92/100000000 -> 1454.404 | E12: 亿 | G12: 1454.404 | H12: =D12/G12-1 -> 0
C13: PE-7年 | D13: =D5/工业富联利润表!P24*7*100000000 -> 27.488207 | G13: 35.232196
C14: PE-3年 | D14: =D5/工业富联利润表!R24*3*100000000 -> 25.95122 | G14: 33.262209
C15: PE-ttm | D15: =D5/D7 -> 16.72041 | G15: 21.430892
C16: PE-自由现金流 | D16: =D5/D9 -> 21.964515 | G16: 28.152368
C17: PB | D17: =D5/D12 -> 2.5403595 | G17: 3.2560306
C18: ROE | D18: =D17/D15 -> 0.15193165 | G18: 0.15193165
C19: ROA | D19: =资产变化路径表7年!B40 -> 0.079854144 | G19: 0.079854144
C20: =资产变化路径表7年!A38 -> 投入资本回报率 | D20: =资产变化路径表7年!B38 -> 0.13835264 | G20: 0.13835264
C21: 毛利率 | D21: =资产变化路径表7年!B32 -> 0.081053585 | G21: 0.081053585
C22: 净利率 | D22: =资产变化路径表7年!B33 -> 0.04517465 | G22: 0.04517465
C23: 所得税率 | D23: =工业富联资产负债变动表!B132 -> 0.091063739 | G23: 0.091063739
C24: 实际资产负债率 | D24: =工业富联资产负债表!B97 -> 0.47167253 | G24: 0.47167253
C25: 自由现金流占比营收%（2017-2023） | D25: =工业富联资产负债变动表!I115 -> 0.025419138 | G25: 0.025419138
C26: 现金分红占比净利润 | D26: =资产变化路径表7年!I10 -> 0.2487287 | G26: 0.2487287
C27: 股息收益率 | D27: =-工业富联资产负债变动表!B106/100000000/'总结 '!D5 -> 0.029569853 | G27: 0.023070439
C28: 投资收益占比净利润 | D28: =资产变化路径表7年!B42 -> 0.00078029726 | G28: 0.00078029726
C29: （投资收益+利息收入）/净利润 | D29: =资产变化路径表7年!B43 -> 0.051869856 | G29: 0.051869856
C30: 2017-2023企业经营现金流/归属净利 | D30: =资产变化路径表7年!B39 -> 0.61518046 | G30: 0.61518046
C31: 总资产周转率 | D31: =资产变化路径表7年!B34 -> 1.767676 | G31: 1.767676
C32: 营业收入/固定资产 | D32: =D6/D11 -> 23.653397 | G32: 23.653397
C33: ΔAR+Δ存货/∑归属净利润 | D33: =资产变化路径表7年!F19 -> 0.38481954 | G33: 0.38481954
C34: ΔFA&CIP/∑归属净利润 | D34: =资产变化路径表7年!F20 -> 0.06399394 | G34: 0.06399394
C35: 年平均自由现金流ROE | D35: =资产变化路径表7年!F21 -> 0.11945509 | G35: 0.11945509
C36: 地域： | D36: 深圳 | G36: 深圳
C37: 上市日期： | D37: 43259 | G37: 43259
C38: 增发情况： | D38: 无 | G38: 无
C39: 行业： | D39: 信息技术-通信设备-通信传输设备 | G39: 信息技术-通信设备-通信传输设备
C40: 发行股份数量：万股 | D40: 197000 | G40: 197000
C41: 发行价：元 | D41: 13.77 | G41: 13.77
C42: 募集费用：万元 | D42: 40400 | G42: 40400
C43: IPO净募集金额：万元 | D43: =D40*D41-D42 -> 2672290 | G43: 2672290
C44: 增发时间： | D44: 无 | G44: 无
C45: 增发数量：万股
C46: 增发价格：元
C47: 增发费用：
C48: 净募集：万元

Sheet 工业富联东财年度指标
A1: 成长能力指标 | B1: 45291 | C1: 44926 | D1: 44561 | E1: 44196 | F1: 43830 | G1: 43465 | H1: 43100 | I1: 42735 | J1: 42369
A2: 营业总收入(元) | B2: 4763 | C2: 5118 | D2: 4396 | E2: 4318 | F2: 4087 | G2: 4154 | H2: 3545 | I2: 2727 | J2: 2728
A3: 毛利润(元) | B3: 383.8 | C3: 371.7 | D3: 365.2 | E3: 348.4 | F3: 342.5 | G3: 358.9 | H3: 359.6 | I3: 290.4 | J3: 286.4
A4: 归属净利润(元) | B4: 210.4 | C4: 200.7 | D4: 200.1 | E4: 174.3 | F4: 186.1 | G4: 169 | H4: 158.7 | I4: 143.7 | J4: 143.5
A5: 扣非净利润(元) | B5: 202.1 | C5: 184.1 | D5: 185.8 | E5: 163.9 | F5: 169.8 | G5: 167.2 | H5: 159.5 | I5: 141.1 | J5: 139.6
A6: 营业总收入同比增长(%) | B6: -6.94 | C6: 16.45 | D6: 1.8 | E6: 5.65 | F6: -1.61 | G6: 17.16 | H6: 30.01 | I6: -0.03 | J6: --
A7: 归属净利润同比增长(%) | B7: 4.82 | C7: 0.32 | D7: 14.8 | E7: -6.32 | F7: 10.08 | G7: 6.52 | H7: 10.45 | I7: 0.11 | J7: --
A8: 扣非净利润同比增长(%) | B8: 9.77 | C8: -0.92 | D8: 13.39 | E8: -3.52 | F8: 1.56 | G8: 4.83 | H8: 13.04 | I8: 1.07 | J8: --
A10: 净资产收益率(加权)(%) | B10: 15.63 | C10: 16.17 | D10: 18.02 | E10: 18.13 | F10: 23.04 | G10: 33.66 | H10: 18.87 | I10: 20.93 | J10: 27.67
A11: 净资产收益率(扣非/加权)(%) | B11: 15.02 | C11: 14.83 | D11: 16.73 | E11: 17.04 | F11: 21.03 | G11: 33.31 | H11: 18.97 | I11: 20.56 | J11: 26.93
A12: 总资产收益率(加权)(%) | B12: 7.35 | C12: 7.29 | D12: 8.14 | E12: 8.08 | F12: 9.16 | G12: 9.68 | H12: 11.41 | I12: 11.73 | J12: 26.16
A13: 毛利率(%) | B13: 8.06 | C13: 7.26 | D13: 8.31 | E13: 8.07 | F13: 8.38 | G13: 8.64 | H13: 10.14 | I13: 10.65 | J13: 10.5
A14: 净利率(%) | B14: 4.41 | C14: 3.92 | D14: 4.56 | E14: 4.04 | F14: 4.55 | G14: 4.07 | H14: 4.57 | I14: 5.28 | J14: 5.26
A16: 预收账款/营业总收入 | B16: -- | C16: -- | D16: -- | E16: -- | F16: 0 | G16: 0 | H16: 0 | I16: 0.001 | J16: 0.001
A17: 销售净现金流/营业总收入 | B17: 0.153 | C17: 0.073 | D17: 0.071 | E17: 0.076 | F17: 0.075 | G17: 0.112 | H17: 0.11 | I17: 0.178 | J17: 0.135
A18: 经营净现金流/营业总收入 | B18: 0.09 | C18: 0.03 | D18: 0.02 | E18: 0.018 | F18: 0.016 | G18: 0.053 | H18: 0.024 | I18: 0.077 | J18: 0.031
A19: 实际税率(%) | B19: 9.11 | C19: 8.56 | D19: 10.27 | E19: 11.75 | F19: 11.96 | G19: 15.76 | H19: 19.07 | I19: 18.05 | J19: 18.08
A21: 流动比率 | B21: 1.829 | C21: 1.669 | D21: 1.749 | E21: 1.769 | F21: 1.687 | G21: 1.484 | H21: 1.135 | I21: 2.102 | J21: 1.915
A22: 速动比率 | B22: 1.273 | C22: 1.15 | D22: 1.24 | E22: 1.393 | F22: 1.328 | G22: 1.191 | H22: 0.84 | I22: 1.61 | J22: 1.374
A23: 现金流量比率 | B23: 0.312 | C23: 0.103 | D23: 0.062 | E23: 0.064 | F23: 0.056 | G23: 0.172 | H23: 0.071 | I23: 0.361 | J23: 0.172
A24: 资产负债率(%) | B24: 51.13 | C24: 54.49 | D24: 55.18 | E24: 53.87 | F24: 56.55 | G24: 63.94 | H24: 81.03 | I24: 42.89 | J24: 45.72
A25: 权益乘数 | B25: 2.046 | C25: 2.197 | D25: 2.231 | E25: 2.168 | F25: 2.301 | G25: 2.773 | H25: 5.273 | I25: 1.751 | J25: 1.842
A26: 产权比率 | B26: 1.046 | C26: 1.197 | D26: 1.231 | E26: 1.168 | F26: 1.301 | G26: 1.773 | H26: 4.273 | I26: 0.751 | J26: 0.842
A28: 总资产周转天数(天) | B28: 216.1 | C28: 193.7 | D28: 201.5 | E28: 179.7 | F28: 178.9 | G28: 151.3 | H28: 144.4 | I28: 162 | J28: --
A29: 存货周转天数(天) | B29: 63.29 | C29: 56.6 | D29: 52.38 | E29: 39.45 | F29: 38.03 | G29: 34.63 | H29: 36.22 | I29: 41.08 | J29: 39.89
A30: 应收账款周转天数(天) | B30: 70.35 | C30: 64.96 | D30: 71.2 | E30: 71.48 | F30: 75.21 | G30: 71.34 | H30: 67.57 | I30: 67.05 | J30: 62.04
A31: 总资产周转率(次) | B31: 1.666 | C31: 1.859 | D31: 1.786 | E31: 2.003 | F31: 2.012 | G31: 2.379 | H31: 2.494 | I31: 2.222 | J31: --
A32: 存货周转率(次) | B32: 5.688 | C32: 6.361 | D32: 6.873 | E32: 9.125 | F32: 9.466 | G32: 10.39 | H32: 9.938 | I32: 8.763 | J32: 9.025
A33: 应收账款周转率(次) | B33: 5.117 | C33: 5.542 | D33: 5.056 | E33: 5.036 | F33: 4.787 | G33: 5.046 | H33: 5.328 | I33: 5.369 | J33: 5.803
A35: 权益乘数又称股本乘数，是指资产总额相当于股东权益的倍数。
A36: 产权比率是在股份制企业中，负债总额与归属所有者权益总额的比率，是为评估资金结构合理性的一种指标。
A38: 权益乘数=资产总额/所有者权益
A39: 产权比率=负债总额/归属股东权益

Sheet 东财季度指标
A1: 成长能力指标 | B1: 45382 | C1: 45291 | D1: 45199 | E1: 45107 | F1: 45016 | G1: 44926 | H1: 44834 | I1: 44742 | J1: 44651
A2: 营业总收入(亿元) | B2: 1187 | C2: 1475 | D2: 1220 | E2: 1009 | F2: 1059 | G2: 1508 | H2: 1358 | I2: 1202 | J2: 1051
A3: 毛利润(亿元) | B3: 90.66 | C3: 122.1 | D3: 113.4 | E3: 70.36 | F3: 77.95 | G3: 121.8 | H3: 103.4 | I3: 75.37 | J3: 71.14
A4: 归属净利润(亿元) | B4: 41.85 | C4: 75.55 | D4: 63.24 | E4: 40.33 | F4: 31.28 | G4: 82.77 | H4: 49.24 | I4: 36.16 | J4: 32.56
A5: 扣非净利润(亿元) | B5: 42.72 | C5: 66.76 | D5: 59.96 | E5: 43.3 | F5: 32.07 | G5: 70.63 | H5: 49.75 | I5: 32.72 | J5: 31
A6: 营业总收入同比增长(%) | B6: 12.09 | C6: -2.15 | D6: -10.15 | E6: -16.07 | F6: 0.79 | G6: 12.34 | H6: 24.24 | I6: 23.09 | J6: 6.79
A7: 归属净利润同比增长(%) | B7: 33.77 | C7: -8.72 | D7: 28.42 | E7: 11.53 | F7: -3.91 | G7: -8.06 | H7: 15.05 | I7: 2.2 | J7: 2.11
A8: 扣非净利润同比增长(%) | B8: 33.22 | C8: -5.49 | D8: 20.54 | E8: 32.31 | F8: 3.44 | G8: -15.32 | H8: 19.24 | I8: 2.23 | J8: 8.15
A9: 营业总收入滚动环比增长(%) | B9: -19.55 | C9: 20.88 | D9: 20.97 | E9: -4.72 | F9: -29.77 | G9: 11 | H9: 13 | I9: 14.41 | J9: -21.71
A10: 归属净利润滚动环比增长(%) | B10: -44.61 | C10: 19.48 | D10: 56.81 | E10: 28.91 | F10: -62.2 | G10: 68.09 | H10: 36.19 | I10: 11.06 | J10: -63.84
A11: 扣非净利润滚动环比增长(%) | B11: -36.01 | C11: 11.33 | D11: 38.5 | E11: 35.02 | F11: -54.6 | G11: 41.99 | H11: 52.02 | I11: 5.56 | J11: -62.84
A13: 摊薄净资产收益率(%) | B13: 2.93 | C13: 5.54 | D13: 4.88 | E13: 3.12 | F13: 2.4 | G13: 6.63 | H13: 4.16 | I13: 3.03 | J13: 2.69
... A16: 净利率(%) | B16: 3.53 | C16: 5.1 | D16: 5.19 | E16: 4 | F16: 2.95 | G16: 5.49 | H16: 3.63 | I16: 3.02 | J16: 3.1
